Workbook

Sheet 需求概述
B1: 序号 | C1: 需求模块 | D1: 模块处理逻辑说明 | E1: 备注
B2: 1 | C2: 往来账龄模块
B3: 2 | C3: 坏账计算逻辑
B4: 3 | C4: 周转分析模块

Sheet 需求总览
B1: 序号 | C1: 需求分类 | D1: 需求小类 | E1: 需求点 | F1: 需求响应（满足/不满足） | G1: PRD文档位置（sheet页） | H1: PRD关键逻辑描述 | I1: 备注 | K1: 0908：后续沟通确认一个统一的梳理的模版
B2: 1 | C2: 维度映射 | D2: 一/二/三级公司分类 | E2: 往来账龄明细表、应收账款周转分析明细表新增【一/二/三级公司分类】字段，按客户主数据取值；营销客户主数据未上线公司（日立、商冷、激光、古洛尼、雅士高、显示基地、冰冷洗基地、空气基地、其他公司）字段置空 | F2: 满足 | G2: dwd_fi_mr_arap_detail_mi | H2: DWD层进行维度映射处理
B3: 2 | C3: 维度映射 | D3: 利润中心映射 | E3: 维护"老利润中心→新利润中心"映射关系；范围限于应收账款清账口径利润中心（《应收维度统计表-利润中心对应关系表（新）》）；涉及电商本次不清洗客户清单 | F3: 满足 | G3: dwd_fi_mr_arap_detail_mi | H3: DWD层进行维度映射处理
B4: 3 | C4: 维度映射 | D4: 渠道分组映射 | E4: 维护"一级/三级公司分类→渠道分组"映射（含下沉/零售/零售-传统零售/零售-新零售/转口贸易/外售）；按优先级：天猫优品/京东专卖/苏宁零售云映射下沉；一级=电商映射零售；一级≠电商映射零售-传统零售 | F4: 满足 | G4: dwd_fi_mr_arap_detail_mi | H4: DWD层进行维度映射处理
B5: 4 | C5: 维度新增 | D5: 业务范围 | E5: 坏账计提凭证入账、传输损益表新增【业务范围】字段；通用规则按《业务范围配置表》；特殊规则：6210 按三级性质映射、1180/12**按客户主数据二级公司分类、商用显示按国家-业务范围映射、日立按国家-大区映射 | F5: 满足 | G5: dwd_fi_mr_arap_detail_mi | H5: DWD层进行维度映射处理
B6: 5 | C6: 维度映射 | D6: 业务管理单元 | E6: 空气事业部管报新增【业务管理单元】字段：SAP600 通过利润中心映射、SAP700 默认 ZZZZ、SAP900 通过三级性质映射（煤改电/OEM/网络能源/其他） | F6: 满足 | G6: dwd_fi_mr_arap_detail_mi | H6: DWD层进行维度映射处理
B7: 6 | C7: 维度新增 | D7: 周转分析渠道 | E7: 应收账款周转分析明细表新增【一/二/三级渠道】字段；上线公司按"渠道分组"+二/三级公司分类映射，未上线公司（除日立、商冷特殊规则）默认缺省值 ZZZZ | F7: 满足 | G7: dwd_fi_mr_arap_detail_mi | H7: DWD层进行维度映射处理
B8: 7 | C8: 维度新增 | D8: MDG 商冷客户群映射 | E8: 6380、6797商冷三级渠道 → MDG【商冷客户群】映射 | F8: 待维度定标
B9: 8 | C9: D 表数据源新增 | D9: 应收账面数据源 | E9: D 表新增"①SAP 应收货款账面余额"字段：来源 SAP600/700/800/900/810（应收账款、合同资产、合同负债、其他应收款、长期应收款-信汇）； | F9: 满足 | G9: dwd_fi_mr_arap_detail_mi | H9: DWD层复刻SAPZZT003的逻辑取底表数据计算账龄天数
B10: 9 | C10: D 表数据源新增 | D10: 调整项数据源 | E10: "②期末出库未开（不含税）"：来源管报 2.0 收入出库未开底稿，仅涉及冰冷洗营销、空气营销；新增"③期末退货未办退税（不含税）"：来源管报 2.0 收入退货未办底稿，涉及冰冷洗营销、空气营销；账龄均放置在 1 个月以内 | F10: 满足 | G10: ARP001_STEP_1 | H10: 在M层直接取收入M01表中的出库和退货的数据
B11: 10 | C11: D 表数据源新增 | D11: 超期款数据源 | E11: D 表新增【超期金额】字段：来源财务中台-问题资金系统，按账套取客户+利润中心/客户超期款金额；显示/激光/冰冷/空气/古洛尼/厨卫事业部需分别确认范围与字段口径（含商显2080、冰冷商冷 6380/6797、空气日立1730-1761、维保、模具等明细） | F11: 满足 | G11: dwd_fi_mr_ar_overdue_mi | H11: 取财务中台-问题资金系统中超期款及开票样机的金额，以及超期款调整口的数据
B12: 11 | C12: D 表数据源新增 | D12: 返利数据源 | E12: D 表新增【已确认未兑现返利余额】：来源政策系统（显示/冰箱/空气营销）、SMS（日立）、FBL5N（SAP600 未清明细）；日立口径以 SMS经销商返利余额为准 | F12: 满足 | G12: dwd_fi_mr_ar_ureb_mi | H12: 取SMS系统、政策系统、SAP系统的欠付返利明细
B13: 12 | C13: D 表数据源新增 | D13: 欠付费用数据源 | E13: D 表新增【已账扣未报账欠付费用】：来源 SAP600，主要覆盖显示/冰冷/空气营销公司，账龄放置在 1 个月以内 | F13: 满足 | G13: ARP001_STEP_1 | H13: 将往来账龄及周转影响因素需要的数据聚合到计算底稿中，包括SAP的账龄明细、信汇明细、出库未开、退货未办、超期款数据、提前回款、电商零售节奏、欠付费用、欠付返利，通过数据分类字段区分开
B14: 12 | C14: D 表数据源新增 | D14: 提前回款数据源 | E14: 新增提前回款的取数逻辑，作为周转分析的影响因素 | F14: 满足 | G14: ARP001_STEP_1 | H14: 将往来账龄及周转影响因素需要的数据聚合到计算底稿中，包括SAP的账龄明细、信汇明细、出库未开、退货未办、超期款数据、提前回款、电商零售节奏、欠付费用、欠付返利，通过数据分类字段区分开
B15: 12 | C15: D 表数据源新增 | D15: 电商零售数据源 | E15: 新增电商销售零售的取数逻辑，作为周转分析的影响因素 | F15: 满足 | G15: ARP001_STEP_1 | H15: 将往来账龄及周转影响因素需要的数据聚合到计算底稿中，包括SAP的账龄明细、信汇明细、出库未开、退货未办、超期款数据、提前回款、电商零售节奏、欠付费用、欠付返利，通过数据分类字段区分开
B16: 13 | C16: D 表数据源新增 | D16: 核销金额数据源 | E16: D表新增财务中台核销金额数据源取数 | F16: 满足 | G16: dwd_fi_mr_ar_writeoff_mi | H16: 取财务中台中坏账核销单中的核销金额数据
B17: 14 | C17: D 表数据源新增 | D17: 国际营销占用数据源 | E17: D表新增国际营销占用取数 | F17: 满足 | G17: dwd_fi_mr_ar_imocc_mi | H17: 取信数系统中国际营销对外的的应收占用数据
B18: 15 | C18: D 表数据源新增 | D18: 账期数据源 | E18: D 表新增【账期】字段：取 SAP-KNB1 付款条件编码，通过 SAP-T052 解释 | F18: 满足 | G18: dwd_fi_mr_ar_cterm_md | H18: 根据SAP的客户主数据相关表单，匹配处理成每个客户的付款条件明细信息
B19: 16 | C19: D/M/S 表逻辑处理 | D19: 账龄进数范围限制 | G19: ARP001_STEP_2 | H19: 往来账龄需要对部分客商或科目等进行剔除，此步骤用于将步骤1取到的数据根据进数范围进行限制
B20: 17 | C20: D/M/S 表逻辑处理 | D20: 重分类 | E20: 法人口径重分类、管理口径重分类、分公司管理口径重分类三个口径的重分类判断规则 | F20: 满足 | G20: ARP001_STEP_3 | H20: 此步骤将往来账龄的数据根据重分类的规则进行重分类的判断，法人口径、管理口径、管理分公司口径三个口径的重分类处理，以及集团归属范围的判断
B21: 18 | C21: D/M/S 表逻辑处理 | D21: 合同负债税额剔除 | F21: 满足 | G21: ARP002_STEP_1 | H21: 此表将往来账龄计算底稿不同数据分类的数据平铺到列上展示，并且针对应收重分类到合同负债的数据，把对应的税额剔除
B22: 19 | C22: D/M/S 表逻辑处理 | D22: 坏账计提基数表 | E22: 指标=调整后应收账款，公式=①SAP 应收+②出库未开-③退货未办-④直销垫资-⑤保证金-⑥海外投保 | F22: 满足 | G22: ARP003_STEP_1 | H22: 将往来账龄表中涉及到需要计算坏账的数据取到坏账计算表中，根据管理分类和分公司分类不同生成两个口径的数据，并且匹配出坏账的调整项，如果有直销垫资的金额，用垫资的金额冲减坏账计提基数，优先从长账龄冲销，如果同一个客户存在负数的账龄金额，拆分到长账龄的区间中
B23: 20 | C23: D/M/S 表逻辑处理 | D23: 坏账计提基数调整优先级 | E23: 基数计算按"个别认定表（优先级1）> 投保信息录入表免赔额（优先级2）> 账龄表-手工调整项（优先级3）" | F23: 满足 | G23: ARP003_STEP_2 | H23: 根据不同的坏账计提规则计算坏账金额，如果有个别认定和煤改电，优先取对应的金额计提坏账，再按照优先级匹配坏账计提比例，根据坏账计提比例*坏账计提基数计算坏账金额，如果保障天数>0，需要再根据保障天数判断坏账计提区间，根据坏账计提比例*坏账计提基数*未覆盖比例计算坏账
B24: 21 | C24: D/M/S 表逻辑处理 | D24: 管理口径坏账计提 | E24: 调整后应收账款中预收余额利润中心使用先进先出法分配至账龄段，按账套+客户+利润中心计算坏账；预收利润中心坏账按"应收利润中心坏账金额/Σ同客户应收利润中心坏账金额"分摊至应收利润中心； | F24: 满足 | G24: ARP003_STEP_3 | H24: 针对坏账计算出来为负数的行项目，按照同一个公司+客户+科目计算正数行的比例，把负数的坏账金额分摊到正数行上
B25: 22 | C25: D/M/S 表逻辑处理 | D25: 应收占用指标重构 | E25: 应收占用=应收账款账面余额+期末出库未开-期末退货未办退税-集团内应收货款占用-虚拟售料外协厂应收余额-应收信汇占用-垫资款+管理口径跨事业部应收占用；剔除项含电视/空调对中国区挂外部户的70012338、虚拟售料外协厂、信汇（1122000095/1131000095）等 | F25: 满足 | G25: ARP004_STEP_1 | H25: 把往来账龄结果表的数据筛选出需要计算周转的应收占用数据，根据取数配置表中的限制进行数据的取数及剔除，以及将手工调整的影响因素也匹配到同一行数据中
B26: 24 | C26: D/M/S 表逻辑处理 | D26: 周转影响因素拆解 | E26: 周转分析表拆解 8 类影响因素：①超期款金额、②提前回款金额、③电商零售销售节奏、④已确认未兑现返利、⑤已账扣未报账欠付费用、⑥开票样机额度、⑦国补未回款影响、⑧手工导入因素 | F26: 满足 | G26: ARP004_STEP_1 | H26: 把往来账龄结果表的数据筛选出需要计算周转的应收占用数据，根据取数配置表中的限制进行数据的取数及剔除，以及将手工调整的影响因素也匹配到同一行数据中
B27: 25 | C27: D/M/S 表逻辑处理 | D27: 主营业务收入指标重构 | E27: 收入=开票收入+期末出库未开-期末退货未办退税-当月计提返利-集团内客户收入+管理口径跨事业部应收占用；剔除项含业绩调拨调入/调出、小 B 国补业务数据冲销/还原 | F27: 满足 | G27: ARP005_STEP_1 | H27: 把单体销售明细表的数据筛选出需要计算周转的收入数据，根据取数配置表中的限制进行数据的取数及剔除
B28: 23 | C28: D/M/S 表逻辑处理 | D28: 利润中心跨事业部拆分 | E28: 同一账套同一客户跨事业部时，只取拆分事业部后>0 的金额（如冰冷/洗护、显示/激光） | F28: 满足 | G28: ARP001_STEP_1 | H28: 将周转计算的占用和收入的M表匹配成一个表单，匹配出对应的事业部维度，将不符合条件的数据进行排除
B29: 24 | C29: D/M/S 表逻辑处理 | D29: 周转表-指标表维度映射 | E29: 周转表与指标表维度对应关系，作为指标表推送规则说明 | F29: 满足 | G29: ARP002_STEP_1 | H29: 根据配置表维护的周转口径的对应关系将指标表需要展示的周转口径的数据计算后同步到核心利润S表中
B30: 25 | C30: 展示报表需求 | D30: 期末汇率余额 | E30: D 表新增【期末汇率余额】【记账汇率余额】【汇率评估方式】【理论汇兑评估】字段，逻辑同管报 1.0
B31: 26 | C31: 展示报表需求 | D31: 调整后返利/退货 | E31: D 表新增【调整后返利】（冰箱专用，67**）与【调整后退货】（显示专用，26**/23**/1632）字段，由公式按应收账面余额与返利/退货余额比较后计算
B32: 27 | C32: 展示报表需求 | D32: 一级/二级/三级性质 | E32: 往来账龄明细表新增【一级/二级/三级性质】字段；一级/二级来源管报 1.0 配置表（B20_0101_02），三级手工填写并联动一级
B33: 28 | C33: 展示报表需求 | D33: 利润中心校验 | E33: 账龄表增加利润中心系统校验：原则上仅允许出现应收账款清账口径利润中心；出现新增利润中心时需提示，报表人调账处理
B34: 29 | C34: 展示报表需求 | D34: 账龄段颜色提示 | E34: 科目余额为正且出现负数账龄时，将负数账龄单元格标记特殊颜色
B35: 30 | C35: 展示报表需求 | D35: 余额三项校验 | E35: 管报 2.0 账龄表新增校验表，校验：①管报 1.0 账龄表、②管报 2.0 账龄表明细表、③管报 1.0 资产负债表科目余额
B36: 31 | C36: 展示报表需求 | D36: 客户/供应商冲突标记 | E36: 同一账套下既为客户又为供应商（名称相同）且本期余额不为 0 时，对应单元格标记颜色
B37: 32 | C37: 展示报表需求 | D37: 是否存续字段联动 | E37: 同一账套下【是否存续】字段填写后，结果附用至同客商（客户与供应商名称相同）
B38: 33 | C38: 展示报表需求 | D38: 应收账款周转分析表-事业部 | E38: 4.5.1：中国区、显示、激光、冰冷、洗护、空气、厨电、古洛尼、雅士高事业部层级周转指标（按账套+客户维度重分类）
B39: 34 | C39: 展示报表需求 | D39: 应收账款周转分析表-单体法人 | E39: 4.5.1：按账套维度出具应收账款周转指标（按账套+客户维度重分类）
B40: 35 | C40: 展示报表需求 | D40: 应收账款周转分析表-分公司 | E40: 4.5.1+4.5.3：电冰空等分公司层级周转指标（按账套+客户+利润中心加严口径），另含 S 表"应收账款周转分析展示表-分公司"

Sheet 0.0 ODS目录
B1: 入湖及数据更新情况列的统计时间是20260907 问题1：很多sap的表分了好几套，ODSS600/ODS_S600/ODSSLT_S600/ODS_SLT_S600，需要确定使用哪些表，需要每个表都确定 问题2：有些是空表，以及更新时间不是最新的 问题3：没有表的需要进行入湖 | K1: 高频抽数（月结）： 主数据类：1-6号，6点开始，每6小时一次 明细项类：1-6号，每小时一次 低频抽数： 其他日期，每日0点抽一次
C2: 黄底为入湖中的表 | I2: 统计日期为20260907 | K2: 抽数频率后续要统一查下，尤其SAP的账期明细变动相关表
B3: 分层 | C3: 编码 | D3: 数据库表名 | E3: 名称 | F3: 用途 | G3: 来源 | H3: 备注 | I3: 入湖及数据更新情况（load_dt为入湖规范中的数据入湖时间） | J3: 最终贴源表 | K3: 抽数调度任务 | L3: 入湖进度
B4: ods | C4: odss600_knb1 | D4: =B4&"."&C4 | E4: 公司客户主数据 | F4: 取客户对应的账期 | G4: SAP | I4: 最新load_dt为20260907 | L4: 无
B5: ods | C5: odss700_knb1 | D5: =B5&"."&C5 | E5: 公司客户主数据 | F5: 取客户对应的账期 | G5: SAP | I5: 最新load_dt为20260907 | L5: 无
B6: ods | C6: odss800_knb1 | D6: =B6&"."&C6 | E6: 公司客户主数据 | F6: 取客户对应的账期 | G6: SAP | I6: 最新load_dt为20260907 | L6: 无
B7: ods | C7: odss900_knb1 | D7: =B7&"."&C7 | E7: 公司客户主数据 | F7: 取客户对应的账期 | G7: SAP | I7: 最新load_dt为20260907 | L7: 无
B8: ods | C8: odss610_knb1 | D8: =B8&"."&C8 | E8: 公司客户主数据 | F8: 取客户对应的账期 | G8: SAP | I8: 最新load_dt为20260907 | L8: 无
B9: ods | C9: odss810_knb1 | D9: =B9&"."&C9 | E9: 公司客户主数据 | F9: 取客户对应的账期 | G9: SAP | I9: 最新load_dt为20260907 | L9: 无
B10: ods | C10: odss600_t052u | D10: =B10&"."&C10 | E10: 付款条件主数据 | F10: 取客户对应的账期 | G10: SAP | H10: 需要统一提一下入湖工单，让大数据团队进行数据入湖 | I10: 空表 | J10: odss600_t052u | K10: 离线任务名：ds1182_ODSS600_T052U 自动调度名：DS_S600@D_1-31_0抽数来源：EDW_STG--STG.S600_T052U | L10: 抽数调度已配，DORIS已查询到当日数据
B11: ods | C11: odss700_t052u | D11: =B11&"."&C11 | E11: 付款条件主数据 | F11: 取客户对应的账期 | G11: SAP | H11: 需要统一提一下入湖工单，让大数据团队进行数据入湖 | I11: 空表 | J11: odss700_t052u | K11: 离线任务名：ds5765_ODSS700_T052U 自动调度名：DS_S700@D_1-31_0抽数来源：EDW_STG--STG.S700_T052U | L11: 抽数调度已配，DORIS已查询到当日数据
B12: ods | C12: odss800_t052u | D12: =B12&"."&C12 | E12: 付款条件主数据 | F12: 取客户对应的账期 | G12: SAP | H12: 需要统一提一下入湖工单，让大数据团队进行数据入湖 | I12: 空表 | J12: odss800_t052u | K12: 离线任务名：ds4873_ODSS800_T052U 自动调度名：DS_S800@D_1-31_0抽数来源：EDW_STG--STG.S800_T052U | L12: 抽数调度已配，最新数为当日8点抽取
B13: ods | C13: odss900_t052u | D13: =B13&"."&C13 | E13: 付款条件主数据 | F13: 取客户对应的账期 | G13: SAP | H13: 需要统一提一下入湖工单，让大数据团队进行数据入湖 | I13: 空表 | K13: 离线任务名：ds6769_ODSS900_T052U 自动调度名：DS_S900@D_1-31_0抽数来源：EDW_STG--STG.S900_T052U | L13: 入湖流程中
B14: ods | C14: odss610_t052u | D14: =B14&"."&C14 | E14: 付款条件主数据 | F14: 取客户对应的账期 | G14: SAP | H14: 需要统一提一下入湖工单，让大数据团队进行数据入湖 | I14: 没有表 | J14: odss610_t052u | K14: 无 | L14: 抽数调度已配，DORIS已查询到当日数据
B15: ods | C15: odss810_t052u | D15: =B15&"."&C15 | E15: 付款条件主数据 | F15: 取客户对应的账期 | G15: SAP | H15: 需要统一提一下入湖工单，让大数据团队进行数据入湖 | I15: 最新load_dt为20260730 | J15: odss810_t052u | K15: 无 | L15: 抽数调度已配，DORIS已查询到当日数据
B16: ods | C16: odsslt_s600_bsid | D16: =B16&"."&C16 | E16: 客户‌未清‌项表 | F16: 计算客户对应的应收账龄明细 | G16: SAP | I16: 最新load_dt为20260907 | L16: 无
B17: ods | C17: odsslt_s600_bsad | D17: =B17&"."&C17 | E17: 客户‌已清‌项表 | F17: 计算客户对应的应收账龄明细 | G17: SAP | I17: 最新load_dt为20260907 | L17: 无
B18: ods | C18: odsslt_s600_bsik | D18: =B18&"."&C18 | E18: 供应商‌未清‌项表 | F18: 计算供应商对应的应收账龄明细 | G18: SAP | I18: 最新load_dt为20260907 | L18: 无
B19: ods | C19: odsslt_s600_bsak | D19: =B19&"."&C19 | E19: 供应商‌已清‌项表 | F19: 计算供应商对应的应收账龄明细 | G19: SAP | I19: 最新load_dt为20260907 | L19: 无
B20: ods | C20: odss600_lfa1 | D20: =B20&"."&C20 | E20: 供应商主数据 | G20: SAP | I20: 最新load_dt为20260907 | L20: 无
B21: ods | C21: ods_slt_s600_kna1 | D21: =B21&"."&C21 | E21: 客户主数据 | G21: SAP | I21: 最新load_dt为20260907 | L21: 无
B22: ods | C22: odsslt_s610_bsid | D22: =B22&"."&C22 | E22: 客户‌未清‌项表 | F22: 计算客户对应的应收账龄明细 | G22: SAP | H22: 如果要用610系统的SLT表，直接从810的SLT表取值即可，mandt='610' | I22: 没有表，只有ods.odss600_bsid且为空表
B23: ods | C23: odsslt_s610_bsad | D23: =B23&"."&C23 | E23: 客户‌已清‌项表 | F23: 计算客户对应的应收账龄明细 | G23: SAP | H23: 如果要用610系统的SLT表，直接从810的SLT表取值即可，mandt='610' | I23: 没有表，只有ods.odss600_bsad且为空表
B24: ods | C24: odsslt_s610_bsik | D24: =B24&"."&C24 | E24: 供应商‌未清‌项表 | F24: 计算供应商对应的应收账龄明细 | G24: SAP | H24: 如果要用610系统的SLT表，直接从810的SLT表取值即可，mandt='610' | I24: 没有表，只有ods.odss600_bsik且为空表
B25: ods | C25: odsslt_s610_bsak | D25: =B25&"."&C25 | E25: 供应商‌已清‌项表 | F25: 计算供应商对应的应收账龄明细 | G25: SAP | H25: 如果要用610系统的SLT表，直接从810的SLT表取值即可，mandt='610' | I25: 没有表，只有ods.odss600_bsak且为空表
B26: ods | C26: odss610_lfa1 | D26: =B26&"."&C26 | E26: 供应商主数据 | G26: SAP | H26: 需要统一提一下入湖工单，让大数据团队进行数据入湖 | I26: 最新load_dt为20260906 | J26: odss610_lfa1 | K26: 离线任务名：ds251_ODSS610_LFA1 自动调度名：PUB_S610@D_1-31_22抽数来源：EDW_STG--stg.S610_LFA1 | L26: 抽数调度已配，DORIS已查询到当日数据
B27: ods | C27: ods_slt_s610_kna1 | D27: =B27&"."&C27 | E27: 客户主数据 | G27: SAP | H27: 如果要用610系统的SLT表，直接从810的SLT表取值即可，mandt='610' | I27: 没有表，只有odss610_kna1且最新load_dt为20260907
B28: ods | C28: odsslt_s700_bsid | D28: =B28&"."&C28 | E28: 客户‌未清‌项表 | F28: 计算客户对应的应收账龄明细 | G28: SAP | I28: 最新load_dt为20260907 | L28: 无
B29: ods | C29: odsslt_s700_bsad | D29: =B29&"."&C29 | E29: 客户‌已清‌项表 | F29: 计算客户对应的应收账龄明细 | G29: SAP | I29: 最新load_dt为20260907 | L29: 无
B30: ods | C30: odsslt_s700_bsik | D30: =B30&"."&C30 | E30: 供应商‌未清‌项表 | F30: 计算供应商对应的应收账龄明细 | G30: SAP | I30: 最新load_dt为20260907 | L30: 无
B31: ods | C31: odsslt_s700_bsak | D31: =B31&"."&C31 | E31: 供应商‌已清‌项表 | F31: 计算供应商对应的应收账龄明细 | G31: SAP | I31: 最新load_dt为20260907 | L31: 无
B32: ods | C32: odss700_lfa1 | D32: =B32&"."&C32 | E32: 供应商主数据 | G32: SAP | I32: 最新load_dt为20260907 | L32: 无
B33: ods | C33: ods_slt_s700_kna1 | D33: =B33&"."&C33 | E33: 客户主数据 | G33: SAP | I33: 最新load_dt为20260907 | L33: 无
B34: ods | C34: odsslt_s800_bsid | D34: =B34&"."&C34 | E34: 客户‌未清‌项表 | F34: 计算客户对应的应收账龄明细 | G34: SAP | I34: 最新load_dt为20260907 | L34: 无
B35: ods | C35: odsslt_s800_bsad | D35: =B35&"."&C35 | E35: 客户‌已清‌项表 | F35: 计算客户对应的应收账龄明细 | G35: SAP | I35: 最新load_dt为20260907 | L35: 无
B36: ods | C36: odsslt_s800_bsik | D36: =B36&"."&C36 | E36: 供应商‌未清‌项表 | F36: 计算供应商对应的应收账龄明细 | G36: SAP | H36: 需要统一提一下入湖工单，让大数据团队进行数据入湖 | I36: 没有表，只有odss800_bsik且最新load_dt为20260907 | J36: odss800_bsik | K36: 离线任务名：ds1414_ODSS800_BSIK 自动调度名：PUB_S800@D_1-31_22、DS_S800@D_1-31_0抽数来源：EDW_STG--STG.S800_BSIK | L36: 调度已配置，最新数为21日0点抽取
B37: ods | C37: odsslt_s800_bsak | D37: =B37&"."&C37 | E37: 供应商‌已清‌项表 | F37: 计算供应商对应的应收账龄明细 | G37: SAP | I37: 最新load_dt为20260907 | L37: 无
B38: ods | C38: odss800_lfa1 | D38: =B38&"."&C38 | E38: 供应商主数据 | G38: SAP | I38: 最新load_dt为20260907 | L38: 无
B39: ods | C39: ods_slt_s800_kna1 | D39: =B39&"."&C39 | E39: 客户主数据 | G39: SAP | H39: 需要统一提一下入湖工单，让大数据团队进行数据入湖 | I39: 没有表，只有odss800_kna1且最新load_dt为20260907 | J39: odss800_kna1 | K39: 离线任务名：py_ODSS800_KNA1_2ds 自动调度名：DS_S800@D_1-31_0、S800@H2_L1-6_2抽数来源：EDW_STG--STG.S800_KNA1 | L39: 入湖流程中，ods_slt_s800b_kna1已有当日数据，但比odss800_kna1少记录数
B40: ods | C40: odsslt_s810_bsid | D40: =B40&"."&C40 | E40: 客户‌未清‌项表 | F40: 计算客户对应的应收账龄明细 | G40: SAP | I40: 最新load_dt为20260907 | L40: 无
B41: ods | C41: odsslt_s810_bsad | D41: =B41&"."&C41 | E41: 客户‌已清‌项表 | F41: 计算客户对应的应收账龄明细 | G41: SAP | I41: 最新load_dt为20260907 | L41: 无
B42: ods | C42: odsslt_s810_bsik | D42: =B42&"."&C42 | E42: 供应商‌未清‌项表 | F42: 计算供应商对应的应收账龄明细 | G42: SAP | I42: 最新load_dt为20260907 | L42: 无
B43: ods | C43: odsslt_s810_bsak | D43: =B43&"."&C43 | E43: 供应商‌已清‌项表 | F43: 计算供应商对应的应收账龄明细 | G43: SAP | H43: 需要统一提一下入湖工单，让大数据团队进行数据入湖 | I43: 没有表，只有ods.odss810_bsak且为空表 | J43: odsslt_s810_bsak | K43: 无 | L43: 抽数调度已配，DORIS已查询到当日数据
B44: ods | C44: odss810_lfa1 | D44: =B44&"."&C44 | E44: 供应商主数据 | G44: SAP | H44: 需要统一提一下入湖工单，让大数据团队进行数据入湖 | I44: 最新load_dt为20260906（当前数据更新在15点多） | J44: odsS810_LFA1 | K44: 离线任务名：ds281_ODSS810_LFA1 自动调度名：PUB_S810@D_1-31_22抽数来源：EDW_STG--stg.S810_LFA1 | L44: 抽数调度已配置，22日验证
B45: ods | C45: ods_slt_s810_kna1 | D45: =B45&"."&C45 | E45: 客户主数据 | G45: SAP | I45: 最新load_dt为20260907 | L45: 无
B46: ods | C46: odsslt_s900_bsid | D46: =B46&"."&C46 | E46: 客户‌未清‌项表 | F46: 计算客户对应的应收账龄明细 | G46: SAP | I46: 最新load_dt为20260907 | L46: 无
B47: ods | C47: odsslt_s900_bsad | D47: =B47&"."&C47 | E47: 客户‌已清‌项表 | F47: 计算客户对应的应收账龄明细 | G47: SAP | I47: 最新load_dt为20260907 | L47: 无
B48: ods | C48: odsslt_s900_bsik | D48: =B48&"."&C48 | E48: 供应商‌未清‌项表 | F48: 计算供应商对应的应收账龄明细 | G48: SAP | H48: 使用ods.odss900_bsik表，需要统一提一下入湖工单，让大数据团队进行数据入湖 | I48: 没有表，只有ods.odss900_bsik且为空表 | J48: odss900_bsik | K48: 离线任务名：py_ODSS900_BSIK_2ds 自动调度名：DS_S900@D_1-31_0抽数来源：EDW_STG--STG.S900_BSIK | L48: 调度已配置，最新数为21日0点抽取
B49: ods | C49: odsslt_s900_bsak | D49: =B49&"."&C49 | E49: 供应商‌已清‌项表 | F49: 计算供应商对应的应收账龄明细 | G49: SAP | I49: 最新load_dt为20260907 | L49: 无
B50: ods | C50: odss900_lfa1 | D50: =B50&"."&C50 | E50: 供应商主数据 | G50: SAP | I50: 最新load_dt为20260907 | L50: 无
B51: ods | C51: ods_slt_s900_kna1 | D51: =B51&"."&C51 | E51: 客户主数据 | G51: SAP | I51: 最新load_dt为20260907 | L51: 无
B52: ods | C52: odss600_ztzt_003 | D52: =B52&"."&C52 | E52: zzt003配置表 | G52: SAP | I52: 最新load_dt为20260907 | L52: 无
B53: ods | C53: odss610_ztzt_003 | D53: =B53&"."&C53 | E53: zzt003配置表 | G53: SAP | I53: 最新load_dt为20260907 | L53: 无
B54: ods | C54: odss700_ztzt_003 | D54: =B54&"."&C54 | E54: zzt003配置表 | G54: SAP | I54: 最新load_dt为20260907 | L54: 无
B55: ods | C55: odss800_ztzt_003 | D55: =B55&"."&C55 | E55: zzt003配置表 | G55: SAP | I55: 最新load_dt为20260907 | L55: 无
B56: ods | C56: odss810_ztzt_003 | D56: =B56&"."&C56 | E56: zzt003配置表 | G56: SAP | I56: 最新load_dt为20260907 | L56: 无
B57: ods | C57: odss900_ztzt_003 | D57: =B57&"."&C57 | E57: zzt003配置表 | G57: SAP | I57: 最新load_dt为20260907 | L57: 无
B58: ods | C58: odss600_t001 | D58: =B58&"."&C58 | E58: 公司编码 | G58: SAP | I58: 最新load_dt为20260907 | L58: 无
B59: ods | C59: odss610_t001 | D59: =B59&"."&C59 | E59: 公司编码 | G59: SAP | H59: 需要统一提一下入湖工单，让大数据团队进行数据入湖 | I59: 没有表 | J59: odss610_t001 | K59: 无 | L59: 抽数调度已配，DORIS已查询到当日数据
B60: ods | C60: odss700_t001 | D60: =B60&"."&C60 | E60: 公司编码 | G60: SAP | I60: 最新load_dt为20260907 | L60: 无
B61: ods | C61: odss800_t001 | D61: =B61&"."&C61 | E61: 公司编码 | G61: SAP | I61: 最新load_dt为20260907 | L61: 无
B62: ods | C62: odss810_t001 | D62: =B62&"."&C62 | E62: 公司编码 | G62: SAP | I62: 最新load_dt为20260907 | L62: 无
B63: ods | C63: odss900_t001 | D63: =B63&"."&C63 | E63: 公司编码 | G63: SAP | I63: 最新load_dt为20260907 | L63: 无
B64: ods | C64: odss600_skb1 | D64: =B64&"."&C64 | E64: 总账科目主记录（公司代码） | G64: SAP | I64: 最新load_dt为20260907 | L64: 无
B65: ods | C65: odss610_skb1 | D65: =B65&"."&C65 | E65: 总账科目主记录（公司代码） | G65: SAP | H65: 需要统一提一下入湖工单，让大数据团队进行数据入湖 | I65: 空表 | J65: odss610_skb1 | K65: 无 | L65: 抽数调度已配，DORIS已查询到当日数据
B66: ods | C66: odss700_skb1 | D66: =B66&"."&C66 | E66: 总账科目主记录（公司代码） | G66: SAP | I66: 最新load_dt为20260907 | L66: 无
B67: ods | C67: odss800_skb1 | D67: =B67&"."&C67 | E67: 总账科目主记录（公司代码） | G67: SAP | I67: 最新load_dt为20260907 | L67: 无
B68: ods | C68: odss810_skb1 | D68: =B68&"."&C68 | E68: 总账科目主记录（公司代码） | G68: SAP | H68: 需要统一提一下入湖工单，让大数据团队进行数据入湖 | I68: 空表 | J68: odss810_skb1 | K68: 无 | L68: 抽数调度已配置，22日验证
B69: ods | C69: odss900_skb1 | D69: =B69&"."&C69 | E69: 总账科目主记录（公司代码） | G69: SAP | I69: 最新load_dt为20260907 | L69: 无
B70: ods | C70: odss600_cepct | D70: =B70&"."&C70 | E70: 利润中心主数据文本 | G70: SAP | I70: 最新load_dt为20260907 | L70: 无
B71: ods | C71: odss610_cepct | D71: =B71&"."&C71 | E71: 利润中心主数据文本 | G71: SAP | H71: 需要统一提一下入湖工单，让大数据团队进行数据入湖 | I71: 没有表 | J71: odss610_cepct | K71: 无 | L71: 抽数调度已配，DORIS已查询到当日数据
B72: ods | C72: odss700_cepct | D72: =B72&"."&C72 | E72: 利润中心主数据文本 | G72: SAP | I72: 最新load_dt为20260907 | L72: 无
B73: ods | C73: odss800_cepct | D73: =B73&"."&C73 | E73: 利润中心主数据文本 | G73: SAP | I73: 最新load_dt为20260907 | L73: 无
B74: ods | C74: odss810_cepct | D74: =B74&"."&C74 | E74: 利润中心主数据文本 | G74: SAP | H74: 需要统一提一下入湖工单，让大数据团队进行数据入湖 | I74: 最新load_dt为20260813 | J74: odss810_cepct | K74: 离线任务名：py_ODSS810_CEPCT_2ds 自动调度名：S810@D_1-31_2、S810@D_1-31_15抽数来源：EDW_STG--STG.S810_CEPCT | L74: 抽数调度已配，DORIS已查询到当日数据，但mandt字段为空
B75: ods | C75: odss900_cepct | D75: =B75&"."&C75 | E75: 利润中心主数据文本 | G75: SAP | I75: 最新load_dt为20260907 | L75: 无
B76: ods | C76: ods_slt_s600_faglflext | D76: =B76&"."&C76 | E76: 科目余额表 | G76: SAP | I76: 最新load_dt为20260907 | L76: 无
B77: ods | C77: ods_slt_s700_faglflext | D77: =B77&"."&C77 | E77: 科目余额表 | G77: SAP | I77: 最新load_dt为20260907 | L77: 无
B78: ods | C78: ods_slt_s800_glfunct | D78: =B78&"."&C78 | E78: 科目余额表 | G78: SAP | I78: 最新load_dt为20260907 | L78: 无
B79: ods | C79: ods_slt_s810_faglflext | D79: =B79&"."&C79 | E79: 科目余额表 | G79: SAP | H79: 如果要用610系统的SLT表，直接从810的SLT表取值即可，mandt='610' | I79: 最新load_dt为20260413
B80: ods | C80: ods_slt_s900_glfunct | D80: =B80&"."&C80 | E80: 科目余额表 | G80: SAP | I80: 最新load_dt为20260907 | L80: 无
B81: dw | C81: dim_customer_base_info_dd | D81: =B81&"."&C81 | E81: MDG客户主数据 | G81: MDG | I81: 最新load_dt为20260907 | L81: 无
B82: dim | C82: dim_rule_fi_mr_acct_mapping | D82: =B82&"."&C82 | E82: 科目映射表 | G82: 规则库 | I82: 规则库只要发布实时更新数据
B83: dim | C83: dim_rule_fi_mr_cust2ctp_mapping | D83: =B83&"."&C83 | E83: 对方公司映射 | G83: 规则库 | I83: 规则库只要发布实时更新数据
B84: dim | C84: dim_rule_fi_mr_ar_onoffline_map | D84: =B84&"."&C84 | E84: 经分项目应收模块-渠道分组映射表 | G84: 规则库 | I84: 规则库只要发布实时更新数据
B85: dim | C85: dim.dim_rule_fi_mr_nf_mapping | D85: =B85&"."&C85 | E85: 经分项目收入模块规则映射表 | G85: 规则库 | I85: 规则库只要发布实时更新数据
B86: dim | C86: dim_rule_fi_mr_ar_prctr_map | D86: =B86&"."&C86 | E86: 经分项目应收模块-利润中心映射表 | G86: 规则库 | I86: 规则库只要发布实时更新数据
B87: ods | C87: odsfima_azienda | D87: =B87&"."&C87 | E87: 经分公司主数据 | G87: 经分1.0 | I87: 最新load_dt为20260907 | L87: 无
A88: select * from | B88: ods | C88: odsmt_fin_bill_view_data | D88: =B88&"."&C88 | E88: 信汇明细表 | G88: 信汇系统 | H88: 时点数，每月抽取一次 | I88: 最新load_dt为20260901 | M88: 月末时点？
B89: ods | C89: odsmr_ztab_9000_acct_maping | D89: =B89&"."&C89 | E89: 内部公司账号 | G89: 管报 | I89: oracle跨用户访问实时数据
B90: dws | C90: dws_fi_mr_ar_overdue_mi | D90: =B90&"."&C90 | E90: 超期款明细表 | G90: 问题资金系统 | I90: 空表
B91: ods | C91: odsfipf_tk_hfi_jtb_bjtwtzjtz | D91: =B91&"."&C91 | E91: 问题资金手工调整项 | I91: 没有load_dt字段 | M91: 问题资金已换接口表
B92: dw | C92: dwd_ltc_cem_reportpay_balance_summary_dd | D92: =B92&"."&C92 | E92: 经销商返利余额汇总管理表 | F92: 计算欠付返利金额 | G92: SMS | H92: 1号0点抽1次，转存为上月末；上线前历史月份用户录入 | I92: 没有load_dt字段 | L92: 如果需要增加load_dt字段，是管报加，还是需要原系统加？
B93: dwd | C93: dwd_mrs_mc_report_reward_account_detail_new_hi | E93: 政策系统欠付返利余额 | G93: 政策
B94: ads | C94: ads_fi_mr_accounts_rec_di | D94: =B94&"."&C94 | E94: 国际营销占用明细表 | G94: 信数系统 | I94: 最新load_dt为20260907 | L94: 无
B95: dw | C95: dwsd_im_td_bdr_area_group | D95: =B95&"."&C95 | E95: 区组主数据 | G95: 信数系统 | I95: 最新load_dt为20260907 | L95: 无
B96: dw | C96: dwfi_im_td_product_category | D96: =B96&"."&C96 | E96: 产品线主数据 | G96: 信数系统 | I96: 最新load_dt为20260907 | L96: 无
B97: ods | C97: odsmf_cm_tab1065 | D97: =B97&"."&C97 | E97: 客户账期主数据 | G97: 信数系统 | H97: 数据更新的起始时间问题 | I97: 最新load_dt为20260906
B98: ods | C98: odsfmfi_t_bd_period | D98: =B98&"."&C98 | E98: 期间主数据 | G98: 财务中台 | I98: 最新load_dt为20260907 | L98: 无
B99: ods | C99: odsfmtss_t_org_org | D99: =B99&"."&C99 | E99: 公司主数据 | G99: 财务中台 | I99: 最新load_dt为20260907 | L99: 无
B100: ods | C100: odsfmfi_t_bd_account | D100: =B100&"."&C100 | E100: 科目主数据 | G100: 财务中台 | I100: 最新load_dt为20260907 | L100: 无
...

Sheet ods表详情
A1: 表名 | B1: 表字段名 | C1: 字段描述
A2: odss600_kna1 | B2: mandt | C2: 客户端
A3: odss600_kna1 | B3: kunnr | C3: 客户编号
A4: odss600_kna1 | B4: land1 | C4: 国家代码
A5: odss600_kna1 | B5: name1 | C5: 名称11
A6: odss600_kna1 | B6: name2 | C6: 名称21
A7: odss600_kna1 | B7: ort01 | C7: 城市
A8: odss600_kna1 | B8: pstlz | C8: 邮政编码
A9: odss600_kna1 | B9: regio | C9: 地区（省/自治区/直辖市、市、县）
A10: odss600_kna1 | B10: sortl | C10: 排序字段
A11: odss600_kna1 | B11: stras | C11: 住宅号及街道
A12: odss600_kna1 | B12: telf1 | C12: 第一个电话号
... A170: odss600_kna1 | B170: psoo5 | C170: 描述1
A171: odss600_kna1 | B171: load_dt
A172: odss600_kna1 | B172: zkunnr_mdg | C172: MDG客户编码
A173: odss600_kna1 | B173: zname1_mdg | C173: MDG客户名称
A174: odss600_kna1 | B174: zname3_mdg | C174: MDG英文名称
A175: odss600_kna1 | B175: zzcvco
A176: odss600_knb1 | B176: mandt | C176: 客户端
A177: odss600_knb1 | B177: kunnr | C177: 客户编号
A178: odss600_knb1 | B178: bukrs | C178: 公司代码
A179: odss600_knb1 | B179: pernr | C179: 人员编号
A180: odss600_knb1 | B180: erdat | C180: 记录创建日期
A181: odss600_knb1 | B181: ernam | C181: 创建对象的人员名称
A182: odss600_knb1 | B182: sperr | C182: 对公司代码过帐冻结
A183: odss600_knb1 | B183: loevm | C183: 主记录删除标记(公司代码级)
A184: odss600_knb1 | B184: zuawa | C184: 根据分配号排序代码
A185: odss600_knb1 | B185: busab | C185: 会计职员
A186: odss600_knb1 | B186: akont | C186: 总帐中的统驭科目
A187: odss600_knb1 | B187: begru | C187: 权限组
... A252: odss600_knb1 | B252: gmvkzd | C252: 正在执行客户
A253: odss600_knb1 | B253: load_dt
A254: odss600_t052u | B254: mandt | C254: 客户端
A255: odss600_t052u | B255: spras | C255: 语言代码
A256: odss600_t052u | B256: zterm | C256: 付款条件代码
A257: odss600_t052u | B257: ztagg | C257: 天数限制
A258: odss600_t052u | B258: text1 | C258: 收付条款的自解释
A259: odss600_t052u | B259: load_dt
A260: odss600_bsid | B260: mandt | C260: 客户端
A261: odss600_bsid | B261: bukrs | C261: 公司代码
A262: odss600_bsid | B262: kunnr | C262: 客户编号
A263: odss600_bsid | B263: umsks | C263: 特殊总分类帐事务类型
A264: odss600_bsid | B264: umskz | C264: 特殊总帐标识
A265: odss600_bsid | B265: augdt | C265: 清帐日期
A266: odss600_bsid | B266: augbl | C266: 清算单据的单据号码
A267: odss600_bsid | B267: zuonr | C267: 分配编号
A268: odss600_bsid | B268: gjahr | C268: 财年
A269: odss600_bsid | B269: belnr | C269: 会计凭证编号
A270: odss600_bsid | B270: buzei | C270: 会计凭证中的行项目数
A271: odss600_bsid | B271: budat | C271: 凭证中的过账日期
... A438: odss600_bsid | B438: propmano | C438: 托管，托管启动合同
A439: odss600_bsid | B439: load_dt
A440: odss610_bsid | B440: mandt | C440: 客户端
A441: odss610_bsid | B441: bukrs | C441: 公司代码
A442: odss610_bsid | B442: kunnr | C442: 客户编号
A443: odss610_bsid | B443: umsks | C443: 特殊总分类帐事务类型
A444: odss610_bsid | B444: umskz | C444: 特殊总帐标识
A445: odss610_bsid | B445: augdt | C445: 清帐日期
A446: odss610_bsid | B446: augbl | C446: 清算单据的单据号码
A447: odss610_bsid | B447: zuonr | C447: 分配编号
A448: odss610_bsid | B448: gjahr | C448: 财年
A449: odss610_bsid | B449: belnr | C449: 会计凭证编号
A450: odss610_bsid | B450: buzei | C450: 会计凭证中的行项目数
A451: odss610_bsid | B451: budat | C451: 凭证中的过账日期
... A614: odss610_bsid | B614: propmano | C614: 托管，托管启动合同
A615: odss610_bsid | B615: load_dt
A616: odss700_bsid | B616: mandt | C616: 客户端
A617: odss700_bsid | B617: bukrs | C617: 公司代码
A618: odss700_bsid | B618: kunnr | C618: 客户编号1
A619: odss700_bsid | B619: umsks | C619: 特殊总分类帐事务类型
A620: odss700_bsid | B620: umskz | C620: 特殊G/L标识
A621: odss700_bsid | B621: augdt | C621: 清帐日期
A622: odss700_bsid | B622: augbl | C622: 清算单据的单据号码
A623: odss700_bsid | B623: zuonr | C623: 分配编号
A624: odss700_bsid | B624: gjahr | C624: 会计年度
A625: odss700_bsid | B625: belnr | C625: 会计凭证编号
A626: odss700_bsid | B626: buzei | C626: 会计凭证中的行项目数
A627: odss700_bsid | B627: budat | C627: 凭证中的过帐日期
... A790: odss700_bsid | B790: propmano | C790: Mandat,mandatser?ffnenderVertrag
A791: odss700_bsid | B791: load_dt
A792: odss800_bsid | B792: mandt | C792: 集团
A793: odss800_bsid | B793: bukrs | C793: 公司代码
A794: odss800_bsid | B794: kunnr | C794: 客户编号1
A795: odss800_bsid | B795: umsks | C795: 特定总帐事务类型
A796: odss800_bsid | B796: umskz | C796: 特别总帐标识
A797: odss800_bsid | B797: augdt | C797: 清帐日期
A798: odss800_bsid | B798: augbl | C798: 清算单据的单据号码
A799: odss800_bsid | B799: zuonr | C799: 分配编号
A800: odss800_bsid | B800: gjahr | C800: 会计年度
A801: odss800_bsid | B801: belnr | C801: 会计凭证号码
A802: odss800_bsid | B802: buzei | C802: 会计凭证中的行项目数
A803: odss800_bsid | B803: budat | C803: 凭证中的记帐日期
... A964: odss800_bsid | B964: btype | C964: 开票标志
A965: odss800_bsid | B965: load_dt
A966: odss800b_bsid | B966: mandt | C966: 客户端
A967: odss800b_bsid | B967: bukrs | C967: 公司代码
A968: odss800b_bsid | B968: kunnr | C968: 客户编号1
A969: odss800b_bsid | B969: umsks | C969: 特殊总分类帐事务类型
A970: odss800b_bsid | B970: umskz | C970: 特殊总帐标识
A971: odss800b_bsid | B971: augdt | C971: 清帐日期
...

Sheet 1. DWD逻辑处理--》》

Sheet 1. 0 DWD层目录
B1: DWD层
B3: 编码 | C3: 名称 | D3: 处理逻辑 | E3: MRD需求 | F3: 表单所属层级 | G3: 来源
B4: dwd_fi_mr_ar_cterm_md | C4: 客户账期明细表 | D4: 根据SAP的客户主数据相关表单，匹配处理成每个客户的付款条件明细信息 | E4: 账期取数 | F4: DWD-标准层 | G4: S600,700,800,900,610,810 | H4: 0908：目前数据是实时的，如果重新出表会按最新的主数据来匹配
B5: dwd_fi_mr_arap_detail_mi | C5: 往来账龄明细表 | D5: 根据SAP的底表处理到凭证编码的行项目明细，计算每行数据的账龄天数，并对维度进行映射处理 | E5: 往来账龄取数 | F5: DWD-标准层 | G5: S600,700,800,900,610,810
B6: dwd_fi_mr_arap_sum_mi | C6: 往来账龄汇总表 | D6: 根据detail的明细表单将数据进行聚合，不到凭证行项目，减少数据量，并且将信汇系统、超期款、欠付返利的数据聚合到一个表单中 | F6: DWD-汇总层
B7: dwd_fi_mr_ar_overdue_mi | C7: 超期款明细表 | D7: 取财务中台-问题资金系统中超期款及开票样机的金额，以及超期款调整口的数据 | E7: 超期金额取数 | F7: DWD-标准层 | G7: 财务中台-问题资金系统
B8: dwd_fi_mr_ar_ureb_mi | C8: 欠付返利明细表 | D8: 取SMS系统、政策系统、SAP系统的欠付返利明细 | E8: 返利余额取数 | F8: DWD-标准层 | G8: SMS系统、政策系统
B9: dwd_fi_mr_ar_imocc_mi | C9: 国际营销应收占用明细表 | D9: 取信数系统中国际营销对外的的应收占用数据 | E9: 应收占用-国际营销取数 | F9: DWD-标准层 | G9: 信数系统
B10: dwd_fi_mr_ar_writeoff_mi | C10: 核销金额明细表 | D10: 取财务中台中坏账核销单中的核销金额数据 | E10: 核销金额取数 | F10: DWD-标准层 | G10: 财务中台

Sheet dwd_fi_mr_ar_cterm_md
A1: 返回 | B1: dwd_fi_mr_ar_cterm_md逻辑处理
A2: 规则库 | B2: 表名称 | C2: dwd.dwd_fi_mr_ar_cterm_md
B3: 表描述 | C3: 客户账期明细表 | D3: 表类型 | E3: 事实表 | F3: 数仓分层 | G3: DWD
B4: L1数仓目录 | C4: 管理财经 | D4: L2数仓目录 | E4: 财报管理 | F4: L3数仓目录 | G4: 应收
B5: 更新方式 | C5: 全量更新 | D5: 设计人员 | F5: 时间
B6: 使用场景 | C6: 根据SAP的客户主数据相关表单，匹配处理成每个客户的付款条件明细信息
B7: 目标表 | M7: 客户主数据相关表单
B8: 字段中文名称 | C8: *字段名称 | D8: *类型 | E8: 主键 | F8: *描述 | G8: 允许为空 | H8: 默认值 | I8: 聚合类型 | J8: 基础标准 | K8: 标准代码 | L8: *安全分级 | M8: 转换清洗规则 | N8: 源系统 | O8: 源头表 | P8: 源头字段 | Q8: 匹配字段 | R8: 匹配过滤 | S8: 数仓处理脚本 | T8: 备注
B9: =IFERROR(VLOOKUP(C9,'字段信息'!A:C,3,),"") | C9: company_code | D9: =IFERROR(VLOOKUP(C9,'字段信息'!A:C,2,),"") | F9: =B9 | G9: √ | L9: 普通级 | M9: 直接对应 | N9: Doris | O9: odss600_knb1 odss700_knb1 odss800_knb1 odss900_knb1 odss610_knb1 odss810_knb1 ods.odsfima_aw_rul_revaaz_000001-SAP700公司映射表 | P9: bukrs | Q9: ods.odsfima_aw_rul_revaaz_000001
B10: 客户编码 | C10: cust_code | D10: =IFERROR(VLOOKUP(C10,'字段信息'!A:C,2,),"") | F10: =B10 | G10: √ | L10: 普通级 | M10: 直接对应 | N10: Doris | O10: odss600_knb1 odss700_knb1 odss800_knb1 odss900_knb1 odss610_knb1 odss810_knb1 | P10: kunnr
B11: =IFERROR(VLOOKUP(C11,'字段信息'!A:C,3,),"") | C11: pay_term_code | D11: =IFERROR(VLOOKUP(C11,'字段信息'!A:C,2,),"") | F11: =B11 | G11: √ | L11: 普通级 | M11: 如果对应多行的话拼成一行展示，用逗号分隔开 | N11: Doris | O11: odss600_knb1 odss700_knb1 odss800_knb1 odss900_knb1 odss610_knb1 odss810_knb1 | P11: zterm
B12: =IFERROR(VLOOKUP(C12,'字段信息'!A:C,3,),"") | C12: pay_term_desc | D12: =IFERROR(VLOOKUP(C12,'字段信息'!A:C,2,),"") | F12: =B12 | G12: √ | L12: 普通级 | M12: 如果对应多行的话拼成一行展示，用逗号分隔开 | N12: Doris | O12: odss600_t052u odss700_t052u odss800_t052u odss900_t052u odss610_t052u odss810_t052u | P12: text1 | Q12: zterm = zterm | R12: 限制语言SPRAS = '1'
B13: =IFERROR(VLOOKUP(C13,'字段信息'!A:C,3,),"") | C13: system_src | D13: =IFERROR(VLOOKUP(C13,'字段信息'!A:C,2,),"") | F13: =B13 | G13: √ | L13: 普通级 | M13: 直接对应 | N13: Doris | O13: odss600_knb1 odss700_knb1 odss800_knb1 odss900_knb1 odss610_knb1 odss810_knb1 | P13: 'S'||mandt
B14: =IFERROR(VLOOKUP(C14,'字段信息'!A:C,3,),"") | C14: load_dt | D14: =IFERROR(VLOOKUP(C14,'字段信息'!A:C,2,),"") | F14: =B14 | G14: √ | L14: 普通级 | M14: 数据更新时间 | N14: Doris

Sheet dwd_fi_mr_arap_detail_mi
A1: 返回 | B1: dwd_fi_mr_arap_detail_mi逻辑处理
A2: 规则库 | B2: 表名称 | C2: dwd.dwd_fi_mr_arap_detail_mi
B3: 表描述 | C3: 往来账龄明细表 | D3: 表类型 | E3: 事实表 | F3: 数仓分层 | G3: DWD
B4: L1数仓目录 | C4: 管理财经 | D4: L2数仓目录 | E4: 财报管理 | F4: L3数仓目录 | G4: 应收
B5: 更新方式 | C5: 增量更新 | D5: 设计人员 | F5: 时间
B6: 使用场景 | C6: 根据SAP的底表处理到凭证编码的行项目明细，计算每行数据的账龄天数
B7: 目标表 | M7: 客户、供应商行项目【BSID/BSAD/BSIK/BSAK】 | V7: 科目余额表【faglflext/glfunct】
B8: 字段中文名称 | C8: *字段名称 | D8: *类型 | E8: 主键 | F8: *描述 | G8: 允许为空 | H8: 默认值 | I8: 聚合类型 | J8: 基础标准 | K8: 标准代码 | L8: *安全分级 | M8: 转换清洗规则 | N8: 源系统 | O8: 源头表 | P8: 源头字段 | Q8: 匹配字段 | R8: 匹配过滤 | S8: 数仓处理脚本 | T8: 备注 | V8: 转换清洗规则 | W8: 源系统 | X8: 源头表 | Y8: 源头字段 | Z8: 匹配字段 | AA8: 匹配过滤 | AB8: 数仓处理脚本 | AC8: 备注
B9: =IFERROR(VLOOKUP(C9,'字段信息'!A:C,3,),"") | C9: dt_month | D9: =IFERROR(VLOOKUP(C9,'字段信息'!A:C,2,),"") | F9: =B9 | N9: 参数年月 | W9: 参数年月
B10: =IFERROR(VLOOKUP(C10,'字段信息'!A:C,3,),"") | C10: year | D10: =IFERROR(VLOOKUP(C10,'字段信息'!A:C,2,),"") | F10: =B10 | G10: √ | L10: 普通级 | M10: 限制条件： 1、凭证状态bstat 不为A,S 2、日期限制： bsid/bsik：budat小于等于参数的月末 bsad/bsak：budat小于等于参数的月末且augdt大于参数的月末 3、科目限制： 限制科目为统驭科目，科目范围ztzt_003表匹配公司账目t001表，获得公司和科目的范围，在通过公司总账科目skb1表获得是否是统驭科目，mitkz为D、K则为统驭科目 应收：bsid/bsad：科目类型为D 应付：bsik/bsak：科目类型为K 单独取BSAD中本月已清项目： augdt介于参数本月的日期中&rstgr = ‘400’ | N10: 参数年 | V10: 限制条件： 1、科目限制： 限制科目为非统驭科目，科目范围ztzt_003表匹配公司账目t001表，获得公司和科目的范围，在通过公司总账科目skb1表获得是否是统驭科目，mitkz为空则为非统驭科目 | W10: 参数年
B11: =IFERROR(VLOOKUP(C11,'字段信息'!A:C,3,),"") | C11: month | D11: =IFERROR(VLOOKUP(C11,'字段信息'!A:C,2,),"") | F11: =B11 | G11: √ | L11: 普通级 | M11: 直接对应 | N11: 参数月 | U11: 0908：审计调整的科目余额怎么取 和用户确认 | V11: 通过金额字段转换获得月份 1月等于：hslvt+hsl01 2月等于：hslvt+hsl01+hsl02 ... 12月等于：hslvt+hsl01+hsl02....+hsl12 | W11: 参数月
B12: =IFERROR(VLOOKUP(C12,'字段信息'!A:C,3,),"") | C12: company_code | D12: =IFERROR(VLOOKUP(C12,'字段信息'!A:C,2,),"") | F12: =B12 | G12: √ | L12: 普通级 | M12: 直接对应 | N12: Doris | O12: odsslt_s600_bsid odsslt_s600_bsad odsslt_s600_bsik odsslt_s600_bsak | P12: bukrs | V12: 直接对应 | W12: Doris | X12: ods.ods_slt_s600_faglflext ods.ods_slt_s700_faglflext ods.ods_slt_s800_glfunct ods.ods_slt_s810_faglflext（S610一起） ods.ods_slt_s900_glfunct | Y12: rbukrs
B13: =IFERROR(VLOOKUP(C13,'字段信息'!A:C,3,),"") | C13: acct_cert_type | D13: =IFERROR(VLOOKUP(C13,'字段信息'!A:C,2,),"") | F13: =B13 | G13: √ | L13: 普通级 | M13: 直接对应 | N13: Doris | O13: odsslt_s600_bsid odsslt_s600_bsad odsslt_s600_bsik odsslt_s600_bsak | P13: blart
B14: 凭证状态 | C14: acct_cert_status | D14: =IFERROR(VLOOKUP(C14,'字段信息'!A:C,2,),"") | F14: =B14 | G14: √ | M14: 直接对应 | N14: Doris | O14: odsslt_s600_bsid odsslt_s600_bsad odsslt_s600_bsik odsslt_s600_bsak | P14: bstat
B15: =IFERROR(VLOOKUP(C15,'字段信息'!A:C,3,),"") | C15: acct_cert_id | D15: =IFERROR(VLOOKUP(C15,'字段信息'!A:C,2,),"") | F15: =B15 | G15: √ | L15: 普通级 | M15: 直接对应 | N15: Doris | O15: odsslt_s600_bsid odsslt_s600_bsad odsslt_s600_bsik odsslt_s600_bsak | P15: belnr
B16: =IFERROR(VLOOKUP(C16,'字段信息'!A:C,3,),"") | C16: acct_cert_item | D16: =IFERROR(VLOOKUP(C16,'字段信息'!A:C,2,),"") | F16: =B16 | G16: √ | M16: 直接对应 | N16: Doris | O16: odsslt_s600_bsid odsslt_s600_bsad odsslt_s600_bsik odsslt_s600_bsak | P16: buzei
B17: =IFERROR(VLOOKUP(C17,'字段信息'!A:C,3,),"") | C17: voucher_dt | D17: =IFERROR(VLOOKUP(C17,'字段信息'!A:C,2,),"") | F17: =B17 | G17: √ | M17: 直接对应 | N17: Doris | O17: odsslt_s600_bsid odsslt_s600_bsad odsslt_s600_bsik odsslt_s600_bsak | P17: bldat
B18: =IFERROR(VLOOKUP(C18,'字段信息'!A:C,3,),"") | C18: posting_dt | D18: =IFERROR(VLOOKUP(C18,'字段信息'!A:C,2,),"") | F18: =B18 | G18: √ | L18: 普通级 | M18: 直接对应 | N18: Doris | O18: odsslt_s600_bsid odsslt_s600_bsad odsslt_s600_bsik odsslt_s600_bsak | P18: budat
B19: =IFERROR(VLOOKUP(C19,'字段信息'!A:C,3,),"") | C19: baseline_dt | D19: =IFERROR(VLOOKUP(C19,'字段信息'!A:C,2,),"") | F19: =B19 | G19: √ | L19: 普通级 | M19: 直接对应 | N19: Doris | O19: odsslt_s600_bsid odsslt_s600_bsad odsslt_s600_bsik odsslt_s600_bsak | P19: AB取ZFBDT，其他取BLDAT ZFBDT
B20: =IFERROR(VLOOKUP(C20,'字段信息'!A:C,3,),"") | C20: netrcp_dt | D20: =IFERROR(VLOOKUP(C20,'字段信息'!A:C,2,),"") | F20: =B20 | G20: √ | M20: 如果shkzg为S，根据基准日期+天数计算 如果为H，直接取基准日期 | N20: Doris | O20: odsslt_s600_bsid odsslt_s600_bsad odsslt_s600_bsik odsslt_s600_bsak | P20: ZFBDT + ZBD1T
B21: =IFERROR(VLOOKUP(C21,'字段信息'!A:C,3,),"") | C21: clearing_dt | D21: =IFERROR(VLOOKUP(C21,'字段信息'!A:C,2,),"") | F21: =B21 | G21: √ | L21: 普通级 | M21: 直接对应 | N21: Doris | O21: odsslt_s600_bsid odsslt_s600_bsad odsslt_s600_bsik odsslt_s600_bsak | P21: augdt
B22: =IFERROR(VLOOKUP(C22,'字段信息'!A:C,3,),"") | C22: cust_code | D22: =IFERROR(VLOOKUP(C22,'字段信息'!A:C,2,),"") | F22: =B22 | G22: √ | L22: 普通级 | M22: 直接对应 | N22: Doris | O22: odsslt_s600_bsid odsslt_s600_bsad odsslt_s600_bsik odsslt_s600_bsak | P22: 优先取分户编码，没有则取主户
B23: =IFERROR(VLOOKUP(C23,'字段信息'!A:C,3,),"") | C23: cust_name | D23: =IFERROR(VLOOKUP(C23,'字段信息'!A:C,2,),"") | F23: =B23 | G23: √ | L23: 普通级 | M23: odsslt_s600_bsid、odsslt_s600_bsad: 匹配客户主数据ods.odss600_kna1 odsslt_s600_bsik、odsslt_s600_bsak: 匹配供应商主数据ods.odss600_lfa1 | N23: Doris | O23: ods.odss600_kna1 ods.odss600_lfa1 | P23: 优先取分户名称，没有则取名称
B24: =IFERROR(VLOOKUP(C24,'字段信息'!A:C,3,),"") | C24: cust_head_code | D24: =IFERROR(VLOOKUP(C24,'字段信息'!A:C,2,),"") | F24: =B24 | G24: √ | L24: 普通级 | M24: 直接对应 | N24: Doris | O24: odsslt_s600_bsid odsslt_s600_bsad odsslt_s600_bsik odsslt_s600_bsak | P24: kunnr lifnr
B25: =IFERROR(VLOOKUP(C25,'字段信息'!A:C,3,),"") | C25: cust_head_name | D25: =IFERROR(VLOOKUP(C25,'字段信息'!A:C,2,),"") | F25: =B25 | G25: √ | L25: 普通级 | M25: odsslt_s600_bsid、odsslt_s600_bsad: 匹配客户主数据ods.odss600_kna1 odsslt_s600_bsik、odsslt_s600_bsak: 匹配供应商主数据ods.odss600_lfa1 | N25: Doris | O25: ods.odss600_kna1 ods.odss600_lfa1 | P25: name1 | Q25: 主户编码匹配客商主数据
B26: =IFERROR(VLOOKUP(C26,'字段信息'!A:C,3,),"") | C26: cust_branch_code | D26: =IFERROR(VLOOKUP(C26,'字段信息'!A:C,2,),"") | F26: =B26 | G26: √ | L26: 普通级 | M26: 直接对应 | N26: Doris | O26: odsslt_s600_bsid odsslt_s600_bsad odsslt_s600_bsik odsslt_s600_bsak | P26: filkd
B27: =IFERROR(VLOOKUP(C27,'字段信息'!A:C,3,),"") | C27: cust_branch_name | D27: =IFERROR(VLOOKUP(C27,'字段信息'!A:C,2,),"") | F27: =B27 | G27: √ | L27: 普通级 | M27: odsslt_s600_bsid、odsslt_s600_bsad: 匹配客户主数据ods.odss600_kna1 odsslt_s600_bsik、odsslt_s600_bsak: 匹配供应商主数据ods.odss600_lfa1 | N27: Doris | O27: ods.odss600_kna1 ods.odss600_lfa1 | P27: name1 | Q27: 分户编码匹配客商主数据
B28: =IFERROR(VLOOKUP(C28,'字段信息'!A:C,3,),"") | C28: cp_company_code | D28: =IFERROR(VLOOKUP(C28,'字段信息'!A:C,2,),"") | F28: =B28 | G28: √ | L28: 普通级 | M28: 匹配客商映射对方公司dim.dim_rule_fi_mr_cust2ctp_mapping | N28: Doris | O28: dim.dim_rule_fi_mr_cust2ctp_mapping | P28: 优先取cp_company_code_mr，为空则取cp_company_code | Q28: 主户编码匹配客商映射对方公司映射表
B29: =IFERROR(VLOOKUP(C29,'字段信息'!A:C,3,),"") | C29: country_code | D29: =IFERROR(VLOOKUP(C29,'字段信息'!A:C,2,),"") | F29: =B29 | G29: √ | L29: 普通级 | M29: 1、先匹配SAP客户主数据得到zkunnr_mdg 2、再匹配mdg客户主数据得到对应字段 | N29: Doris | O29: 1、ods.ods_slt_s600_kna1-客户主数据 2、dw.dim_customer_base_info_dd-客户主数据基本信息 | P29: 1、zkunnr_mdg 2、country_code | Q29: 1、kunnr = kunnr 2、zkunnr_mdg = cust_code
B30: =IFERROR(VLOOKUP(C30,'字段信息'!A:C,3,),"") | C30: country_name | D30: =IFERROR(VLOOKUP(C30,'字段信息'!A:C,2,),"") | F30: =B30 | G30: √ | M30: 1、先匹配SAP客户主数据得到zkunnr_mdg 2、再匹配mdg客户主数据得到对应字段 | N30: Doris | O30: 1、ods.ods_slt_s600_kna1-客户主数据 2、dw.dim_customer_base_info_dd-客户主数据基本信息 | P30: 1、zkunnr_mdg 2、country_name | Q30: 1、kunnr = kunnr 2、zkunnr_mdg = cust_code
B31: =IFERROR(VLOOKUP(C31,'字段信息'!A:C,3,),"") | C31: acct_type_code | D31: =IFERROR(VLOOKUP(C31,'字段信息'!A:C,2,),"") | F31: =B31 | G31: √ | L31: 普通级 | M31: 直接对应 | N31: Doris | O31: odsslt_s600_bsid odsslt_s600_bsad odsslt_s600_bsik odsslt_s600_bsak | P31: koart | V31: 直接对应 | W31: Doris | X31: ods.odss600_ztzt_003 | Y31: koart
B32: =IFERROR(VLOOKUP(C32,'字段信息'!A:C,3,),"") | C32: acct_src_code | D32: =IFERROR(VLOOKUP(C32,'字段信息'!A:C,2,),"") | F32: =B32 | G32: √ | L32: 普通级 | M32: 直接对应 | N32: Doris | O32: odsslt_s600_bsid odsslt_s600_bsad odsslt_s600_bsik odsslt_s600_bsak | P32: hkont | V32: 直接对应 | W32: Doris | X32: ods.ods_slt_s600_faglflext ods.ods_slt_s700_faglflext ods.ods_slt_s800_glfunct ods.ods_slt_s810_faglflext（S610一起） ods.ods_slt_s900_glfunct | Y32: racct
B33: =IFERROR(VLOOKUP(C33,'字段信息'!A:C,3,),"") | C33: acct_map_code | D33: =IFERROR(VLOOKUP(C33,'字段信息'!A:C,2,),"") | F33: =B33 | G33: √ | L33: 普通级 | M33: 匹配科目映射表dim.dim_rule_fi_mr_acct_mapping | N33: Doris | O33: dim.dim_rule_fi_mr_acct_mapping | P33: acct_map_code | Q33: 科目编码匹配科目映射表 | V33: 匹配科目映射表dim.dim_rule_fi_mr_acct_mapping | W33: Doris | X33: dim.dim_rule_fi_mr_acct_mapping | Y33: acct_map_code | Z33: 科目编码匹配科目映射表
A34: 0908：客户主数据匹配可以统一一个客户大表，通用逻辑匹配 | B34: =IFERROR(VLOOKUP(C34,'字段信息'!A:C,3,),"") | C34: channel_l1_code | D34: =IFERROR(VLOOKUP(C34,'字段信息'!A:C,2,),"") | F34: =B34 | G34: √ | L34: 普通级 | M34: 1、先匹配SAP客户主数据得到zkunnr_mdg 2、再匹配mdg客户主数据得到对应字段 | N34: Doris | O34: 1、ods.ods_slt_s600_kna1-客户主数据 2、dw.dim_customer_base_info_dd-客户主数据基本信息 | P34: 1、zkunnr_mdg 2、com_1st_code | Q34: 1、kunnr = kunnr 2、zkunnr_mdg = cust_code
B35: =IFERROR(VLOOKUP(C35,'字段信息'!A:C,3,),"") | C35: channel_l1_name | D35: =IFERROR(VLOOKUP(C35,'字段信息'!A:C,2,),"") | F35: =B35 | G35: √ | L35: 普通级 | M35: 1、先匹配SAP客户主数据得到zkunnr_mdg 2、再匹配mdg客户主数据得到对应字段 | N35: Doris | O35: 1、ods.ods_slt_s600_kna1-客户主数据 2、dw.dim_customer_base_info_dd-客户主数据基本信息 | P35: 1、zkunnr_mdg 2、com_1st_name | Q35: 1、kunnr = kunnr 2、zkunnr_mdg = cust_code
B36: =IFERROR(VLOOKUP(C36,'字段信息'!A:C,3,),"") | C36: channel_l2_code | D36: =IFERROR(VLOOKUP(C36,'字段信息'!A:C,2,),"") | F36: =B36 | G36: √ | L36: 普通级 | M36: 1、先匹配SAP客户主数据得到zkunnr_mdg 2、再匹配mdg客户主数据得到对应字段 | N36: Doris | O36: 1、ods.ods_slt_s600_kna1-客户主数据 2、dw.dim_customer_base_info_dd-客户主数据基本信息 | P36: 1、zkunnr_mdg 2、com_2nd_code | Q36: 1、kunnr = kunnr 2、zkunnr_mdg = cust_code
B37: =IFERROR(VLOOKUP(C37,'字段信息'!A:C,3,),"") | C37: channel_l2_name | D37: =IFERROR(VLOOKUP(C37,'字段信息'!A:C,2,),"") | F37: =B37 | G37: √ | L37: 普通级 | M37: 1、先匹配SAP客户主数据得到zkunnr_mdg 2、再匹配mdg客户主数据得到对应字段 | N37: Doris | O37: 1、ods.ods_slt_s600_kna1-客户主数据 2、dw.dim_customer_base_info_dd-客户主数据基本信息 | P37: 1、zkunnr_mdg 2、com_2nd_name | Q37: 1、kunnr = kunnr 2、zkunnr_mdg = cust_code
B38: =IFERROR(VLOOKUP(C38,'字段信息'!A:C,3,),"") | C38: channel_l3_code | D38: =IFERROR(VLOOKUP(C38,'字段信息'!A:C,2,),"") | F38: =B38 | G38: √ | L38: 普通级 | M38: 1、先匹配SAP客户主数据得到zkunnr_mdg 2、再匹配mdg客户主数据得到对应字段 | N38: Doris | O38: 1、ods.ods_slt_s600_kna1-客户主数据 2、dw.dim_customer_base_info_dd-客户主数据基本信息 | P38: 1、zkunnr_mdg 2、com_3rd_code | Q38: 1、kunnr = kunnr 2、zkunnr_mdg = cust_code
B39: =IFERROR(VLOOKUP(C39,'字段信息'!A:C,3,),"") | C39: channel_l3_name | D39: =IFERROR(VLOOKUP(C39,'字段信息'!A:C,2,),"") | F39: =B39 | G39: √ | L39: 普通级 | M39: 1、先匹配SAP客户主数据得到zkunnr_mdg 2、再匹配mdg客户主数据得到对应字段 | N39: Doris | O39: 1、ods.ods_slt_s600_kna1-客户主数据 2、dw.dim_customer_base_info_dd-客户主数据基本信息 | P39: 1、zkunnr_mdg 2、com_3rd_name | Q39: 1、kunnr = kunnr 2、zkunnr_mdg = cust_code
A40: 0908：等后续拉通后统一处理 | B40: =IFERROR(VLOOKUP(C40,'字段信息'!A:C,3,),"") | C40: tov_channel_code | D40: =IFERROR(VLOOKUP(C40,'字段信息'!A:C,2,),"") | F40: =B40 | G40: √ | M40: 待拉通后处理 | N40: Doris
B41: =IFERROR(VLOOKUP(C41,'字段信息'!A:C,3,),"") | C41: tov_channel_name | D41: =IFERROR(VLOOKUP(C41,'字段信息'!A:C,2,),"") | F41: =B41 | G41: √ | M41: 待拉通后处理 | N41: Doris
B42: =IFERROR(VLOOKUP(C42,'字段信息'!A:C,3,),"") | C42: cust_unity_code | D42: =IFERROR(VLOOKUP(C42,'字段信息'!A:C,2,),"") | F42: =B42 | G42: √ | M42: 1、先匹配SAP客户主数据得到zkunnr_mdg 2、再匹配mdg客户主数据得到对应字段 | N42: Doris | O42: 1、ods.ods_slt_s600_kna1-客户主数据 2、dw.dim_customer_base_info_dd-客户主数据基本信息 | P42: 1、zkunnr_mdg 2、cust_unity_code
B43: =IFERROR(VLOOKUP(C43,'字段信息'!A:C,3,),"") | C43: cust_unity_name | D43: =IFERROR(VLOOKUP(C43,'字段信息'!A:C,2,),"") | F43: =B43 | G43: √ | M43: 1、先匹配SAP客户主数据得到zkunnr_mdg 2、再匹配mdg客户主数据得到对应字段 | N43: Doris | O43: 1、ods.ods_slt_s600_kna1-客户主数据 2、dw.dim_customer_base_info_dd-客户主数据基本信息 | P43: 1、zkunnr_mdg 2、cust_unity_name
A44: 0908：非标准的单独讨论 | B44: =IFERROR(VLOOKUP(C44,'字段信息'!A:C,3,),"") | C44: cc_cust_group_code | D44: =IFERROR(VLOOKUP(C44,'字段信息'!A:C,2,),"") | F44: =B44 | G44: √ | M44: 待维度定标
B45: =IFERROR(VLOOKUP(C45,'字段信息'!A:C,3,),"") | C45: cc_cust_group_name | D45: =IFERROR(VLOOKUP(C45,'字段信息'!A:C,2,),"") | F45: =B45 | G45: √ | M45: 待维度定标
B46: =IFERROR(VLOOKUP(C46,'字段信息'!A:C,3,),"") | C46: onoffline_code | D46: =IFERROR(VLOOKUP(C46,'字段信息'!A:C,2,),"") | F46: =B46 | G46: √ | L46: 普通级 | M46: 1、匹配《应收模块-渠道分组映射表》，根据优先级按顺序映射 2、其余公司： 匹配《收入模块-线上线下映射表》，按照收入模块的处理映射 如果上述所有规则均不涉及，则默认020_OFF_002（零售-传统零售） | N46: Doris | O46: dim.dim_rule_fi_mr_ar_nf_mapping-渠道分组映射表 dim.dim_rule_fi_mr_nf_mapping-经分项目收入模块规则映射表 | P46: onoffline_code
B47: =IFERROR(VLOOKUP(C47,'字段信息'!A:C,3,),"") | C47: onoffline_name | D47: =IFERROR(VLOOKUP(C47,'字段信息'!A:C,2,),"") | F47: =B47 | G47: √ | L47: 普通级 | M47: 1、匹配《应收模块-渠道分组映射表》，根据优先级按顺序映射 2、其余公司： 匹配《收入模块-线上线下映射表》，按照收入模块的处理映射 如果上述所有规则均不涉及，则默认020_OFF_002（零售-传统零售） | N47: Doris | O47: dim.dim_rule_fi_mr_ar_nf_mapping-渠道分组映射表 dim.dim_rule_fi_mr_nf_mapping-经分项目收入模块规则映射表 | P47: onoffline_name
B48: =IFERROR(VLOOKUP(C48,'字段信息'!A:C,3,),"") | C48: src_profitcenter_code | D48: =IFERROR(VLOOKUP(C48,'字段信息'!A:C,2,),"") | F48: =B48 | G48: √ | L48: 普通级 | M48: 直接对应 | N48: Doris | O48: odsslt_s600_bsid odsslt_s600_bsad odsslt_s600_bsik odsslt_s600_bsak | P48: prctr | V48: 直接对应 | W48: Doris | X48: ods.ods_slt_s600_faglflext ods.ods_slt_s700_faglflext ods.ods_slt_s800_glfunct ods.ods_slt_s810_faglflext（S610一起） ods.ods_slt_s900_glfunct | Y48: faglflext:prctr glfunct:null
B49: =IFERROR(VLOOKUP(C49,'字段信息'!A:C,3,),"") | C49: src_profitcenter_name | D49: =IFERROR(VLOOKUP(C49,'字段信息'!A:C,2,),"") | F49: =B49 | G49: √ | L49: 普通级 | M49: 匹配利润中心主数据ods.odss600_cepct | N49: Doris | O49: ods.odss600_cepct | P49: ktext | V49: 匹配利润中心主数据ods.odss600_cepct | W49: Doris | X49: ods.odss600_cepct | Y49: ktext
B50: =IFERROR(VLOOKUP(C50,'字段信息'!A:C,3,),"") | C50: profitcenter_code | D50: =IFERROR(VLOOKUP(C50,'字段信息'!A:C,2,),"") | F50: =B50 | G50: √ | L50: 普通级 | M50: 如果客户范围在《电商零售客户》内 匹配《应收模块-利润中心映射表》，筛选映射类型为“新旧利润中心映射”，将旧利润中心映射成新利润中心 | N50: Doris | O50: dim.dim_rule_fi_mr_ar_profit_mapping-利润中心映射表 | V50: 如果客户范围在《电商零售客户》内 匹配《应收模块-利润中心映射表》，筛选映射类型为“新旧利润中心映射”，将旧利润中心映射成新利润中心 | W50: Doris | X50: dim.dim_rule_fi_mr_ar_profit_mapping-利润中心映射表
B51: =IFERROR(VLOOKUP(C51,'字段信息'!A:C,3,),"") | C51: profitcenter_name | D51: =IFERROR(VLOOKUP(C51,'字段信息'!A:C,2,),"") | F51: =B51 | G51: √ | L51: 普通级 | M51: 如果客户范围在《电商零售客户》内 匹配《应收模块-利润中心映射表》，筛选映射类型为“新旧利润中心映射”，将旧利润中心映射成新利润中心 | N51: Doris | O51: dim.dim_rule_fi_mr_ar_profit_mapping-利润中心映射表 | V51: 如果客户范围在《电商零售客户》内 匹配《应收模块-利润中心映射表》，筛选映射类型为“新旧利润中心映射”，将旧利润中心映射成新利润中心 | W51: Doris | X51: dim.dim_rule_fi_mr_ar_profit_mapping-利润中心映射表
B52: =IFERROR(VLOOKUP(C52,'字段信息'!A:C,3,),"") | C52: bus_range_code | D52: =IFERROR(VLOOKUP(C52,'字段信息'!A:C,2,),"") | F52: =B52 | G52: √ | L52: 普通级 | M52: 1、商显公司（公司10架构中，节点代码01020）： 根据客户主数据匹配出国家，如果是CN的为2000-中国区公共，其余放3000-海外公共 2、日立公司（公司10架构中，节点代码050）： 根据客户主数据匹配出国家，如果是CN的放2200-日立国内营销分公司公共，其余的根据《国家业务范围映射表》，匹配出对应的业务范围 3、其余： 匹配《业务范围映射表》，根据优先级判断映射出业务范围 | N52: Doris | O52: dim_rule_fi_mr_ar_busrange_mapping-业务范围映射表 dim_rule_fi_mr_ar_country_busrange_mapping-国家业务范围映射表 | V52: 直接对应 | W52: Doris | X52: ods.ods_slt_s600_faglflext ods.ods_slt_s700_faglflext ods.ods_slt_s800_glfunct ods.ods_slt_s810_faglflext（S610一起） ods.ods_slt_s900_glfunct | Y52: rbusa
B53: =IFERROR(VLOOKUP(C53,'字段信息'!A:C,3,),"") | C53: bus_range_name | D53: =IFERROR(VLOOKUP(C53,'字段信息'!A:C,2,),"") | F53: =B53 | G53: √ | L53: 普通级 | M53: 1、商显公司（公司10架构中，节点代码01020）： 根据客户主数据匹配出国家，如果是CN的为2000-中国区公共，其余放3000-海外公共 2、日立公司（公司10架构中，节点代码050）： 根据客户主数据匹配出国家，如果是CN的放2200-日立国内营销分公司公共，其余的根据《国家业务范围映射表》，匹配出对应的业务范围 3、其余： 匹配《业务范围映射表》，根据优先级判断映射出业务范围 | N53: Doris | O53: dim_rule_fi_mr_ar_busrange_mapping-业务范围映射表 dim_rule_fi_mr_ar_country_busrange_mapping-国家业务范围映射表
B54: =IFERROR(VLOOKUP(C54,'字段信息'!A:C,3,),"") | C54: marketing_dept_code | D54: =IFERROR(VLOOKUP(C54,'字段信息'!A:C,2,),"") | F54: =B54 | G54: √ | L54: 普通级 | M54: 匹配《业务管理单元映射表》，根据不同的系统映射业务管理单元 | N54: Doris | O54: dim_rule_fi_mr_ar_busdept_mapping-业务管理单元映射表
B55: =IFERROR(VLOOKUP(C55,'字段信息'!A:C,3,),"") | C55: marketing_dept_name | D55: =IFERROR(VLOOKUP(C55,'字段信息'!A:C,2,),"") | F55: =B55 | G55: √ | L55: 普通级 | M55: 匹配《业务管理单元映射表》，根据不同的系统映射业务管理单元 | N55: Doris | O55: dim_rule_fi_mr_ar_busdept_mapping-业务管理单元映射表
B56: =IFERROR(VLOOKUP(C56,'字段信息'!A:C,3,),"") | C56: nature_l1_name | D56: varchar(2000) | F56: =B56 | G56: √ | M56: 匹配《性质维护表》，按照顺序优先级处理 1、匹配规则batch_id为1，按照公司company_code+科目acct_src_code+主户cust_code匹配 2、匹配规则batch_id为2，按照公司company_code+主户cust_code匹配 3、匹配规则batch_id为3，按照公司company_code+科目acct_src_code+利润中心profitcenter_code匹配 4、匹配规则batch_id为4，按照公司company_code+科目acct_src_code匹配 5、匹配规则batch_id为5，按照科目company_code+主户cust_code匹配 6、以上未匹配到的，按照公司+客商性质+客商编码匹配sap主数据客户和供应商主数据取KVERM | N56: Doris | O56: dim_rule_fi_mr_ar_nature | P56: nature_l1_name
B57: =IFERROR(VLOOKUP(C57,'字段信息'!A:C,3,),"") | C57: nature_l2_name | D57: varchar(2000) | F57: =B57 | G57: √ | M57: 同一级性质 | N57: Doris | O57: dim_rule_fi_mr_ar_nature | P57: nature_l2_name
B58: =IFERROR(VLOOKUP(C58,'字段信息'!A:C,3,),"") | C58: nature_l3_name | D58: varchar(2000) | F58: =B58 | G58: √ | M58: 同一级性质 | N58: Doris | O58: dim_rule_fi_mr_ar_nature | P58: nature_l3_name
B59: =IFERROR(VLOOKUP(C59,'字段信息'!A:C,3,),"") | C59: pay_method | D59: =IFERROR(VLOOKUP(C59,'字段信息'!A:C,2,),"") | F59: =B59 | G59: √ | O59: odsslt_s600_bsid odsslt_s600_bsad odsslt_s600_bsik odsslt_s600_bsak | P59: zlsch
B60: =IFERROR(VLOOKUP(C60,'字段信息'!A:C,3,),"") | C60: pay_reason_code | D60: =IFERROR(VLOOKUP(C60,'字段信息'!A:C,2,),"") | F60: =B60 | G60: √ | L60: 普通级 | M60: 直接对应 | N60: Doris | O60: odsslt_s600_bsid odsslt_s600_bsad odsslt_s600_bsik odsslt_s600_bsak | P60: rstgr
B61: =IFERROR(VLOOKUP(C61,'字段信息'!A:C,3,),"") | C61: bcy_code | D61: =IFERROR(VLOOKUP(C61,'字段信息'!A:C,2,),"") | F61: =B61 | G61: √ | L61: 普通级 | M61: 匹配公司映射币种ods.odss600_t001 | N61: Doris | O61: odsslt_s600_bsid odsslt_s600_bsad odsslt_s600_bsik odsslt_s600_bsak ods.odss600_t001 | P61: waers | Q61: 公司匹配t001的bukrs，取t001的waers | V61: 匹配公司映射币种ods.odss600_t001 | W61: Doris | X61: ods.ods_slt_s600_faglflext ods.ods_slt_s700_faglflext ods.ods_slt_s800_glfunct ods.ods_slt_s810_faglflext（S610一起） ods.ods_slt_s900_glfunct ods.odss600_t001 | Y61: waers | Z61: 公司匹配t001的bukrs，取t001的waers
B62: =IFERROR(VLOOKUP(C62,'字段信息'!A:C,3,),"") | C62: qcy_code | D62: =IFERROR(VLOOKUP(C62,'字段信息'!A:C,2,),"") | F62: =B62 | G62: √ | L62: 普通级 | M62: 直接对应 | N62: Doris | O62: odsslt_s600_bsid odsslt_s600_bsad odsslt_s600_bsik odsslt_s600_bsak | P62: waers | V62: 直接对应 | W62: Doris | X62: ods.ods_slt_s600_faglflext ods.ods_slt_s700_faglflext ods.ods_slt_s800_glfunct ods.ods_slt_s810_faglflext（S610一起） ods.ods_slt_s900_glfunct | Y62: rtcur
B63: =IFERROR(VLOOKUP(C63,'字段信息'!A:C,3,),"") | C63: bcy_amt | D63: =IFERROR(VLOOKUP(C63,'字段信息'!A:C,2,),"") | F63: =B63 | G63: √ | L63: 普通级 | M63: 直接对应 | N63: Doris | O63: odsslt_s600_bsid odsslt_s600_bsad odsslt_s600_bsik odsslt_s600_bsak | P63: CASE WHEN a.shkzg = 'H' THEN -a.dmbtr ELSE a.dmbtr END | V63: 直接对应 | W63: Doris | X63: ods.ods_slt_s600_faglflext ods.ods_slt_s700_faglflext ods.ods_slt_s800_glfunct ods.ods_slt_s810_faglflext（S610一起） ods.ods_slt_s900_glfunct | Y63: 1月等于：hslvt+hsl01 2月等于：hslvt+hsl01+hsl02 ... 12月等于：hslvt+hsl01+hsl02....+hsl12
B64: =IFERROR(VLOOKUP(C64,'字段信息'!A:C,3,),"") | C64: qcy_amt | D64: =IFERROR(VLOOKUP(C64,'字段信息'!A:C,2,),"") | F64: =B64 | G64: √ | L64: 普通级 | M64: 直接对应 | N64: Doris | O64: odsslt_s600_bsid odsslt_s600_bsad odsslt_s600_bsik odsslt_s600_bsak | P64: CASE WHEN a.shkzg = 'H' THEN -a.wrbtr ELSE a.wrbtr END | V64: 直接对应 | W64: Doris | X64: ods.ods_slt_s600_faglflext ods.ods_slt_s700_faglflext ods.ods_slt_s800_glfunct ods.ods_slt_s810_faglflext（S610一起） ods.ods_slt_s900_glfunct | Y64: 1月等于：tslvt+tsl01 2月等于：tslvt+tsl01+tsl02 ... 12月等于：tslvt+tsl01+tsl02....+tsl12
A65: 0908：需要增加账龄段的判断 | B65: =IFERROR(VLOOKUP(C65,'字段信息'!A:C,3,),"") | C65: aging_days | D65: =IFERROR(VLOOKUP(C65,'字段信息'!A:C,2,),"") | F65: =B65 | G65: √ | L65: 普通级 | M65: 1、如果凭证类型为AB时起算日期用基准日期zfbdt， 2、根据《账龄日期计算配置-dim_rule_fi_mr_ar_agingdate》判断，用系统号+公司匹配对应，基准日期zfbdt 3、其余用凭证日期bldat计算 公式：aging_days = 月末最后一天 - 起算日期 + 1 | N65: Doris | O65: odsslt_s600_bsid odsslt_s600_bsad odsslt_s600_bsik odsslt_s600_bsak | P65: 月末最后一天 - 起算日期 + 1 | V65: 固定值：1
B66: =IFERROR(VLOOKUP(C66,'字段信息'!A:C,3,),"") | C66: aging_seg_code | D66: =IFERROR(VLOOKUP(C66,'字段信息'!A:C,2,),"") | F66: =B66 | G66: √ | M66: 根据计算的账龄天数匹配【账龄段配置表dim.dim_rule_fi_mr_ar_aging_seg】 | N66: Doris | O66: dim.dim_rule_fi_mr_ar_aging_seg-账龄段配置表 | P66: 账龄段编码
B67: =IFERROR(VLOOKUP(C67,'字段信息'!A:C,3,),"") | C67: aging_seg_name | D67: =IFERROR(VLOOKUP(C67,'字段信息'!A:C,2,),"") | F67: =B67 | G67: √ | M67: 根据计算的账龄天数匹配【账龄段配置表dim.dim_rule_fi_mr_ar_aging_seg】 | N67: Doris | O67: dim.dim_rule_fi_mr_ar_aging_seg-账龄段配置表 | P67: 账龄段名称
B68: =IFERROR(VLOOKUP(C68,'字段信息'!A:C,3,),"") | C68: pays_tran | D68: =IFERROR(VLOOKUP(C68,'字段信息'!A:C,2,),"") | F68: =B68 | G68: √ | M68: 直接对应 | N68: Doris | O68: odsslt_s600_bsid odsslt_s600_bsad odsslt_s600_bsik odsslt_s600_bsak | P68: pays_tran
B69: =IFERROR(VLOOKUP(C69,'字段信息'!A:C,3,),"") | C69: note | D69: =IFERROR(VLOOKUP(C69,'字段信息'!A:C,2,),"") | F69: =B69 | G69: √ | M69: 直接对应 | N69: Doris | O69: odsslt_s600_bsid odsslt_s600_bsad odsslt_s600_bsik odsslt_s600_bsak | P69: sgtxt
B70: =IFERROR(VLOOKUP(C70,'字段信息'!A:C,3,),"") | C70: system_src | D70: =IFERROR(VLOOKUP(C70,'字段信息'!A:C,2,),"") | F70: =B70 | G70: √ | L70: 普通级 | M70: 根据取数表判断取数值S600 | V70: 根据取数表判断取数值S600
B71: =IFERROR(VLOOKUP(C71,'字段信息'!A:C,3,),"") | C71: ods_src | D71: =IFERROR(VLOOKUP(C71,'字段信息'!A:C,2,),"") | F71: =B71 | G71: √ | L71: 普通级 | M71: odsslt_s600_bsid:BSID odsslt_s600_bsad:BSAD odsslt_s600_bsik:BSIK odsslt_s600_bsak:BSAK 单独取BSAD中本月已清项目：bsad_epay | N71: Doris | V71: 固定值： FAGLFLEXT GLFUNCT | W71: Doris
A72: 0908：补充摘要等信息字段 | B72: =IFERROR(VLOOKUP(C72,'字段信息'!A:C,3,),"") | C72: load_dt | D72: =IFERROR(VLOOKUP(C72,'字段信息'!A:C,2,),"") | F72: =B72 | G72: √ | L72: 普通级 | M72: NOW() | N72: Doris | V72: NOW() | W72: Doris

Sheet dwd_fi_mr_ar_overdue_mi
A1: 返回 | B1: dwd_fi_mr_ar_odue_mi逻辑处理
A2: 规则库 | B2: 表名称 | C2: dwd.dwd_fi_mr_ar_overdue_mi
B3: 表描述 | C3: 超期款明细表 | D3: 表类型 | E3: 事实表 | F3: 数仓分层 | G3: DWD
B4: L1数仓目录 | C4: 管理财经 | D4: L2数仓目录 | E4: 财报管理 | F4: L3数仓目录 | G4: 应收
B5: 更新方式 | C5: 增量更新 | D5: 设计人员 | F5: 时间
B6: 使用场景 | C6: 取财务中台-问题资金系统中超期款及开票样机的金额 | M6: 待跟进事项： 1、问题资金系统需要新增公司+客商+利润中心字段--用户在提需求 | P6: 0908：超期款宽表应该包含调整数据，待文霞沟通 | V6: 待跟进事项： 1、问题资金系统需要新增公司+客商+利润中心字段--用户在提需求 2、问题资金给的后台表各字段筛选条件及匹配逻辑--待和问题资金的顾问沟通确认
B7: 目标表 | M7: 超期款dws.dws_fi_mr_wtzjcqkmx_mi | V7: 问题资金手工调整项【ods.odsfipf_tk_hfi_jtb_bjwtzjtz】
B8: 字段中文名称 | C8: *字段名称 | D8: *类型 | E8: 主键 | F8: *描述 | G8: 允许为空 | H8: 默认值 | I8: 聚合类型 | J8: 基础标准 | K8: 标准代码 | L8: *安全分级 | M8: 转换清洗规则 | N8: 源系统 | O8: 源头表 | P8: 源头字段 | Q8: 匹配字段 | R8: 匹配过滤 | S8: 数仓处理脚本 | T8: 备注 | V8: 转换清洗规则 | W8: 源系统 | X8: 源头表 | Y8: 源头字段 | Z8: 匹配字段 | AA8: 匹配过滤 | AB8: 数仓处理脚本 | AC8: 备注
B9: =IFERROR(VLOOKUP(C9,'字段信息'!A:C,3,),"") | C9: dt_month | D9: =IFERROR(VLOOKUP(C9,'字段信息'!A:C,2,),"") | F9: =B9 | M9: 直接对应 | N9: 参数年月 | O9: dws.dws_fi_mr_wtzjcqkmx_mi | P9: start_dt | V9: 截取字段对应年月 限制条件： fstatus = 'E' and fk_hifi_mk = '4' | W9: 参数年月 | X9: ods.odsfipf_tk_hfi_jtb_bjtwtzjtz | Y9: fk_hifi_tzyf
B10: =IFERROR(VLOOKUP(C10,'字段信息'!A:C,3,),"") | C10: year | D10: =IFERROR(VLOOKUP(C10,'字段信息'!A:C,2,),"") | F10: =B10 | G10: √ | M10: 直接对应 | N10: 参数年 | O10: dws.dws_fi_mr_wtzjcqkmx_mi | P10: start_dt截取年份 | V10: 截取字段对应年份 | W10: 参数年 | X10: ods.odsfipf_tk_hfi_jtb_bjtwtzjtz | Y10: fk_hifi_tzyf
B11: =IFERROR(VLOOKUP(C11,'字段信息'!A:C,3,),"") | C11: month | D11: =IFERROR(VLOOKUP(C11,'字段信息'!A:C,2,),"") | F11: =B11 | G11: √ | L11: 普通级 | M11: 直接对应 | N11: 参数月 | O11: dws.dws_fi_mr_wtzjcqkmx_mi | P11: start_dt截取月份 | V11: 截取字段对应月份 | W11: 参数月 | X11: ods.odsfipf_tk_hfi_jtb_bjtwtzjtz | Y11: fk_hifi_tzyf
B12: =IFERROR(VLOOKUP(C12,'字段信息'!A:C,3,),"") | C12: company_code | D12: =IFERROR(VLOOKUP(C12,'字段信息'!A:C,2,),"") | F12: =B12 | G12: √ | L12: 普通级 | M12: 直接对应 | N12: Doris | O12: dws.dws_fi_mr_wtzjcqkmx_mi | P12: ledge_code | V12: 根据公司名称判断 平板电视： 冰箱公司（冰冷）： 空调公司： 海信日立： 营销服中心——内销： | W12: Doris | X12: ods.odsfipf_tk_hfi_jtb_bjtwtzjtz | Y12: fk_hifi_gs
B13: =IFERROR(VLOOKUP(C13,'字段信息'!A:C,3,),"") | C13: acct_src_code | D13: =IFERROR(VLOOKUP(C13,'字段信息'!A:C,2,),"") | F13: =B13 | G13: √ | L13: 普通级 | M13: 直接对应 | N13: Doris | O13: dws.dws_fi_mr_wtzjcqkmx_mi | P13: gl_account | V13: 1122000000
B14: =IFERROR(VLOOKUP(C14,'字段信息'!A:C,3,),"") | C14: cust_code | D14: =IFERROR(VLOOKUP(C14,'字段信息'!A:C,2,),"") | F14: =B14 | G14: √ | L14: 普通级 | M14: 直接对应 | N14: Doris | O14: dws.dws_fi_mr_wtzjcqkmx_mi | P14: cust_code
B15: =IFERROR(VLOOKUP(C15,'字段信息'!A:C,3,),"") | C15: cust_name | D15: =IFERROR(VLOOKUP(C15,'字段信息'!A:C,2,),"") | F15: =B15 | G15: √ | L15: 普通级 | M15: 直接对应 | N15: Doris | O15: dws.dws_fi_mr_wtzjcqkmx_mi | P15: cust_name
B16: =IFERROR(VLOOKUP(C16,'字段信息'!A:C,3,),"") | C16: cp_company_code | D16: =IFERROR(VLOOKUP(C16,'字段信息'!A:C,2,),"") | F16: =B16 | G16: √ | M16: 匹配客商映射对方公司dim.dim_rule_fi_mr_cust2ctp_mapping | N16: Doris | O16: dim.dim_rule_fi_mr_cust2ctp_mapping | P16: 优先取cp_company_code_mr，为空则取cp_company_code | Q16: 客商编码匹配客商映射对方公司映射表
B17: =IFERROR(VLOOKUP(C17,'字段信息'!A:C,3,),"") | C17: country_code | D17: =IFERROR(VLOOKUP(C17,'字段信息'!A:C,2,),"") | F17: =B17 | G17: √ | M17: 直接对应 | N17: Doris | O17: dws.dws_fi_mr_wtzjcqkmx_mi | P17: country_code
B18: =IFERROR(VLOOKUP(C18,'字段信息'!A:C,3,),"") | C18: country_name | D18: =IFERROR(VLOOKUP(C18,'字段信息'!A:C,2,),"") | F18: =B18 | G18: √ | M18: 直接对应 | N18: Doris | O18: dws.dws_fi_mr_wtzjcqkmx_mi | P18: country_name
B19: =IFERROR(VLOOKUP(C19,'字段信息'!A:C,3,),"") | C19: channel_l1_code | D19: =IFERROR(VLOOKUP(C19,'字段信息'!A:C,2,),"") | F19: =B19 | G19: √ | M19: 直接对应 | N19: Doris | O19: dws.dws_fi_mr_wtzjcqkmx_mi | P19: comp_cls_l1
B20: =IFERROR(VLOOKUP(C20,'字段信息'!A:C,3,),"") | C20: channel_l1_name | D20: =IFERROR(VLOOKUP(C20,'字段信息'!A:C,2,),"") | F20: =B20 | G20: √ | N20: Doris
B21: =IFERROR(VLOOKUP(C21,'字段信息'!A:C,3,),"") | C21: channel_l2_code | D21: =IFERROR(VLOOKUP(C21,'字段信息'!A:C,2,),"") | F21: =B21 | G21: √ | M21: 直接对应 | N21: Doris | O21: dws.dws_fi_mr_wtzjcqkmx_mi | P21: comp_cls_l2
B22: =IFERROR(VLOOKUP(C22,'字段信息'!A:C,3,),"") | C22: channel_l2_name | D22: =IFERROR(VLOOKUP(C22,'字段信息'!A:C,2,),"") | F22: =B22 | G22: √ | N22: Doris
B23: =IFERROR(VLOOKUP(C23,'字段信息'!A:C,3,),"") | C23: channel_l3_code | D23: =IFERROR(VLOOKUP(C23,'字段信息'!A:C,2,),"") | F23: =B23 | G23: √ | M23: 直接对应 | N23: Doris | O23: dws.dws_fi_mr_wtzjcqkmx_mi | P23: comp_cls_l3
B24: =IFERROR(VLOOKUP(C24,'字段信息'!A:C,3,),"") | C24: channel_l3_name | D24: =IFERROR(VLOOKUP(C24,'字段信息'!A:C,2,),"") | F24: =B24 | G24: √ | N24: Doris
B25: =IFERROR(VLOOKUP(C25,'字段信息'!A:C,3,),"") | C25: onoffline_code | D25: =IFERROR(VLOOKUP(C25,'字段信息'!A:C,2,),"") | F25: =B25 | G25: √ | M25: 直接对应 | N25: Doris | O25: dws.dws_fi_mr_wtzjcqkmx_mi | P25: channel_group
B26: =IFERROR(VLOOKUP(C26,'字段信息'!A:C,3,),"") | C26: onoffline_name | D26: =IFERROR(VLOOKUP(C26,'字段信息'!A:C,2,),"") | F26: =B26 | G26: √
B27: =IFERROR(VLOOKUP(C27,'字段信息'!A:C,3,),"") | C27: src_profitcenter_code | D27: =IFERROR(VLOOKUP(C27,'字段信息'!A:C,2,),"") | F27: =B27 | G27: √ | L27: 普通级 | M27: 直接对应 | N27: Doris | O27: dws.dws_fi_mr_wtzjcqkmx_mi | P27: profit_center_code
B28: =IFERROR(VLOOKUP(C28,'字段信息'!A:C,3,),"") | C28: src_profitcenter_name | D28: =IFERROR(VLOOKUP(C28,'字段信息'!A:C,2,),"") | F28: =B28 | G28: √ | L28: 普通级 | M28: 直接对应 | N28: Doris | O28: dws.dws_fi_mr_wtzjcqkmx_mi | P28: profit_center_name
B29: =IFERROR(VLOOKUP(C29,'字段信息'!A:C,3,),"") | C29: profitcenter_code | D29: =IFERROR(VLOOKUP(C29,'字段信息'!A:C,2,),"") | F29: =B29 | G29: √ | L29: 普通级 | M29: 直接对应 | N29: Doris | O29: dws.dws_fi_mr_wtzjcqkmx_mi | P29: profit_center_code
B30: =IFERROR(VLOOKUP(C30,'字段信息'!A:C,3,),"") | C30: profitcenter_name | D30: =IFERROR(VLOOKUP(C30,'字段信息'!A:C,2,),"") | F30: =B30 | G30: √ | L30: 普通级 | M30: 直接对应 | N30: Doris | O30: dws.dws_fi_mr_wtzjcqkmx_mi | P30: profit_center_name
B31: =IFERROR(VLOOKUP(C31,'字段信息'!A:C,3,),"") | C31: bus_range_code | D31: =IFERROR(VLOOKUP(C31,'字段信息'!A:C,2,),"") | F31: =B31 | G31: √ | M31: 直接对应 | N31: Doris | O31: dws.dws_fi_mr_wtzjcqkmx_mi | P31: bus_scope_code
B32: =IFERROR(VLOOKUP(C32,'字段信息'!A:C,3,),"") | C32: bus_range_name | D32: =IFERROR(VLOOKUP(C32,'字段信息'!A:C,2,),"") | F32: =B32 | G32: √ | M32: 直接对应 | N32: Doris | O32: dws.dws_fi_mr_wtzjcqkmx_mi | P32: bus_scope_desc
B33: =IFERROR(VLOOKUP(C33,'字段信息'!A:C,3,),"") | C33: marketing_dept_code | D33: =IFERROR(VLOOKUP(C33,'字段信息'!A:C,2,),"") | F33: =B33 | G33: √ | M33: 直接对应 | N33: Doris | O33: dws.dws_fi_mr_wtzjcqkmx_mi | P33: biz_mgmt_unit
B34: =IFERROR(VLOOKUP(C34,'字段信息'!A:C,3,),"") | C34: marketing_dept_name | D34: =IFERROR(VLOOKUP(C34,'字段信息'!A:C,2,),"") | F34: =B34 | G34: √
B35: =IFERROR(VLOOKUP(C35,'字段信息'!A:C,3,),"") | C35: bcy_code | D35: =IFERROR(VLOOKUP(C35,'字段信息'!A:C,2,),"") | F35: =B35 | G35: √ | V35: CNY
B36: =IFERROR(VLOOKUP(C36,'字段信息'!A:C,3,),"") | C36: qcy_code | D36: =IFERROR(VLOOKUP(C36,'字段信息'!A:C,2,),"") | F36: =B36 | G36: √ | V36: CNY
B37: =IFERROR(VLOOKUP(C37,'字段信息'!A:C,3,),"") | C37: overdue_1_amt | D37: =IFERROR(VLOOKUP(C37,'字段信息'!A:C,2,),"") | F37: =B37 | G37: √
B38: =IFERROR(VLOOKUP(C38,'字段信息'!A:C,3,),"") | C38: overdue_2_amt | D38: =IFERROR(VLOOKUP(C38,'字段信息'!A:C,2,),"") | F38: =B38 | G38: √
B39: =IFERROR(VLOOKUP(C39,'字段信息'!A:C,3,),"") | C39: overdue_3_amt | D39: =IFERROR(VLOOKUP(C39,'字段信息'!A:C,2,),"") | F39: =B39 | G39: √
B40: =IFERROR(VLOOKUP(C40,'字段信息'!A:C,3,),"") | C40: overdue_4_amt | D40: =IFERROR(VLOOKUP(C40,'字段信息'!A:C,2,),"") | F40: =B40 | G40: √
B41: =IFERROR(VLOOKUP(C41,'字段信息'!A:C,3,),"") | C41: overdue_5_amt | D41: =IFERROR(VLOOKUP(C41,'字段信息'!A:C,2,),"") | F41: =B41 | G41: √
B42: =IFERROR(VLOOKUP(C42,'字段信息'!A:C,3,),"") | C42: overdue_6_amt | D42: =IFERROR(VLOOKUP(C42,'字段信息'!A:C,2,),"") | F42: =B42 | G42: √
B43: =IFERROR(VLOOKUP(C43,'字段信息'!A:C,3,),"") | C43: overdue_7_amt | D43: =IFERROR(VLOOKUP(C43,'字段信息'!A:C,2,),"") | F43: =B43 | G43: √
B44: =IFERROR(VLOOKUP(C44,'字段信息'!A:C,3,),"") | C44: overdue_8_amt | D44: =IFERROR(VLOOKUP(C44,'字段信息'!A:C,2,),"") | F44: =B44 | G44: √
B45: =IFERROR(VLOOKUP(C45,'字段信息'!A:C,3,),"") | C45: overdue_9_amt | D45: =IFERROR(VLOOKUP(C45,'字段信息'!A:C,2,),"") | F45: =B45 | G45: √
B46: =IFERROR(VLOOKUP(C46,'字段信息'!A:C,3,),"") | C46: overdue_0_amt | D46: =IFERROR(VLOOKUP(C46,'字段信息'!A:C,2,),"") | F46: =B46 | G46: √ | L46: 普通级 | M46: 超期款金额-超期款调整金额 | N46: Doris | O46: dws.dws_fi_mr_wtzjcqkmx_mi | P46: overdue_amt - overdue_adj_amt | V46: 直接对应 | W46: Doris | X46: ods.odsfipf_tk_hfi_jtb_bjtwtzjtz | Y46: fk_hifi_tzje
B47: =IFERROR(VLOOKUP(C47,'字段信息'!A:C,3,),"") | C47: inv_sample_amt | D47: =IFERROR(VLOOKUP(C47,'字段信息'!A:C,2,),"") | F47: =B47 | G47: √ | L47: 普通级 | M47: 直接对应 | N47: Doris | O47: dws.dws_fi_mr_wtzjcqkmx_mi | P47: inv_sample_amt
B48: =IFERROR(VLOOKUP(C48,'字段信息'!A:C,3,),"") | C48: ods_src | D48: =IFERROR(VLOOKUP(C48,'字段信息'!A:C,2,),"") | F48: =B48 | G48: √ | L48: 普通级 | M48: 固定值 | N48: Doris | V48: 固定值 | W48: Doris
B49: =IFERROR(VLOOKUP(C49,'字段信息'!A:C,3,),"") | C49: load_dt | D49: =IFERROR(VLOOKUP(C49,'字段信息'!A:C,2,),"") | F49: =B49 | G49: √ | L49: 普通级 | M49: NOW() | N49: Doris | V49: NOW() | W49: Doris

Sheet dwd_fi_mr_ar_ureb_mi
A1: 返回 | B1: dwd_fi_mr_ar_ureb_mi逻辑处理
A2: 规则库 | B2: 表名称 | C2: dwd.dwd_fi_mr_ar_ureb_mi
B3: 表描述 | C3: 欠付返利明细表 | D3: 表类型 | E3: 事实表 | F3: 数仓分层 | G3: DWD
B4: L1数仓目录 | C4: 管理财经 | D4: L2数仓目录 | E4: 财报管理 | F4: L3数仓目录 | G4: 收入
B5: 更新方式 | C5: 增量更新 | D5: 设计人员 | F5: 时间 | M5: 待确认：1、数据更新机制；2、不到利润中心怎么匹配--日立的往来数据不到利润中心
B6: 使用场景 | C6: 取SMS系统、政策系统、SAP系统的欠付返利明细 | M6: 0908：前面要再加一个静态存数的表，和用户沟通风险点，最好是前端系统存静态数据
B7: 目标表 | M7: SMS经销商返利余额汇总管理表 | V7: 已确认未兑现政策余额数据 | AE7: SAP客户行项目明细
B8: 字段中文名称 | C8: *字段名称 | D8: *类型 | E8: 主键 | F8: *描述 | G8: 允许为空 | H8: 默认值 | I8: 聚合类型 | J8: 基础标准 | K8: 标准代码 | L8: *安全分级 | M8: 转换清洗规则 | N8: 源系统 | O8: 源头表 | P8: 源头字段 | Q8: 匹配字段 | R8: 匹配过滤 | S8: 数仓处理脚本 | T8: 备注 | V8: 转换清洗规则 | W8: 源系统 | X8: 源头表 | Y8: 源头字段 | Z8: 匹配字段 | AA8: 匹配过滤 | AB8: 数仓处理脚本 | AC8: 备注 | AE8: 转换清洗规则 | AF8: 源系统 | AG8: 源头表 | AH8: 源头字段 | AI8: 匹配字段 | AJ8: 匹配过滤 | AK8: 数仓处理脚本 | AL8: 备注
B9: =IFERROR(VLOOKUP(C9,'字段信息'!A:C,3,),"") | C9: dt_month | D9: =IFERROR(VLOOKUP(C9,'字段信息'!A:C,2,),"") | F9: =B9 | M9: 参数年月 | V9: 参数年月 | W9: Doris | X9: ods.ods_plc_v_hpms_account_gb | Y9: period | AE9: 参数年月 | AG9: dwd_fi_mr_arap_detail_mi | AH9: dt_month
B10: =IFERROR(VLOOKUP(C10,'字段信息'!A:C,3,),"") | C10: year | D10: =IFERROR(VLOOKUP(C10,'字段信息'!A:C,2,),"") | F10: =B10 | G10: √ | L10: 普通级 | M10: 参数年 | N10: Doris | V10: 参数年 | W10: Doris | X10: ods.ods_plc_v_hpms_account_gb | Y10: LEFT(period,4) | AE10: 参数年 | AF10: Doris | AG10: dwd_fi_mr_arap_detail_mi | AH10: year
B11: =IFERROR(VLOOKUP(C11,'字段信息'!A:C,3,),"") | C11: month | D11: =IFERROR(VLOOKUP(C11,'字段信息'!A:C,2,),"") | F11: =B11 | G11: √ | L11: 普通级 | M11: 参数月 | N11: Doris | V11: 参数月 | W11: Doris | X11: ods.ods_plc_v_hpms_account_gb | Y11: RIGHT(period,2) | AE11: 参数月 | AF11: Doris | AG11: dwd_fi_mr_arap_detail_mi | AH11: month
B12: =IFERROR(VLOOKUP(C12,'字段信息'!A:C,3,),"") | C12: company_code | D12: =IFERROR(VLOOKUP(C12,'字段信息'!A:C,2,),"") | F12: =B12 | G12: √ | L12: 普通级 | M12: 直接对应 | N12: Doris | O12: dwd_ltc_cem_reportpay_balance_summary_dd | P12: company_code | V12: 直接对应 | W12: Doris | X12: ods.ods_plc_v_hpms_account_gb | Y12: sales_group | AE12: 直接对应 | AF12: Doris | AG12: dwd_fi_mr_arap_detail_mi | AH12: company_code
B13: 客商编码 | C13: cust_code | D13: =IFERROR(VLOOKUP(C13,'字段信息'!A:C,2,),"") | F13: =B13 | G13: √ | L13: 普通级 | M13: 直接对应 | N13: Doris | O13: dwd_ltc_cem_reportpay_balance_summary_dd | P13: sales_code | V13: 直接对应 | W13: Doris | X13: ods.ods_plc_v_hpms_account_gb | Y13: customer_code | AE13: 直接对应 | AF13: Doris | AG13: dwd_fi_mr_arap_detail_mi | AH13: customer_code
B14: 客商名称 | C14: cust_name | D14: =IFERROR(VLOOKUP(C14,'字段信息'!A:C,2,),"") | F14: =B14 | G14: √ | L14: 普通级 | M14: 直接对应 | N14: Doris | O14: dwd_ltc_cem_reportpay_balance_summary_dd | P14: sname | V14: 直接对应 | W14: Doris | X14: ods.ods_plc_v_hpms_account_gb | Y14: customer_name | AE14: 直接对应 | AF14: Doris | AG14: dwd_fi_mr_arap_detail_mi | AH14: customer_name
B15: =IFERROR(VLOOKUP(C15,'字段信息'!A:C,3,),"") | C15: cp_company_code | D15: =IFERROR(VLOOKUP(C15,'字段信息'!A:C,2,),"") | F15: =B15 | G15: √ | M15: 匹配客商映射对方公司dim.dim_rule_fi_mr_cust2ctp_mapping | N15: Doris | O15: dim.dim_rule_fi_mr_cust2ctp_mapping | P15: 优先取cp_company_code_mr，为空则取cp_company_code | Q15: 客商编码匹配客商映射对方公司映射表 | V15: 匹配客商映射对方公司dim.dim_rule_fi_mr_cust2ctp_mapping | W15: Doris | X15: dim.dim_rule_fi_mr_cust2ctp_mapping | Y15: 优先取cp_company_code_mr，为空则取cp_company_code | Z15: 客商编码匹配客商映射对方公司映射表 | AE15: 直接对应 | AF15: Doris | AG15: dwd_fi_mr_arap_detail_mi | AH15: cp_company_code
B16: =IFERROR(VLOOKUP(C16,'字段信息'!A:C,3,),"") | C16: country_code | D16: =IFERROR(VLOOKUP(C16,'字段信息'!A:C,2,),"") | F16: =B16 | G16: √ | M16: 匹配mdg客户主数据得到对应字段 | N16: Doris | O16: dw.dim_customer_base_info_dd-客户主数据基本信息 | P16: country_code | Q16: kunnr_mdg = cust_code | V16: 匹配mdg客户主数据得到对应字段 | W16: Doris | X16: dw.dim_customer_base_info_dd-客户主数据基本信息 | Y16: country_code | Z16: kunnr_mdg = cust_code | AE16: 直接对应 | AF16: Doris | AG16: dwd_fi_mr_arap_detail_mi | AH16: country_code
B17: =IFERROR(VLOOKUP(C17,'字段信息'!A:C,3,),"") | C17: country_name | D17: =IFERROR(VLOOKUP(C17,'字段信息'!A:C,2,),"") | F17: =B17 | G17: √ | M17: 匹配mdg客户主数据得到对应字段 | N17: Doris | O17: dw.dim_customer_base_info_dd-客户主数据基本信息 | P17: country_code | Q17: kunnr_mdg = cust_code | V17: 匹配mdg客户主数据得到对应字段 | W17: Doris | X17: dw.dim_customer_base_info_dd-客户主数据基本信息 | Y17: country_code | Z17: kunnr_mdg = cust_code | AE17: 直接对应 | AF17: Doris | AG17: dwd_fi_mr_arap_detail_mi | AH17: country_code
B18: =IFERROR(VLOOKUP(C18,'字段信息'!A:C,3,),"") | C18: src_profitcenter_code | D18: =IFERROR(VLOOKUP(C18,'字段信息'!A:C,2,),"") | F18: =B18 | G18: √ | L18: 普通级 | M18: / | V18: 直接对应 | W18: Doris | X18: ods.ods_plc_v_hpms_account_gb | Y18: profit_center | AE18: 直接对应 | AF18: Doris | AG18: dwd_fi_mr_arap_detail_mi | AH18: src_profitcenter_code
B19: =IFERROR(VLOOKUP(C19,'字段信息'!A:C,3,),"") | C19: src_profitcenter_name | D19: =IFERROR(VLOOKUP(C19,'字段信息'!A:C,2,),"") | F19: =B19 | G19: √ | L19: 普通级 | M19: / | V19: / | AE19: 直接对应 | AF19: Doris | AG19: dwd_fi_mr_arap_detail_mi | AH19: src_profitcenter_name
B20: =IFERROR(VLOOKUP(C20,'字段信息'!A:C,3,),"") | C20: profitcenter_code | D20: =IFERROR(VLOOKUP(C20,'字段信息'!A:C,2,),"") | F20: =B20 | G20: √ | M20: / | V20: 匹配《应收模块-利润中心映射表》，筛选映射类型为“收入利润中心映射往来利润中心”，将收入利润中心映射成应收利润中心 | W20: Doris | X20: dim_rule_fi_mr_ar_prctr_map经分项目应收模块-利润中心映射表 | AE20: 直接对应 | AF20: Doris | AG20: dwd_fi_mr_arap_detail_mi | AH20: profitcenter_code
B21: =IFERROR(VLOOKUP(C21,'字段信息'!A:C,3,),"") | C21: profitcenter_name | D21: =IFERROR(VLOOKUP(C21,'字段信息'!A:C,2,),"") | F21: =B21 | G21: √ | M21: / | V21: 匹配《应收模块-利润中心映射表》，筛选映射类型为“收入利润中心映射往来利润中心”，将收入利润中心映射成应收利润中心 | W21: Doris | X21: dim_rule_fi_mr_ar_prctr_map经分项目应收模块-利润中心映射表 | AE21: 直接对应 | AF21: Doris | AG21: dwd_fi_mr_arap_detail_mi | AH21: profitcenter_name
B22: =IFERROR(VLOOKUP(C22,'字段信息'!A:C,3,),"") | C22: reb_type | D22: =IFERROR(VLOOKUP(C22,'字段信息'!A:C,2,),"") | F22: =B22 | G22: √ | M22: 直接对应 | N22: Doris | O22: dwd_ltc_cem_reportpay_balance_summary_dd | P22: leibie | V22: 直接对应 | W22: Doris | AE22: / | AF22: Doris
B23: =IFERROR(VLOOKUP(C23,'字段信息'!A:C,3,),"") | C23: ledger_status | D23: =IFERROR(VLOOKUP(C23,'字段信息'!A:C,2,),"") | F23: =B23 | G23: √ | M23: / | N23: Doris | V23: 直接对应 | W23: Doris | X23: ods.ods_plc_v_hpms_account_gb | Y23: policystatename | AA23: 已确认未兑现：兑现过程中、确认完成 已计提未兑现：待确认 | AE23: / | AF23: Doris
B24: =IFERROR(VLOOKUP(C24,'字段信息'!A:C,3,),"") | C24: acct_cert_type | D24: =IFERROR(VLOOKUP(C24,'字段信息'!A:C,2,),"") | F24: =B24 | G24: √ | M24: / | V24: / | AE24: 直接对应 | AF24: Doris | AG24: dwd_fi_mr_arap_detail_mi | AH24: acct_cert_type | AJ24: zz
B25: =IFERROR(VLOOKUP(C25,'字段信息'!A:C,3,),"") | C25: pay_reason_code | D25: =IFERROR(VLOOKUP(C25,'字段信息'!A:C,2,),"") | F25: =B25 | G25: √ | M25: / | V25: / | AE25: 直接对应 | AF25: Doris | AG25: dwd_fi_mr_arap_detail_mi | AH25: pay_reason_code | AJ25: 600 | AK25: 0908：从凭证明细表中取，根据打的标签来判断
B26: =IFERROR(VLOOKUP(C26,'字段信息'!A:C,3,),"") | C26: bcy_code | D26: =IFERROR(VLOOKUP(C26,'字段信息'!A:C,2,),"") | F26: =B26 | G26: √ | L26: 普通级 | M26: 固定CNY | N26: Doris | O26: CNY | V26: 固定CNY | W26: Doris | X26: ods.ods_plc_v_hpms_account_gb | Y26: CNY | AE26: 直接对应 | AF26: Doris | AG26: dwd_fi_mr_arap_detail_mi | AH26: bcy_code | AJ26: 筛选ods_src为bsid且acct_map_code为1122%
B27: =IFERROR(VLOOKUP(C27,'字段信息'!A:C,3,),"") | C27: qcy_code | D27: =IFERROR(VLOOKUP(C27,'字段信息'!A:C,2,),"") | F27: =B27 | G27: √ | L27: 普通级 | M27: 固定CNY | N27: Doris | O27: CNY | V27: 固定CNY | W27: Doris | X27: ods.ods_plc_v_hpms_account_gb | Y27: CNY | AE27: 直接对应 | AF27: Doris | AG27: dwd_fi_mr_arap_detail_mi | AH27: qcy_code
B28: =IFERROR(VLOOKUP(C28,'字段信息'!A:C,3,),"") | C28: bcy_amt | D28: =IFERROR(VLOOKUP(C28,'字段信息'!A:C,2,),"") | F28: =B28 | G28: √ | L28: 普通级 | M28: 直接对应 | N28: Doris | O28: dwd_ltc_cem_reportpay_balance_summary_dd | P28: yue | V28: 直接对应 | W28: Doris | X28: ods.ods_plc_v_hpms_account_gb | Y28: arrears_amount | AE28: 直接对应 | AF28: Doris | AG28: dwd_fi_mr_arap_detail_mi | AH28: bcy_amt
B29: =IFERROR(VLOOKUP(C29,'字段信息'!A:C,3,),"") | C29: qcy_amt | D29: =IFERROR(VLOOKUP(C29,'字段信息'!A:C,2,),"") | F29: =B29 | G29: √ | L29: 普通级 | M29: 直接对应 | N29: Doris | O29: dwd_ltc_cem_reportpay_balance_summary_dd | P29: yue | V29: 直接对应 | W29: Doris | X29: ods.ods_plc_v_hpms_account_gb | Y29: arrears_amount | AE29: 直接对应 | AF29: Doris | AG29: dwd_fi_mr_arap_detail_mi | AH29: qcy_amt
B30: =IFERROR(VLOOKUP(C30,'字段信息'!A:C,3,),"") | C30: ods_src | D30: =IFERROR(VLOOKUP(C30,'字段信息'!A:C,2,),"") | F30: =B30 | G30: √ | L30: 普通级 | M30: 固定值 | N30: Doris | P30: SMS | V30: 固定值 | W30: Doris | Y30: policy | AE30: 固定值 | AF30: Doris | AK30: SAP
B31: =IFERROR(VLOOKUP(C31,'字段信息'!A:C,3,),"") | C31: load_dt | D31: =IFERROR(VLOOKUP(C31,'字段信息'!A:C,2,),"") | F31: =B31 | G31: √ | L31: 普通级 | M31: 数据更新时间 | N31: Doris | V31: 数据更新时间 | W31: Doris | AE31: 数据更新时间 | AF31: Doris

Sheet dwd_fi_mr_ar_imocc_mi
A1: 返回 | B1: dwd_fi_mr_ar_imocc_mi逻辑处理
A2: 规则库 | B2: 表名称 | C2: dwd.dwd_fi_mr_ar_imocc_mi
B3: 表描述 | C3: 国际营销应收占用明细表 | D3: 表类型 | E3: 事实表 | F3: 数仓分层 | G3: DWD
B4: L1数仓目录 | C4: 管理财经 | D4: L2数仓目录 | E4: 财报管理 | F4: L3数仓目录 | G4: 应收
B5: 更新方式 | C5: 增量更新 | D5: 设计人员 | F5: 时间
B6: 使用场景 | C6: 取信数系统中国际营销对外的的应收占用数据
B7: 目标表 | M7: 国际营销占用ads.ads_fi_mr_accounts_rec_di
B8: 字段中文名称 | C8: *字段名称 | D8: *类型 | E8: 主键 | F8: *描述 | G8: 允许为空 | H8: 默认值 | I8: 聚合类型 | J8: 基础标准 | K8: 标准代码 | L8: *安全分级 | M8: 转换清洗规则 | N8: 源系统 | O8: 源头表 | P8: 源头字段 | Q8: 匹配字段 | R8: 匹配过滤 | S8: 数仓处理脚本 | T8: 备注
B9: =IFERROR(VLOOKUP(C9,'字段信息'!A:C,3,),"") | C9: dt_month | D9: =IFERROR(VLOOKUP(C9,'字段信息'!A:C,2,),"") | F9: =B9 | M9: 直接对应 | N9: 参数年月 | O9: ads.ads_fi_mr_accounts_rec_di | P9: month_dt
B10: =IFERROR(VLOOKUP(C10,'字段信息'!A:C,3,),"") | C10: year | D10: =IFERROR(VLOOKUP(C10,'字段信息'!A:C,2,),"") | F10: =B10 | G10: √ | M10: 直接对应 | N10: 参数年 | O10: ads.ads_fi_mr_accounts_rec_di | P10: month_dt截取年份
B11: =IFERROR(VLOOKUP(C11,'字段信息'!A:C,3,),"") | C11: month | D11: =IFERROR(VLOOKUP(C11,'字段信息'!A:C,2,),"") | F11: =B11 | G11: √ | L11: 普通级 | M11: 直接对应 | N11: 参数月 | O11: ads.ads_fi_mr_accounts_rec_di | P11: month_dt截取月份
B12: =IFERROR(VLOOKUP(C12,'字段信息'!A:C,3,),"") | C12: company_src_code | D12: =IFERROR(VLOOKUP(C12,'字段信息'!A:C,2,),"") | F12: =B12 | G12: √ | L12: 普通级 | M12: 直接对应 | N12: Doris | O12: ads.ads_fi_mr_accounts_rec_di | P12: bukrs
B13: =IFERROR(VLOOKUP(C13,'字段信息'!A:C,3,),"") | C13: company_code | D13: =IFERROR(VLOOKUP(C13,'字段信息'!A:C,2,),"") | F13: =B13 | G13: √ | M13: 根据条件判断 1、商显公司2080： 取product_line_code=01A0 OR region_flag为‘B2B业务拓展部’的数据 2、日立公司1740： region_flag为‘产品线大区’ AND product_line_code=0207 其余默认放8010
B14: =IFERROR(VLOOKUP(C14,'字段信息'!A:C,3,),"") | C14: region_code | D14: =IFERROR(VLOOKUP(C14,'字段信息'!A:C,2,),"") | F14: =B14 | G14: √ | M14: 直接对应 | N14: Doris | O14: ads.ads_fi_mr_accounts_rec_di | P14: rgn
B15: =IFERROR(VLOOKUP(C15,'字段信息'!A:C,3,),"") | C15: region_name | D15: =IFERROR(VLOOKUP(C15,'字段信息'!A:C,2,),"") | F15: =B15 | G15: √ | M15: 匹配区组主数据 | N15: Doris | O15: ads.ads_fi_mr_accounts_rec_didw.dwsd_im_td_bdr_area_group a2--区组主数据 | P15: rgn_zh
B16: =IFERROR(VLOOKUP(C16,'字段信息'!A:C,3,),"") | C16: region_flag | D16: =IFERROR(VLOOKUP(C16,'字段信息'!A:C,2,),"") | F16: =B16 | G16: √ | M16: 匹配区组主数据和产品线主数据进行判断 | N16: Doris | O16: ads.ads_fi_mr_accounts_rec_di dw.dwsd_im_td_bdr_area_group a2--区组主数据 dw.dwfi_im_td_product_category a3--产品线主数据 | P16: case when A1.month_dt>='202504' AND (A3.prdln in ('0207','0403','0401','0402') OR (A3.prdln='01A0' AND A2.grp<>'D0090')) then '产品线大区' when A1.month_dt<'202504' AND A3.prdln in ('0207','01A0','0403','0401','0402') then '产品线大区' when (A2.rgn_zh is null and A3.prdln not in ('0207','01A0','0403','0401','0402')) or A1.type ='8002' then '欧洲区' else A2.rgn_zh end | Q16: a1.grp=a2.grp a1.prdln=a3.prdln | R16: 产品线主数据需要现在enable_flag='T'
B17: =IFERROR(VLOOKUP(C17,'字段信息'!A:C,3,),"") | C17: area_group_code | D17: =IFERROR(VLOOKUP(C17,'字段信息'!A:C,2,),"") | F17: =B17 | G17: √ | M17: 直接对应 | N17: Doris | O17: ads.ads_fi_mr_accounts_rec_di | P17: grp
B18: =IFERROR(VLOOKUP(C18,'字段信息'!A:C,3,),"") | C18: area_group_name | D18: =IFERROR(VLOOKUP(C18,'字段信息'!A:C,2,),"") | F18: =B18 | G18: √ | M18: 匹配区组主数据 | N18: Doris | O18: ads.ads_fi_mr_accounts_rec_di dw.dwsd_im_td_bdr_area_group a2--区组主数据 | P18: grp_zh
B19: =IFERROR(VLOOKUP(C19,'字段信息'!A:C,3,),"") | C19: area_group_flag | D19: =IFERROR(VLOOKUP(C19,'字段信息'!A:C,2,),"") | F19: =B19 | G19: √ | M19: 匹配区组主数据 | N19: Doris | O19: ads.ads_fi_mr_accounts_rec_di dw.dwsd_im_td_bdr_area_group a2--区组主数据 | P19: case when A1.type ='8002' then '欧洲海外' else A2.grp_zh end | Q19: a1.grp=a2.grp
B20: =IFERROR(VLOOKUP(C20,'字段信息'!A:C,3,),"") | C20: bus_model_code | D20: =IFERROR(VLOOKUP(C20,'字段信息'!A:C,2,),"") | F20: =B20 | G20: √ | M20: 直接对应 | N20: Doris | O20: ads.ads_fi_mr_accounts_rec_di | P20: bus_model
B21: =IFERROR(VLOOKUP(C21,'字段信息'!A:C,3,),"") | C21: product_big_class_code | D21: =IFERROR(VLOOKUP(C21,'字段信息'!A:C,2,),"") | F21: =B21 | G21: √ | M21: 直接对应 | N21: Doris | O21: ads.ads_fi_mr_accounts_rec_di | P21: prdctgy
B22: =IFERROR(VLOOKUP(C22,'字段信息'!A:C,3,),"") | C22: product_big_class_name | D22: =IFERROR(VLOOKUP(C22,'字段信息'!A:C,2,),"") | F22: =B22 | G22: √ | M22: 匹配产品线主数据进行判断 | N22: Doris | O22: ads.ads_fi_mr_accounts_rec_di dw.dwfi_im_td_product_category a3--产品线主数据 | P22: prdctgy_zh | Q22: a1.prdln=a3.prdln | R22: 产品线主数据需要现在enable_flag='T'
B23: =IFERROR(VLOOKUP(C23,'字段信息'!A:C,3,),"") | C23: product_line_code | D23: =IFERROR(VLOOKUP(C23,'字段信息'!A:C,2,),"") | F23: =B23 | G23: √ | M23: 直接对应 | N23: Doris | O23: ads.ads_fi_mr_accounts_rec_di | P23: prdln
B24: =IFERROR(VLOOKUP(C24,'字段信息'!A:C,3,),"") | C24: product_line_name | D24: =IFERROR(VLOOKUP(C24,'字段信息'!A:C,2,),"") | F24: =B24 | G24: √ | M24: 匹配产品线主数据进行判断 | N24: Doris | O24: ads.ads_fi_mr_accounts_rec_di dw.dwfi_im_td_product_category a3--产品线主数据 | P24: prdln_zh | Q24: a1.prdln=a3.prdln | R24: 产品线主数据需要现在enable_flag='T'
B25: =IFERROR(VLOOKUP(C25,'字段信息'!A:C,3,),"") | C25: cust_pay_term | D25: =IFERROR(VLOOKUP(C25,'字段信息'!A:C,2,),"") | F25: =B25 | G25: √ | M25: 直接对应 | N25: Doris | O25: ads.ads_fi_mr_accounts_rec_di ods.odsmf_cm_tab1065 a5 | P25: case when a5.zterm_c is null then '其他' else a5.zterm_c end | Q25: a1.zterm=a5.zterm
B26: =IFERROR(VLOOKUP(C26,'字段信息'!A:C,3,),"") | C26: data_scope_code | D26: =IFERROR(VLOOKUP(C26,'字段信息'!A:C,2,),"") | F26: =B26 | G26: √ | M26: 直接对应 | N26: Doris | O26: ads.ads_fi_mr_accounts_rec_di | P26: extent
B27: =IFERROR(VLOOKUP(C27,'字段信息'!A:C,3,),"") | C27: cust_code | D27: =IFERROR(VLOOKUP(C27,'字段信息'!A:C,2,),"") | F27: =B27 | G27: √ | L27: 普通级 | M27: 直接对应 | N27: Doris | O27: ads.ads_fi_mr_accounts_rec_di | P27: kunnr
B28: =IFERROR(VLOOKUP(C28,'字段信息'!A:C,3,),"") | C28: cust_name | D28: =IFERROR(VLOOKUP(C28,'字段信息'!A:C,2,),"") | F28: =B28 | G28: √ | L28: 普通级 | M28: 如果客户主数据匹配不到则取科目主数据 | N28: Doris | O28: ads.ads_fi_mr_accounts_rec_di 1、ods.ods_slt_s810_kna1-客户主数据 2、ods.odsslt_s810_skat-科目主数据 mandt = '810' and spras = '1' | P28: cust_name txt_20
B29: =IFERROR(VLOOKUP(C29,'字段信息'!A:C,3,),"") | C29: cust_branch_code | D29: =IFERROR(VLOOKUP(C29,'字段信息'!A:C,2,),"") | F29: =B29 | G29: √ | M29: 直接对应 | N29: Doris | O29: ads.ads_fi_mr_accounts_rec_di | P29: custfundcode
B30: =IFERROR(VLOOKUP(C30,'字段信息'!A:C,3,),"") | C30: cust_branch_name | D30: =IFERROR(VLOOKUP(C30,'字段信息'!A:C,2,),"") | F30: =B30 | G30: √ | M30: 直接对应 | N30: Doris | O30: ads.ads_fi_mr_accounts_rec_di | P30: custfundname
B31: =IFERROR(VLOOKUP(C31,'字段信息'!A:C,3,),"") | C31: cp_company_code | D31: =IFERROR(VLOOKUP(C31,'字段信息'!A:C,2,),"") | F31: =B31 | G31: √ | M31: 匹配客商映射对方公司dim.dim_rule_fi_mr_cust2ctp_mapping | N31: Doris | O31: dim.dim_rule_fi_mr_cust2ctp_mapping | P31: 优先取cp_company_code_mr，为空则取cp_company_code | Q31: 客商编码匹配客商映射对方公司映射表
B32: =IFERROR(VLOOKUP(C32,'字段信息'!A:C,3,),"") | C32: country_code | D32: =IFERROR(VLOOKUP(C32,'字段信息'!A:C,2,),"") | F32: =B32 | G32: √ | L32: 普通级 | M32: 1、先匹配SAP客户主数据得到zkunnr_mdg 2、再匹配mdg客户主数据得到对应字段 | N32: Doris | O32: 1、ods.ods_slt_s810_kna1-客户主数据 2、dw.dim_customer_base_info_dd-客户主数据基本信息 | P32: 1、zkunnr_mdg 2、country_code | Q32: 1、kunnr = kunnr 2、zkunnr_mdg = cust_code
B33: =IFERROR(VLOOKUP(C33,'字段信息'!A:C,3,),"") | C33: country_name | D33: =IFERROR(VLOOKUP(C33,'字段信息'!A:C,2,),"") | F33: =B33 | G33: √ | M33: 1、先匹配SAP客户主数据得到zkunnr_mdg 2、再匹配mdg客户主数据得到对应字段 | N33: Doris | O33: 1、ods.ods_slt_s810_kna1-客户主数据 2、dw.dim_customer_base_info_dd-客户主数据基本信息 | P33: 1、zkunnr_mdg 2、country_name | Q33: 1、kunnr = kunnr 2、zkunnr_mdg = cust_code
B34: =IFERROR(VLOOKUP(C34,'字段信息'!A:C,3,),"") | C34: channel_l1_code | D34: =IFERROR(VLOOKUP(C34,'字段信息'!A:C,2,),"") | F34: =B34 | G34: √ | M34: 1、先匹配SAP客户主数据得到zkunnr_mdg 2、再匹配mdg客户主数据得到对应字段 | N34: Doris | O34: 1、ods.ods_slt_s810_kna1-客户主数据 2、dw.dim_customer_base_info_dd-客户主数据基本信息 | P34: 1、zkunnr_mdg 2、com_1st_code | Q34: 1、kunnr = kunnr 2、zkunnr_mdg = cust_code
B35: =IFERROR(VLOOKUP(C35,'字段信息'!A:C,3,),"") | C35: channel_l1_name | D35: =IFERROR(VLOOKUP(C35,'字段信息'!A:C,2,),"") | F35: =B35 | G35: √ | M35: 1、先匹配SAP客户主数据得到zkunnr_mdg 2、再匹配mdg客户主数据得到对应字段 | N35: Doris | O35: 1、ods.ods_slt_s810_kna1-客户主数据 2、dw.dim_customer_base_info_dd-客户主数据基本信息 | P35: 1、zkunnr_mdg 2、com_1st_name | Q35: 1、kunnr = kunnr 2、zkunnr_mdg = cust_code
B36: =IFERROR(VLOOKUP(C36,'字段信息'!A:C,3,),"") | C36: channel_l2_code | D36: =IFERROR(VLOOKUP(C36,'字段信息'!A:C,2,),"") | F36: =B36 | G36: √ | M36: 1、先匹配SAP客户主数据得到zkunnr_mdg 2、再匹配mdg客户主数据得到对应字段 | N36: Doris | O36: 1、ods.ods_slt_s810_kna1-客户主数据 2、dw.dim_customer_base_info_dd-客户主数据基本信息 | P36: 1、zkunnr_mdg 2、com_2nd_code | Q36: 1、kunnr = kunnr 2、zkunnr_mdg = cust_code
B37: =IFERROR(VLOOKUP(C37,'字段信息'!A:C,3,),"") | C37: channel_l2_name | D37: =IFERROR(VLOOKUP(C37,'字段信息'!A:C,2,),"") | F37: =B37 | G37: √ | M37: 1、先匹配SAP客户主数据得到zkunnr_mdg 2、再匹配mdg客户主数据得到对应字段 | N37: Doris | O37: 1、ods.ods_slt_s810_kna1-客户主数据 2、dw.dim_customer_base_info_dd-客户主数据基本信息 | P37: 1、zkunnr_mdg 2、com_2nd_name | Q37: 1、kunnr = kunnr 2、zkunnr_mdg = cust_code
B38: =IFERROR(VLOOKUP(C38,'字段信息'!A:C,3,),"") | C38: channel_l3_code | D38: =IFERROR(VLOOKUP(C38,'字段信息'!A:C,2,),"") | F38: =B38 | G38: √ | M38: 1、先匹配SAP客户主数据得到zkunnr_mdg 2、再匹配mdg客户主数据得到对应字段 | N38: Doris | O38: 1、ods.ods_slt_s810_kna1-客户主数据 2、dw.dim_customer_base_info_dd-客户主数据基本信息 | P38: 1、zkunnr_mdg 2、com_3rd_code | Q38: 1、kunnr = kunnr 2、zkunnr_mdg = cust_code
B39: =IFERROR(VLOOKUP(C39,'字段信息'!A:C,3,),"") | C39: channel_l3_name | D39: =IFERROR(VLOOKUP(C39,'字段信息'!A:C,2,),"") | F39: =B39 | G39: √ | M39: 1、先匹配SAP客户主数据得到zkunnr_mdg 2、再匹配mdg客户主数据得到对应字段 | N39: Doris | O39: 1、ods.ods_slt_s810_kna1-客户主数据 2、dw.dim_customer_base_info_dd-客户主数据基本信息 | P39: 1、zkunnr_mdg 2、com_3rd_name | Q39: 1、kunnr = kunnr 2、zkunnr_mdg = cust_code
B40: =IFERROR(VLOOKUP(C40,'字段信息'!A:C,3,),"") | C40: bus_range_code | D40: =IFERROR(VLOOKUP(C40,'字段信息'!A:C,2,),"") | F40: =B40 | G40: √
B41: =IFERROR(VLOOKUP(C41,'字段信息'!A:C,3,),"") | C41: bus_range_name | D41: =IFERROR(VLOOKUP(C41,'字段信息'!A:C,2,),"") | F41: =B41 | G41: √
B42: =IFERROR(VLOOKUP(C42,'字段信息'!A:C,3,),"") | C42: profitcenter_code | D42: =IFERROR(VLOOKUP(C42,'字段信息'!A:C,2,),"") | F42: =B42 | G42: √ | M42: 公司为2080： 客户名称如果包含“119项目”，则输出X00000002，其他输出101008002 公司为1740：ZZZZ
B43: =IFERROR(VLOOKUP(C43,'字段信息'!A:C,3,),"") | C43: profitcenter_name | D43: =IFERROR(VLOOKUP(C43,'字段信息'!A:C,2,),"") | F43: =B43 | G43: √ | M43: 公司为2080： 客户名称如果包含“119项目”，则输出商显大项目，其他输出海信商用显示-触控平板-会议 公司为1740：缺省
B44: =IFERROR(VLOOKUP(C44,'字段信息'!A:C,3,),"") | C44: bcy_code | D44: =IFERROR(VLOOKUP(C44,'字段信息'!A:C,2,),"") | F44: =B44 | G44: √ | M44: 直接对应 | N44: Doris | O44: ads.ads_fi_mr_accounts_rec_di | P44: sm
B45: =IFERROR(VLOOKUP(C45,'字段信息'!A:C,3,),"") | C45: qcy_code | D45: =IFERROR(VLOOKUP(C45,'字段信息'!A:C,2,),"") | F45: =B45 | G45: √ | M45: 固定值 CNY
B46: =IFERROR(VLOOKUP(C46,'字段信息'!A:C,3,),"") | C46: imocc_cny_amt | D46: =IFERROR(VLOOKUP(C46,'字段信息'!A:C,2,),"") | F46: =B46 | G46: √ | L46: 普通级 | M46: 直接对应 | N46: Doris | O46: ads.ads_fi_mr_accounts_rec_di | P46: end_amt_cny_m
B47: =IFERROR(VLOOKUP(C47,'字段信息'!A:C,3,),"") | C47: imocc_con_amt | D47: =IFERROR(VLOOKUP(C47,'字段信息'!A:C,2,),"") | F47: =B47 | G47: √ | L47: 普通级 | M47: 直接对应 | N47: Doris | O47: ads.ads_fi_mr_accounts_rec_di | P47: end_amt_usd_m
B48: =IFERROR(VLOOKUP(C48,'字段信息'!A:C,3,),"") | C48: imocc_usd_amt | D48: =IFERROR(VLOOKUP(C48,'字段信息'!A:C,2,),"") | F48: =B48 | G48: √ | L48: 普通级 | M48: 直接对应 | N48: Doris | O48: ads.ads_fi_mr_accounts_rec_di | P48: end_amt_cod_m
B49: =IFERROR(VLOOKUP(C49,'字段信息'!A:C,3,),"") | C49: ods_src | D49: =IFERROR(VLOOKUP(C49,'字段信息'!A:C,2,),"") | F49: =B49 | G49: √ | L49: 普通级 | M49: IMOCC | N49: Doris
B50: =IFERROR(VLOOKUP(C50,'字段信息'!A:C,3,),"") | C50: load_dt | D50: =IFERROR(VLOOKUP(C50,'字段信息'!A:C,2,),"") | F50: =B50 | G50: √ | L50: 普通级 | M50: NOW() | N50: Doris

Sheet dwd_fi_mr_ar_writeoff_mi
A1: 返回 | B1: dwd_fi_mr_ar_writeoff_mi逻辑处理
A2: 规则库 | B2: 表名称 | C2: dwd.dwd_fi_mr_ar_writeoff_mi
B3: 表描述 | C3: 核销金额明细表 | D3: 表类型 | E3: 事实表 | F3: 数仓分层 | G3: DWD
B4: L1数仓目录 | C4: 管理财经 | D4: L2数仓目录 | E4: 财报管理 | F4: L3数仓目录 | G4: 应收
B5: 更新方式 | C5: 增量更新 | D5: 设计人员 | F5: 时间
B6: 使用场景 | C6: 取财务中台中坏账核销单中的核销金额数据
B7: 目标表 | M7: 财务中台坏账核销单
B8: 字段中文名称 | C8: *字段名称 | D8: *类型 | E8: 主键 | F8: *描述 | G8: 允许为空 | H8: 默认值 | I8: 聚合类型 | J8: 基础标准 | K8: 标准代码 | L8: *安全分级 | M8: 转换清洗规则 | N8: 源系统 | O8: 源头表 | P8: 源头字段 | Q8: 匹配字段 | R8: 匹配过滤 | S8: 数仓处理脚本 | T8: 备注
B9: =IFERROR(VLOOKUP(C9,'字段信息'!A:C,3,),"") | C9: dt_month | D9: =IFERROR(VLOOKUP(C9,'字段信息'!A:C,2,),"") | F9: =B9 | M9: 限制条件： 1、限制科目为应收、其他应收、长期应收、合同资产 2、单据状态fbillstatus = 'C' 3、SAP凭证号fk_hifi_sapvouchernum 不为空 | N9: 参数年月 | O9: ods.odsfmfi_tk_hifi_baddebtverify ods.odsfmfi_t_bd_period | P9: 参数截取年月 | Q9: fk_hifi_accountdate = fid | R9: fnumber=参数年月 ods.ODSFMFI_TK_HIFI_BADDEBTVERIFY.fbillstatus = 'C' ods.ODSFMFI_TK_HIFI_BADDEBTVERIFY.fk_hifi_sapvouchernum IS NOT NULL ( (r.fk_hifi_sap_version = 'SAP600' AND (a.fnumber LIKE '1122%' OR a.fnumber LIKE '1221%' OR a.fnumber LIKE '1531%' OR a.fnumber = '1460000000')) OR (r.fk_hifi_sap_version = 'SAP700' AND (a.fnumber LIKE '1122%' OR a.fnumber LIKE '1221%' OR a.fnumber = '1460000000')) OR (r.fk_hifi_sap_version = 'SAP900' AND (a.fnumber LIKE '1131%' OR a.fnumber LIKE '1133%' OR a.fnumber = '1460000000')) OR (r.fk_hifi_sap_version = 'SAP800B'AND (a.fnumber LIKE '1122%' OR a.fnumber LIKE '1221%' OR a.fnumber = '1460000000')) OR (r.fk_hifi_sap_version = 'SAP800' AND (a.fnumber LIKE '1131%' OR a.fnumber LIKE '1133%' OR a.fnumber = '1460000000')) OR (r.fk_hifi_sap_version = 'SAP810' AND (a.fnumber LIKE '1122%' OR a.fnumber LIKE '1221%')) ) | S9: r:ods.ODSFMSECD_TK_HIFI_ORGS_REF匹配sap版本号fk_hifi_org_id=fid a:匹配科目主数据ods.ODSFMFI_T_BD_ACCOUNT fk_hifi_accountorg = fid
B10: =IFERROR(VLOOKUP(C10,'字段信息'!A:C,3,),"") | C10: year | D10: =IFERROR(VLOOKUP(C10,'字段信息'!A:C,2,),"") | F10: =B10 | G10: √ | M10: 直接对应 | N10: 参数年 | P10: 参数截取年份
B11: =IFERROR(VLOOKUP(C11,'字段信息'!A:C,3,),"") | C11: month | D11: =IFERROR(VLOOKUP(C11,'字段信息'!A:C,2,),"") | F11: =B11 | G11: √ | L11: 普通级 | M11: 直接对应 | N11: 参数月 | P11: 参数截取月份
B12: =IFERROR(VLOOKUP(C12,'字段信息'!A:C,3,),"") | C12: company_code | D12: =IFERROR(VLOOKUP(C12,'字段信息'!A:C,2,),"") | F12: =B12 | G12: √ | L12: 普通级 | M12: 匹配公司主数据 | N12: Doris | O12: ods.odsfmfi_tk_hifi_baddebtverify ods.odsfmtss_t_org_org | P12: ods.odsfmtss_t_org_org.fnumber | Q12: fk_hifi_accountorg = fid
B13: =IFERROR(VLOOKUP(C13,'字段信息'!A:C,3,),"") | C13: acct_src_code | D13: =IFERROR(VLOOKUP(C13,'字段信息'!A:C,2,),"") | F13: =B13 | M13: 直接对应 | N13: Doris | O13: ods.odsfmfi_tk_hifi_baddebtverifysub ods.odsfmfi_t_bd_account | P13: fnumber | Q13: fk_hifi_subjects = fid
A14: 0908：科目分类的处理后续统一处理，D层放原始科目 | B14: =IFERROR(VLOOKUP(C14,'字段信息'!A:C,3,),"") | C14: acct_map_code | D14: =IFERROR(VLOOKUP(C14,'字段信息'!A:C,2,),"") | F14: =B14 | G14: √ | L14: 普通级 | M14: 匹配科目映射表dim.dim_rule_fi_mr_acct_mapping | N14: Doris | O14: dim.dim_rule_fi_mr_acct_mapping | P14: 取映射后科目 | Q14: 科目编码匹配科目映射表 | S14: case when a.fnumber LIKE '1122%' OR a.fnumber LIKE '1131%' then '1122000000' when a.fnumber LIKE '1221%' OR a.fnumber LIKE '1133%' then '122101F' when a.fnumber = '1460000000' then '1460000000' when a.fnumber LIKE '1531%' then '1531000000' END
B15: =IFERROR(VLOOKUP(C15,'字段信息'!A:C,3,),"") | C15: cust_code | D15: =IFERROR(VLOOKUP(C15,'字段信息'!A:C,2,),"") | F15: =B15 | G15: √ | L15: 普通级 | M15: 匹配客户主数据 | N15: Doris | O15: ods.odsfmfi_tk_hifi_baddebtverifysub ods.odsfmtss_t_bd_customer | P15: SUBSTR(cus.fnumber,1,INSTR(cus.fnumber,'(')-1) | Q15: fk_hifi_customer = fid
B16: =IFERROR(VLOOKUP(C16,'字段信息'!A:C,3,),"") | C16: cust_name | D16: =IFERROR(VLOOKUP(C16,'字段信息'!A:C,2,),"") | F16: =B16 | G16: √ | L16: 普通级 | M16: 匹配客户主数据 | N16: Doris | O16: ods.odsfmfi_tk_hifi_baddebtverifysub ods.odsfmtss_t_bd_customer | P16: fname | Q16: fk_hifi_customer = fid
B17: =IFERROR(VLOOKUP(C17,'字段信息'!A:C,3,),"") | C17: src_profitcenter_code | D17: =IFERROR(VLOOKUP(C17,'字段信息'!A:C,2,),"") | F17: =B17 | G17: √ | M17: 匹配利润中心主数据 | N17: Doris | O17: ods.odsfmfi_tk_hifi_baddebtverifysub ods.odsfmfi_tk_hifi_cas_profitcenter | P17: ltrim(pf.fnumber,'0') | Q17: fk_hifi_profitcenter = fid
B18: =IFERROR(VLOOKUP(C18,'字段信息'!A:C,3,),"") | C18: src_profitcenter_name | D18: =IFERROR(VLOOKUP(C18,'字段信息'!A:C,2,),"") | F18: =B18 | G18: √ | M18: 匹配利润中心主数据 | N18: Doris | O18: ods.odsfmfi_tk_hifi_cas_profitcenter ods.odsfmfi_tk_hifi_cas_profitcenter_l | P18: fname | Q18: fid = fid and flocaleid = 'zh_CN'
B19: =IFERROR(VLOOKUP(C19,'字段信息'!A:C,3,),"") | C19: profitcenter_code | D19: =IFERROR(VLOOKUP(C19,'字段信息'!A:C,2,),"") | F19: =B19 | G19: √ | M19: 匹配利润中心主数据 | N19: Doris | O19: ods.odsfmfi_tk_hifi_baddebtverifysub ods.odsfmfi_tk_hifi_cas_profitcenter | P19: ltrim(pf.fnumber,'0') | Q19: fk_hifi_profitcenter = fid
B20: =IFERROR(VLOOKUP(C20,'字段信息'!A:C,3,),"") | C20: profitcenter_name | D20: =IFERROR(VLOOKUP(C20,'字段信息'!A:C,2,),"") | F20: =B20 | G20: √ | M20: 匹配利润中心主数据 | N20: Doris | O20: ods.odsfmfi_tk_hifi_cas_profitcenter ods.odsfmfi_tk_hifi_cas_profitcenter_l | P20: fname | Q20: fid = fid and flocaleid = 'zh_CN'
B21: =IFERROR(VLOOKUP(C21,'字段信息'!A:C,3,),"") | C21: bus_range_code | D21: =IFERROR(VLOOKUP(C21,'字段信息'!A:C,2,),"") | F21: =B21 | G21: √ | M21: 匹配业务范围主数据 | N21: Doris | O21: ods.odsfmfi_tk_hifi_baddebtverifysub ods.odsfmfi_tk_hifi_cas_bizrange | P21: fnumber | Q21: fk_hifi_businessscope = fid
B22: =IFERROR(VLOOKUP(C22,'字段信息'!A:C,3,),"") | C22: bus_range_name | D22: =IFERROR(VLOOKUP(C22,'字段信息'!A:C,2,),"") | F22: =B22 | G22: √ | M22: 匹配业务范围主数据 | N22: Doris | O22: ods.odsfmfi_tk_hifi_cas_bizrange ods.odsfmfi_tk_hifi_cas_bizrange_l | P22: fname | Q22: fid = fid and flocaleid = 'zh_CN'
B23: =IFERROR(VLOOKUP(C23,'字段信息'!A:C,3,),"") | C23: bcy_code | D23: =IFERROR(VLOOKUP(C23,'字段信息'!A:C,2,),"") | F23: =B23 | G23: √ | M23: 匹配币种主数据 | N23: Doris | O23: ods.odsfmfi_tk_hifi_baddebtverifysub ods.odsfmtssys_t_bd_currency | P23: fnumber | Q23: fk_hifi_localcurrency = fid
B24: =IFERROR(VLOOKUP(C24,'字段信息'!A:C,3,),"") | C24: qcy_code | D24: =IFERROR(VLOOKUP(C24,'字段信息'!A:C,2,),"") | F24: =B24 | G24: √ | M24: 匹配币种主数据 | N24: Doris | O24: ods.odsfmfi_tk_hifi_baddebtverifysub ods.odsfmtssys_t_bd_currency | P24: fnumber | Q24: fk_hifi_currencyfield = fid
B25: =IFERROR(VLOOKUP(C25,'字段信息'!A:C,3,),"") | C25: bcy_amt | D25: =IFERROR(VLOOKUP(C25,'字段信息'!A:C,2,),"") | F25: =B25 | G25: √ | M25: 直接对应 | N25: Doris | O25: ods.odsfmfi_tk_hifi_baddebtverify ods.odsfmfi_tk_hifi_baddebtverifysub | P25: fk_hifi_local_lossmoneys | Q25: fid = fid
B26: =IFERROR(VLOOKUP(C26,'字段信息'!A:C,3,),"") | C26: qcy_amt | D26: =IFERROR(VLOOKUP(C26,'字段信息'!A:C,2,),"") | F26: =B26 | G26: √ | L26: 普通级 | M26: 直接对应 | N26: Doris | O26: ods.odsfmfi_tk_hifi_baddebtverify ods.odsfmfi_tk_hifi_baddebtverifysub | P26: fk_hifi_lossmoneys | Q26: fid = fid
B27: =IFERROR(VLOOKUP(C27,'字段信息'!A:C,3,),"") | C27: ods_src | D27: =IFERROR(VLOOKUP(C27,'字段信息'!A:C,2,),"") | F27: =B27 | G27: √ | L27: 普通级 | M27: 固定值 | N27: Doris
B28: =IFERROR(VLOOKUP(C28,'字段信息'!A:C,3,),"") | C28: load_dt | D28: =IFERROR(VLOOKUP(C28,'字段信息'!A:C,2,),"") | F28: =B28 | G28: √ | L28: 普通级 | M28: NOW() | N28: Doris

Sheet dwd_fi_mr_arap_sum_mi
A1: 返回 | B1: dwd_fi_mr_arap_sum_mi逻辑处理
A2: 规则库 | B2: 表名称 | C2: dwd.dwd_fi_mr_arap_sum_mi
B3: 表描述 | C3: 往来账龄汇总表 | D3: 表类型 | E3: 事实表 | F3: 数仓分层 | G3: DWD
B4: L1数仓目录 | C4: 管理财经 | D4: L2数仓目录 | E4: 财报管理 | F4: L3数仓目录 | G4: 应收
B5: 更新方式 | C5: 增量更新 | D5: 设计人员 | F5: 时间
B6: 使用场景 | C6: 根据detail的明细表单将数据进行聚合，不到凭证行项目，减少数据量，并且将信汇系统的明细数据聚合 | V6: 待确认：ods.odsmr_ztab_9000_acct_maping公司匹配表怎么处理--表单入湖，逻辑延用
B7: 目标表 | M7: 1、往来账龄明细表【dwd_fi_mr_arap_detail_mi】 | V7: 2、信汇ods.odsmt_fin_bill_view_data | AE7: 3、超期款明细表 | AN7: 4.1、SMS欠付返利明细表 | AW7: 4.2、政策欠付返利明细表 | BF7: 5、提前回款【dwd_fi_mr_arap_sum_mi】 | BO7: 6、核销金额明细表dwd.dwd_fi_mr_ar_writeoff_mi
B8: 字段中文名称 | C8: *字段名称 | D8: *类型 | E8: 主键 | F8: *描述 | G8: 允许为空 | H8: 默认值 | I8: 聚合类型 | J8: 基础标准 | K8: 标准代码 | L8: *安全分级 | M8: 转换清洗规则 | N8: 源系统 | O8: 源头表 | P8: 源头字段 | Q8: 匹配字段 | R8: 匹配过滤 | S8: 数仓处理脚本 | T8: 备注 | V8: 转换清洗规则 | W8: 源系统 | X8: 源头表 | Y8: 源头字段 | Z8: 匹配字段 | AA8: 匹配过滤 | AB8: 数仓处理脚本 | AC8: 备注 | AE8: 转换清洗规则 | AF8: 源系统 | AG8: 源头表 | AH8: 源头字段 | AI8: 匹配字段 | AJ8: 匹配过滤 | AK8: 数仓处理脚本 | AL8: 备注 | AN8: 转换清洗规则 | AO8: 源系统 | AP8: 源头表 | AQ8: 源头字段 | AR8: 匹配字段 | AS8: 匹配过滤 | AT8: 数仓处理脚本 | AU8: 备注 | AW8: 转换清洗规则 | AX8: 源系统 | AY8: 源头表 | AZ8: 源头字段 | BA8: 匹配字段 | BB8: 匹配过滤 | BC8: 数仓处理脚本 | BD8: 备注 | BF8: 转换清洗规则 | BG8: 源系统 | BH8: 源头表 | BI8: 源头字段 | BJ8: 匹配字段 | BK8: 匹配过滤 | BL8: 数仓处理脚本 | BM8: 备注 | BO8: 转换清洗规则 | BP8: 源系统 | BQ8: 源头表 | BR8: 源头字段 | BS8: 匹配字段 | BT8: 匹配过滤 | BU8: 数仓处理脚本 | BV8: 备注
B9: =IFERROR(VLOOKUP(C9,'字段信息'!A:C,3,),"") | C9: dt_month | D9: =IFERROR(VLOOKUP(C9,'字段信息'!A:C,2,),"") | F9: =B9 | M9: 直接对应 | N9: 参数年月 | V9: 直接对应 | W9: 参数年月 | AE9: 直接对应 | AF9: 参数年月 | AG9: dws.dws_fi_mr_ar_overdue_mi | AH9: start_dt | AW9: 参数年月 | AX9: Doris | AY9: dwd_mrs_mc_report_reward_account_detail_new_hi | AZ9: period | BF9: 直接对应 | BG9: doris | BH9: dwd_fi_mr_arap_sum_mi | BI9: dt_month | BO9: 限制条件： 1、限制科目为应收、其他应收、长期应收、合同资产 2、单据状态fbillstatus = 'C' 3、SAP凭证号fk_hifi_sapvouchernum 不为空 | BP9: 参数年月 | BQ9: ods.odsfmfi_tk_hifi_baddebtverify ods.odsfmfi_t_bd_period | BR9: 参数截取年月
B10: =IFERROR(VLOOKUP(C10,'字段信息'!A:C,3,),"") | C10: year | D10: =IFERROR(VLOOKUP(C10,'字段信息'!A:C,2,),"") | F10: =B10 | G10: √ | L10: 普通级 | M10: 直接对应 | N10: 参数年 | V10: 限制条件： 1、同一个票据编号，区间保留子序号最大的一条记录 2、排除BILL_STATUS=9999 3、排除应收公司与应付公司相同的数据；两列均为空时也排除。 4、按“应付公司 + 应收公司 + SIGN_DATE”汇总 BILL_AMOUNT。 排除汇总金额为0的数据。 5、目标组织排除 9000、9002、9003、9005、9008、空 | W10: 参数年 | AE10: 直接对应 | AF10: 参数年 | AG10: dws.dws_fi_mr_ar_overdue_mi | AH10: start_dt截取年份 | AW10: 参数年 | AX10: Doris | AY10: dwd_mrs_mc_report_reward_account_detail_new_hi | AZ10: LEFT(period,4) | BF10: 直接对应 | BG10: doris | BH10: dwd_fi_mr_arap_sum_mi | BI10: year | BO10: 直接对应 | BP10: 参数年 | BR10: 参数截取年份
B11: =IFERROR(VLOOKUP(C11,'字段信息'!A:C,3,),"") | C11: month | D11: =IFERROR(VLOOKUP(C11,'字段信息'!A:C,2,),"") | F11: =B11 | G11: √ | L11: 普通级 | M11: 直接对应 | N11: 参数月 | V11: 直接对应 | W11: 参数月 | AE11: 取8月份的数据，start_dt为9月1号 | AF11: 参数月 | AG11: dws.dws_fi_mr_ar_overdue_mi | AH11: start_dt截取月份 -1 | AW11: 参数月 | AX11: Doris | AY11: dwd_mrs_mc_report_reward_account_detail_new_hi | AZ11: RIGHT(period,2) | BF11: 直接对应 | BG11: doris | BH11: dwd_fi_mr_arap_sum_mi | BI11: month | BO11: 直接对应 | BP11: 参数月 | BR11: 参数截取月份
B12: =IFERROR(VLOOKUP(C12,'字段信息'!A:C,3,),"") | C12: company_code | D12: =IFERROR(VLOOKUP(C12,'字段信息'!A:C,2,),"") | F12: =B12 | G12: √ | L12: 普通级 | M12: 直接对应 | N12: Doris | O12: dwd_fi_mr_arap_detail_mi | P12: company_code | V12: 应付公司映射： 1、通过CREDIT_CUSTOMER_ACCOUNT匹配ods.odsmr_ztab_9000_acct_maping的ACCOUNT_NO，取BUKRS 2、按CREDIT_CUSTOMER_CODE匹配公司主数据中的AZIENDA.SEDE_LEGALE，取最小COD_AZIENDA 应收公司映射： 1、若HOLD_CUSTOMER_NAME='青岛海信商业保理有限公司'，AR_BUKRS固定为9002 2、按HOLD_CUSTOMER_ACCOUNT匹配ods.odsmr_ztab_9000_acct_mapingBUKRS的ACCOUNT_NO，取BUKRS 3、按RECEIVE_CREDIT_CODE匹配公司主数据中AZIENDA.SEDE_LEGALE，取最小COD_AZIENDA 应收公司生成一条数放公司，应付公司生成一条数放公司 | W12: Doris | X12: ods.odsmt_fin_bill_view_data | Y12: AP_BUKRS/AR_BUKRS | AE12: 直接对应 | AF12: Doris | AG12: dws.dws_fi_mr_ar_overdue_mi | AH12: ledge_code | AN12: 直接对应 | AO12: Doris | AP12: dwd_ltc_cem_reportpay_balance_summary_dd | AQ12: company_code | AW12: 直接对应 | AX12: Doris | AY12: dwd_mrs_mc_report_reward_account_detail_new_hi | AZ12: sales_group | BF12: 直接对应 | BG12: doris | BH12: dwd_fi_mr_arap_sum_mi | BI12: company_code | BO12: 匹配公司主数据 | BP12: Doris | BQ12: ods.odsfmfi_tk_hifi_baddebtverify ods.odsfmtss_t_org_org | BR12: ods.odsfmtss_t_org_org.fnumber
B13: =IFERROR(VLOOKUP(C13,'字段信息'!A:C,3,),"") | C13: cust_code | D13: =IFERROR(VLOOKUP(C13,'字段信息'!A:C,2,),"") | F13: =B13 | G13: √ | L13: 普通级 | M13: 直接对应 | N13: Doris | O13: dwd_fi_mr_arap_detail_mi | P13: cust_code | V13: 公司放应收公司时：XH_ + AP_BUKRS 公司放应付公司时：XH_ + AR_BUKRS； 对方为空时XH_Z001 | AE13: 直接对应 | AF13: Doris | AG13: dws.dws_fi_mr_ar_overdue_mi | AH13: cust_code | AN13: 直接对应 | AO13: Doris | AP13: dwd_ltc_cem_reportpay_balance_summary_dd | AQ13: sales_code | AW13: 直接对应 | AX13: Doris | AY13: dwd_mrs_mc_report_reward_account_detail_new_hi | AZ13: customer_code | BF13: 直接对应 | BG13: doris | BH13: dwd_fi_mr_arap_sum_mi | BI13: cust_code | BO13: 匹配客户主数据 | BP13: Doris | BQ13: ods.odsfmfi_tk_hifi_baddebtverifysub ods.odsfmtss_t_bd_customer | BR13: SUBSTR(cus.fnumber,1,INSTR(cus.fnumber,'(')-1)
B14: =IFERROR(VLOOKUP(C14,'字段信息'!A:C,3,),"") | C14: cust_name | D14: =IFERROR(VLOOKUP(C14,'字段信息'!A:C,2,),"") | F14: =B14 | G14: √ | L14: 普通级 | M14: 直接对应 | N14: Doris | O14: dwd_fi_mr_arap_detail_mi | P14: cust_name | V14: 公司放应收公司时：应收账款-信汇； 公司放应付公司时：应付账款-信汇 | AE14: 直接对应 | AF14: Doris | AG14: dws.dws_fi_mr_ar_overdue_mi | AH14: cust_name | AN14: 直接对应 | AO14: Doris | AP14: dwd_ltc_cem_reportpay_balance_summary_dd | AQ14: sname | AW14: 直接对应 | AX14: Doris | AY14: dwd_mrs_mc_report_reward_account_detail_new_hi | AZ14: customer_name | BF14: 直接对应 | BG14: doris | BH14: dwd_fi_mr_arap_sum_mi | BI14: cust_name | BO14: 匹配客户主数据 | BP14: Doris | BQ14: ods.odsfmfi_tk_hifi_baddebtverifysub ods.odsfmtss_t_bd_customer | BR14: fname
B15: =IFERROR(VLOOKUP(C15,'字段信息'!A:C,3,),"") | C15: cust_head_code | D15: =IFERROR(VLOOKUP(C15,'字段信息'!A:C,2,),"") | F15: =B15 | G15: √ | L15: 普通级 | M15: 直接对应 | N15: Doris | O15: dwd_fi_mr_arap_detail_mi | P15: cust_head_code | V15: 公司放应收公司时：XH_ + AP_BUKRS 公司放应付公司时：XH_ + AR_BUKRS； 对方为空时XH_Z001 | W15: Doris | X15: ods.odsmt_fin_bill_view_data | BF15: 直接对应 | BG15: doris | BH15: dwd_fi_mr_arap_sum_mi | BI15: cust_head_code
B16: =IFERROR(VLOOKUP(C16,'字段信息'!A:C,3,),"") | C16: cust_head_name | D16: =IFERROR(VLOOKUP(C16,'字段信息'!A:C,2,),"") | F16: =B16 | G16: √ | L16: 普通级 | M16: 直接对应 | N16: Doris | O16: dwd_fi_mr_arap_detail_mi | P16: cust_head_name | V16: 公司放应收公司时：应收账款-信汇； 公司放应付公司时：应付账款-信汇 | W16: Doris | Y16: 应收账款-信汇/应付账款-信汇 | BF16: 直接对应 | BG16: doris | BH16: dwd_fi_mr_arap_sum_mi | BI16: cust_head_name
B17: =IFERROR(VLOOKUP(C17,'字段信息'!A:C,3,),"") | C17: cust_branch_code | D17: =IFERROR(VLOOKUP(C17,'字段信息'!A:C,2,),"") | F17: =B17 | G17: √ | L17: 普通级 | M17: 直接对应 | N17: Doris | O17: dwd_fi_mr_arap_detail_mi | P17: cust_branch_code | V17: 无 | AE17: 直接对应 | AF17: Doris | AG17: dws.dws_fi_mr_ar_overdue_mi | AH17: rsv_field_7 | BF17: 直接对应 | BG17: doris | BH17: dwd_fi_mr_arap_sum_mi | BI17: cust_branch_code
B18: =IFERROR(VLOOKUP(C18,'字段信息'!A:C,3,),"") | C18: cust_branch_name | D18: =IFERROR(VLOOKUP(C18,'字段信息'!A:C,2,),"") | F18: =B18 | G18: √ | L18: 普通级 | M18: 直接对应 | N18: Doris | O18: dwd_fi_mr_arap_detail_mi | P18: cust_branch_name | V18: 无 | AE18: 直接对应 | AF18: Doris | AG18: dws.dws_fi_mr_ar_overdue_mi | AH18: rsv_field_8 | BF18: 直接对应 | BG18: doris | BH18: dwd_fi_mr_arap_sum_mi | BI18: cust_branch_name
B19: =IFERROR(VLOOKUP(C19,'字段信息'!A:C,3,),"") | C19: cp_company_code | D19: =IFERROR(VLOOKUP(C19,'字段信息'!A:C,2,),"") | F19: =B19 | G19: √ | L19: 普通级 | M19: 直接对应 | N19: Doris | O19: dwd_fi_mr_arap_detail_mi | P19: cp_company_code | V19: 公司放应收公司时：AP_BUKRS 公司放应付公司时：AR_BUKRS | W19: Doris | X19: ods.odsmt_fin_bill_view_data | Y19: AP_BUKRS/AR_BUKRS | AE19: 匹配客商映射对方公司dim.dim_rule_fi_mr_cust2ctp_mapping | AF19: Doris | AG19: dim.dim_rule_fi_mr_cust2ctp_mapping | AH19: 优先取cp_company_code_mr，为空则取cp_company_code | AI19: 客商编码匹配客商映射对方公司映射表 | AN19: 匹配客商映射对方公司dim.dim_rule_fi_mr_cust2ctp_mapping | AO19: Doris | AP19: dim.dim_rule_fi_mr_cust2ctp_mapping | AQ19: 优先取cp_company_code_mr，为空则取cp_company_code | AR19: 客商编码匹配客商映射对方公司映射表 | AW19: 匹配客商映射对方公司dim.dim_rule_fi_mr_cust2ctp_mapping | AX19: Doris | AY19: dim.dim_rule_fi_mr_cust2ctp_mapping | AZ19: 优先取cp_company_code_mr，为空则取cp_company_code | BA19: 客商编码匹配客商映射对方公司映射表 | BF19: 直接对应 | BG19: doris | BH19: dwd_fi_mr_arap_sum_mi | BI19: cp_company_code
B20: =IFERROR(VLOOKUP(C20,'字段信息'!A:C,3,),"") | C20: country_code | D20: =IFERROR(VLOOKUP(C20,'字段信息'!A:C,2,),"") | F20: =B20 | G20: √ | L20: 普通级 | M20: 直接对应 | N20: Doris | O20: dwd_fi_mr_arap_detail_mi | P20: country_code | V20: 无 | AE20: 直接对应 | AF20: Doris | AG20: dws.dws_fi_mr_ar_overdue_mi | AH20: country_code | AN20: 匹配mdg客户主数据得到对应字段 | AO20: Doris | AP20: dw.dim_customer_base_info_dd-客户主数据基本信息 | AQ20: country_code | AR20: kunnr_mdg = cust_code | AW20: 匹配mdg客户主数据得到对应字段 | AX20: Doris | AY20: dw.dim_customer_base_info_dd-客户主数据基本信息 | AZ20: country_code | BA20: kunnr_mdg = cust_code | BF20: 直接对应 | BG20: doris | BH20: dwd_fi_mr_arap_sum_mi | BI20: country_code
B21: =IFERROR(VLOOKUP(C21,'字段信息'!A:C,3,),"") | C21: country_name | D21: =IFERROR(VLOOKUP(C21,'字段信息'!A:C,2,),"") | F21: =B21 | G21: √ | M21: 直接对应 | N21: Doris | O21: dwd_fi_mr_arap_detail_mi | P21: country_name | V21: 无 | AE21: 直接对应 | AF21: Doris | AG21: dws.dws_fi_mr_ar_overdue_mi | AH21: country_name | AN21: 匹配mdg客户主数据得到对应字段 | AO21: Doris | AP21: dw.dim_customer_base_info_dd-客户主数据基本信息 | AQ21: country_code | AR21: kunnr_mdg = cust_code | AW21: 匹配mdg客户主数据得到对应字段 | AX21: Doris | AY21: dw.dim_customer_base_info_dd-客户主数据基本信息 | AZ21: country_code | BA21: kunnr_mdg = cust_code | BF21: 直接对应 | BG21: doris | BH21: dwd_fi_mr_arap_sum_mi | BI21: country_name
B22: =IFERROR(VLOOKUP(C22,'字段信息'!A:C,3,),"") | C22: acct_type_code | D22: =IFERROR(VLOOKUP(C22,'字段信息'!A:C,2,),"") | F22: =B22 | G22: √ | L22: 普通级 | M22: 直接对应 | N22: Doris | O22: dwd_fi_mr_arap_detail_mi | P22: acct_type_code | V22: 公司放应收公司时：D 公司放应付公司时：K | W22: Doris | X22: ods.odsmt_fin_bill_view_data | Y22: D/K | BF22: 直接对应 | BG22: doris | BH22: dwd_fi_mr_arap_sum_mi | BI22: acct_type_code
B23: =IFERROR(VLOOKUP(C23,'字段信息'!A:C,3,),"") | C23: acct_src_code | D23: =IFERROR(VLOOKUP(C23,'字段信息'!A:C,2,),"") | F23: =B23 | G23: √ | L23: 普通级 | M23: 直接对应 | N23: Doris | O23: dwd_fi_mr_arap_detail_mi | P23: acct_src_code | V23: 公司放应收公司时：1122000095 公司放应付公司时：2202000095 | W23: Doris | X23: ods.odsmt_fin_bill_view_data | Y23: 1122000095/2202000095 | AE23: 直接对应 | AF23: Doris | AG23: dws.dws_fi_mr_ar_overdue_mi | AH23: gl_account | BO23: 直接对应 | BP23: Doris | BQ23: ods.odsfmfi_tk_hifi_baddebtverifysub ods.odsfmfi_t_bd_account | BR23: fnumber
B24: =IFERROR(VLOOKUP(C24,'字段信息'!A:C,3,),"") | C24: acct_map_code | D24: =IFERROR(VLOOKUP(C24,'字段信息'!A:C,2,),"") | F24: =B24 | G24: √ | L24: 普通级 | M24: 直接对应 | N24: Doris | O24: dwd_fi_mr_arap_detail_mi | P24: acct_map_code | R24: 剔除科目为1122000095、2202000095 | V24: 匹配科目映射表dim.dim_rule_fi_mr_acct_mapping | W24: Doris | X24: dim.dim_rule_fi_mr_acct_mapping | Y24: acct_map_code | Z24: 科目编码匹配科目映射表 | BF24: 1122000000 | BO24: 匹配科目映射表dim.dim_rule_fi_mr_acct_mapping | BP24: Doris | BQ24: dim.dim_rule_fi_mr_acct_mapping | BR24: 取映射后科目
B25: =IFERROR(VLOOKUP(C25,'字段信息'!A:C,3,),"") | C25: channel_l1_code | D25: =IFERROR(VLOOKUP(C25,'字段信息'!A:C,2,),"") | F25: =B25 | G25: √ | L25: 普通级 | M25: 直接对应 | N25: Doris | O25: dwd_fi_mr_arap_detail_mi | P25: channel_l1_code | V25: 无 | AE25: 直接对应 | AF25: Doris | AG25: dws.dws_fi_mr_ar_overdue_mi | AH25: comp_cls_l1 | BF25: 直接对应 | BG25: doris | BH25: dwd_fi_mr_arap_sum_mi | BI25: channel_l1_code
B26: =IFERROR(VLOOKUP(C26,'字段信息'!A:C,3,),"") | C26: channel_l1_name | D26: =IFERROR(VLOOKUP(C26,'字段信息'!A:C,2,),"") | F26: =B26 | G26: √ | L26: 普通级 | M26: 直接对应 | N26: Doris | O26: dwd_fi_mr_arap_detail_mi | P26: channel_l1_name | V26: 无 | AF26: Doris | BF26: 直接对应 | BG26: doris | BH26: dwd_fi_mr_arap_sum_mi | BI26: channel_l1_name
B27: =IFERROR(VLOOKUP(C27,'字段信息'!A:C,3,),"") | C27: channel_l2_code | D27: =IFERROR(VLOOKUP(C27,'字段信息'!A:C,2,),"") | F27: =B27 | G27: √ | L27: 普通级 | M27: 直接对应 | N27: Doris | O27: dwd_fi_mr_arap_detail_mi | P27: channel_l2_code | V27: 无 | AE27: 直接对应 | AF27: Doris | AG27: dws.dws_fi_mr_ar_overdue_mi | AH27: comp_cls_l2 | BF27: 直接对应 | BG27: doris | BH27: dwd_fi_mr_arap_sum_mi | BI27: channel_l2_code
B28: =IFERROR(VLOOKUP(C28,'字段信息'!A:C,3,),"") | C28: channel_l2_name | D28: =IFERROR(VLOOKUP(C28,'字段信息'!A:C,2,),"") | F28: =B28 | G28: √ | L28: 普通级 | M28: 直接对应 | N28: Doris | O28: dwd_fi_mr_arap_detail_mi | P28: channel_l2_name | V28: 无 | AF28: Doris | BF28: 直接对应 | BG28: doris | BH28: dwd_fi_mr_arap_sum_mi | BI28: channel_l2_name
B29: =IFERROR(VLOOKUP(C29,'字段信息'!A:C,3,),"") | C29: channel_l3_code | D29: =IFERROR(VLOOKUP(C29,'字段信息'!A:C,2,),"") | F29: =B29 | G29: √ | L29: 普通级 | M29: 直接对应 | N29: Doris | O29: dwd_fi_mr_arap_detail_mi | P29: channel_l3_code | V29: 无 | AE29: 直接对应 | AF29: Doris | AG29: dws.dws_fi_mr_ar_overdue_mi | AH29: comp_cls_l3 | BF29: 直接对应 | BG29: doris | BH29: dwd_fi_mr_arap_sum_mi | BI29: channel_l3_code
B30: =IFERROR(VLOOKUP(C30,'字段信息'!A:C,3,),"") | C30: channel_l3_name | D30: =IFERROR(VLOOKUP(C30,'字段信息'!A:C,2,),"") | F30: =B30 | G30: √ | L30: 普通级 | M30: 直接对应 | N30: Doris | O30: dwd_fi_mr_arap_detail_mi | P30: channel_l3_name | V30: 无 | AF30: Doris | BF30: 直接对应 | BG30: doris | BH30: dwd_fi_mr_arap_sum_mi | BI30: channel_l3_name
B31: =IFERROR(VLOOKUP(C31,'字段信息'!A:C,3,),"") | C31: onoffline_code | D31: =IFERROR(VLOOKUP(C31,'字段信息'!A:C,2,),"") | F31: =B31 | G31: √ | L31: 普通级 | M31: 直接对应 | N31: Doris | O31: dwd_fi_mr_arap_detail_mi | P31: onoffline_code | W31: Doris | AE31: 直接对应 | AF31: Doris | AG31: dws.dws_fi_mr_ar_overdue_mi | AH31: channel_group | BF31: 直接对应 | BG31: doris | BH31: dwd_fi_mr_arap_sum_mi | BI31: onoffline_code
B32: =IFERROR(VLOOKUP(C32,'字段信息'!A:C,3,),"") | C32: onoffline_name | D32: =IFERROR(VLOOKUP(C32,'字段信息'!A:C,2,),"") | F32: =B32 | G32: √ | L32: 普通级 | M32: 直接对应 | N32: Doris | O32: dwd_fi_mr_arap_detail_mi | P32: onoffline_name | W32: Doris | BF32: 直接对应 | BG32: doris | BH32: dwd_fi_mr_arap_sum_mi | BI32: onoffline_name
B33: =IFERROR(VLOOKUP(C33,'字段信息'!A:C,3,),"") | C33: src_profitcenter_code | D33: =IFERROR(VLOOKUP(C33,'字段信息'!A:C,2,),"") | F33: =B33 | G33: √ | L33: 普通级 | M33: 直接对应 | N33: Doris | O33: dwd_fi_mr_arap_detail_mi | P33: src_profitcenter_code | V33: 无 | AE33: 直接对应 | AF33: Doris | AG33: dws.dws_fi_mr_ar_overdue_mi | AH33: profit_center_code | AW33: 直接对应 | AX33: Doris | AY33: dwd_mrs_mc_report_reward_account_detail_new_hi | AZ33: profit_center | BF33: 直接对应 | BG33: doris | BH33: dwd_fi_mr_arap_sum_mi | BI33: src_profitcenter_code | BO33: 匹配利润中心主数据 | BP33: Doris | BQ33: ods.odsfmfi_tk_hifi_baddebtverifysub ods.odsfmfi_tk_hifi_cas_profitcenter | BR33: ltrim(pf.fnumber,'0')
B34: =IFERROR(VLOOKUP(C34,'字段信息'!A:C,3,),"") | C34: src_profitcenter_name | D34: =IFERROR(VLOOKUP(C34,'字段信息'!A:C,2,),"") | F34: =B34 | G34: √ | L34: 普通级 | M34: 直接对应 | N34: Doris | O34: dwd_fi_mr_arap_detail_mi | P34: src_profitcenter_name | V34: 无 | AE34: 直接对应 | AF34: Doris | AG34: dws.dws_fi_mr_ar_overdue_mi | AH34: profit_center_name | BF34: 直接对应 | BG34: doris | BH34: dwd_fi_mr_arap_sum_mi | BI34: src_profitcenter_name | BO34: 匹配利润中心主数据 | BP34: Doris | BQ34: ods.odsfmfi_tk_hifi_cas_profitcenter ods.odsfmfi_tk_hifi_cas_profitcenter_l | BR34: fname
B35: =IFERROR(VLOOKUP(C35,'字段信息'!A:C,3,),"") | C35: profitcenter_code | D35: =IFERROR(VLOOKUP(C35,'字段信息'!A:C,2,),"") | F35: =B35 | G35: √ | L35: 普通级 | M35: 直接对应 | N35: Doris | O35: dwd_fi_mr_arap_detail_mi | P35: profitcenter_code | V35: 无 | AE35: 直接对应 | AF35: Doris | AG35: dws.dws_fi_mr_ar_overdue_mi | AH35: profit_center_code | AW35: 匹配《应收模块-利润中心映射表》，筛选映射类型为“收入利润中心映射往来利润中心”，将收入利润中心映射成应收利润中心 | AX35: Doris | AY35: dim_rule_fi_mr_ar_profit_mapping经分项目应收模块-利润中心映射表 | AZ35: profitcenter_code | BA35: profit_center = src_profitcenter_code | BF35: 直接对应 | BG35: doris | BH35: dwd_fi_mr_arap_sum_mi | BI35: profitcenter_code | BO35: 匹配利润中心主数据 | BP35: Doris | BQ35: ods.odsfmfi_tk_hifi_baddebtverifysub ods.odsfmfi_tk_hifi_cas_profitcenter | BR35: ltrim(pf.fnumber,'0')
B36: =IFERROR(VLOOKUP(C36,'字段信息'!A:C,3,),"") | C36: profitcenter_name | D36: =IFERROR(VLOOKUP(C36,'字段信息'!A:C,2,),"") | F36: =B36 | G36: √ | L36: 普通级 | M36: 直接对应 | N36: Doris | O36: dwd_fi_mr_arap_detail_mi | P36: profitcenter_name | V36: 无 | AE36: 直接对应 | AF36: Doris | AG36: dws.dws_fi_mr_ar_overdue_mi | AH36: profit_center_name | AW36: 匹配《应收模块-利润中心映射表》，筛选映射类型为“收入利润中心映射往来利润中心”，将收入利润中心映射成应收利润中心 | AX36: Doris | AY36: dim_rule_fi_mr_ar_profit_mapping经分项目应收模块-利润中心映射表 | AZ36: profitcenter_name | BF36: 直接对应 | BG36: doris | BH36: dwd_fi_mr_arap_sum_mi | BI36: profitcenter_name | BO36: 匹配利润中心主数据 | BP36: Doris | BQ36: ods.odsfmfi_tk_hifi_cas_profitcenter ods.odsfmfi_tk_hifi_cas_profitcenter_l | BR36: fname
B37: =IFERROR(VLOOKUP(C37,'字段信息'!A:C,3,),"") | C37: bus_range_code | D37: =IFERROR(VLOOKUP(C37,'字段信息'!A:C,2,),"") | F37: =B37 | G37: √ | L37: 普通级 | M37: 直接对应 | N37: Doris | O37: dwd_fi_mr_arap_detail_mi | P37: bus_range_code | W37: Doris | AE37: 直接对应 | AF37: Doris | AG37: dws.dws_fi_mr_ar_overdue_mi | AH37: bus_scope_code | BF37: 直接对应 | BG37: doris | BH37: dwd_fi_mr_arap_sum_mi | BI37: bus_range_code | BO37: 匹配业务范围主数据 | BP37: Doris | BQ37: ods.odsfmfi_tk_hifi_baddebtverifysub ods.odsfmfi_tk_hifi_cas_bizrange | BR37: fnumber
B38: =IFERROR(VLOOKUP(C38,'字段信息'!A:C,3,),"") | C38: bus_range_name | D38: =IFERROR(VLOOKUP(C38,'字段信息'!A:C,2,),"") | F38: =B38 | G38: √ | L38: 普通级 | M38: 直接对应 | N38: Doris | O38: dwd_fi_mr_arap_detail_mi | P38: bus_range_name | W38: Doris | AE38: 直接对应 | AF38: Doris | AG38: dws.dws_fi_mr_ar_overdue_mi | AH38: bus_scope_desc | BF38: 直接对应 | BG38: doris | BH38: dwd_fi_mr_arap_sum_mi | BI38: bus_range_name | BO38: 匹配业务范围主数据 | BP38: Doris | BQ38: ods.odsfmfi_tk_hifi_cas_bizrange ods.odsfmfi_tk_hifi_cas_bizrange_l | BR38: fname
B39: =IFERROR(VLOOKUP(C39,'字段信息'!A:C,3,),"") | C39: marketing_dept_code | D39: =IFERROR(VLOOKUP(C39,'字段信息'!A:C,2,),"") | F39: =B39 | G39: √ | L39: 普通级 | M39: 直接对应 | N39: Doris | O39: dwd_fi_mr_arap_detail_mi | P39: marketing_dept_code | W39: Doris | AE39: 直接对应 | AF39: Doris | AG39: dws.dws_fi_mr_ar_overdue_mi | AH39: biz_mgmt_unit | BF39: 直接对应 | BG39: doris | BH39: dwd_fi_mr_arap_sum_mi | BI39: marketing_dept_code
B40: =IFERROR(VLOOKUP(C40,'字段信息'!A:C,3,),"") | C40: marketing_dept_name | D40: =IFERROR(VLOOKUP(C40,'字段信息'!A:C,2,),"") | F40: =B40 | G40: √ | L40: 普通级 | M40: 直接对应 | N40: Doris | O40: dwd_fi_mr_arap_detail_mi | P40: marketing_dept_name | W40: Doris | BF40: 直接对应 | BG40: doris | BH40: dwd_fi_mr_arap_sum_mi | BI40: marketing_dept_name
B41: =IFERROR(VLOOKUP(C41,'字段信息'!A:C,3,),"") | C41: tov_channel_code | D41: =IFERROR(VLOOKUP(C41,'字段信息'!A:C,2,),"") | F41: =B41 | G41: √ | M41: 直接对应 | N41: Doris | O41: dwd_fi_mr_arap_detail_mi | P41: tov_channel_code
B42: =IFERROR(VLOOKUP(C42,'字段信息'!A:C,3,),"") | C42: tov_channel_name | D42: =IFERROR(VLOOKUP(C42,'字段信息'!A:C,2,),"") | F42: =B42 | G42: √ | M42: 直接对应 | N42: Doris | O42: dwd_fi_mr_arap_detail_mi | P42: tov_channel_name
B43: =IFERROR(VLOOKUP(C43,'字段信息'!A:C,3,),"") | C43: cc_cust_group_code | D43: =IFERROR(VLOOKUP(C43,'字段信息'!A:C,2,),"") | F43: =B43 | G43: √ | M43: 直接对应 | N43: Doris | O43: dwd_fi_mr_arap_detail_mi | P43: cc_cust_group_code
B44: =IFERROR(VLOOKUP(C44,'字段信息'!A:C,3,),"") | C44: cc_cust_group_name | D44: =IFERROR(VLOOKUP(C44,'字段信息'!A:C,2,),"") | F44: =B44 | G44: √ | M44: 直接对应 | N44: Doris | O44: dwd_fi_mr_arap_detail_mi | P44: cc_cust_group_name
B45: =IFERROR(VLOOKUP(C45,'字段信息'!A:C,3,),"") | C45: pay_reason_code | D45: =IFERROR(VLOOKUP(C45,'字段信息'!A:C,2,),"") | F45: =B45 | G45: √ | L45: 普通级 | M45: 直接对应 | N45: Doris | O45: dwd_fi_mr_arap_detail_mi | P45: pay_reason_code | V45: 无
B46: =IFERROR(VLOOKUP(C46,'字段信息'!A:C,3,),"") | C46: bcy_code | D46: =IFERROR(VLOOKUP(C46,'字段信息'!A:C,2,),"") | F46: =B46 | G46: √ | L46: 普通级 | M46: 直接对应 | N46: Doris | O46: dwd_fi_mr_arap_detail_mi | P46: bcy_code | V46: 固定CNY | W46: Doris | X46: ods.odsmt_fin_bill_view_data | Y46: CNY | AN46: 固定CNY | AO46: Doris | AP46: CNY | AW46: 固定CNY | AX46: Doris | AY46: dwd_mrs_mc_report_reward_account_detail_new_hi | AZ46: CNY | BF46: 直接对应 | BG46: doris | BH46: dwd_fi_mr_arap_sum_mi | BI46: bcy_code | BO46: 匹配币种主数据 | BP46: Doris | BQ46: ods.odsfmfi_tk_hifi_baddebtverifysub ods.odsfmtssys_t_bd_currency | BR46: fnumber
B47: =IFERROR(VLOOKUP(C47,'字段信息'!A:C,3,),"") | C47: qcy_code | D47: =IFERROR(VLOOKUP(C47,'字段信息'!A:C,2,),"") | F47: =B47 | G47: √ | L47: 普通级 | M47: 直接对应 | N47: Doris | O47: dwd_fi_mr_arap_detail_mi | P47: qcy_code | V47: 固定CNY | W47: Doris | X47: ods.odsmt_fin_bill_view_data | Y47: CNY | AN47: 固定CNY | AO47: Doris | AP47: CNY | AW47: 固定CNY | AX47: Doris | AY47: dwd_mrs_mc_report_reward_account_detail_new_hi | AZ47: CNY | BF47: 直接对应 | BG47: doris | BH47: dwd_fi_mr_arap_sum_mi | BI47: qcy_code | BO47: 匹配币种主数据 | BP47: Doris | BQ47: ods.odsfmfi_tk_hifi_baddebtverifysub ods.odsfmtssys_t_bd_currency | BR47: fnumber
B48: =IFERROR(VLOOKUP(C48,'字段信息'!A:C,3,),"") | C48: bcy_0_amt | D48: =IFERROR(VLOOKUP(C48,'字段信息'!A:C,2,),"") | F48: =B48 | G48: √ | L48: 普通级 | M48: 各个账龄段金额合计 | N48: Doris | O48: dwd_fi_mr_arap_detail_mi | P48: bcy_amt | V48: 公司放应收公司时：金额 公司放应付公司时：金额*-1 | W48: Doris | X48: ods.odsmt_fin_bill_view_data | Y48: BILL_AMOUNT | AE48: overdue_adj_after_amt inv_sample_amt 分两行数据展示 | AF48: Doris | AG48: dws.dws_fi_mr_ar_overdue_mi | AH48: overdue_adj_after_amt inv_sample_amt | AN48: 直接对应 | AO48: Doris | AP48: dwd_ltc_cem_reportpay_balance_summary_dd | AQ48: yue | AW48: 1、dim_rule_fi_mr_ar_cust_type规则库中，cust_type为结算类客户，筛选政策台账状态policystatename为【兑现过程中】、【确认完毕】的数据 2、电商类客户【待确认如何判断】，政策清单policy_list筛选【退差未冲红】的数据 | AX48: Doris | AY48: dwd_mrs_mc_report_reward_account_detail_new_hi | AZ48: arrears_amount | BF48: 1、ods_src为bsid和bsad%的，pay_reason_code=400，acct_map_code为1122%，判断baseline_dt<=当前年月最后一天，取大于0的数据 2、ods_src为bsid和bsad%的，pay_reason_code=400，acct_map_code为1122%，取小于0的数据 3、根据同一个科目+客商+利润中心计算1+2的数据，小于0时输出1+2的数据 | BI48: bcy_0_amt | BO48: 直接对应 | BP48: Doris | BQ48: ods.odsfmfi_tk_hifi_baddebtverify ods.odsfmfi_tk_hifi_baddebtverifysub | BR48: fk_hifi_local_lossmoneys
B49: =IFERROR(VLOOKUP(C49,'字段信息'!A:C,3,),"") | C49: bcy_1_amt | D49: =IFERROR(VLOOKUP(C49,'字段信息'!A:C,2,),"") | F49: =B49 | G49: √ | M49: 根据detail表中的账龄段编码将本位币账龄金额放入对应的账龄区间 | N49: Doris | O49: dwd_fi_mr_arap_detail_mi | P49: bcy_amt | V49: 公式:aging_days=月末最后一天-起算日期+1 起算日期为SIGN_DATE 根据计算的账龄天数匹配【账龄段配置表】 | AE49: overdue_adj_after_amt inv_sample_amt 分两行数据展示 | AF49: Doris | AG49: dws.dws_fi_mr_ar_overdue_mi | AH49: overdue_adj_after_amt inv_sample_amt | AN49: 直接对应 | AO49: Doris | AP49: dwd_ltc_cem_reportpay_balance_summary_dd | AQ49: yue | AW49: 同本月账龄逻辑 | AX49: Doris | AY49: dwd_mrs_mc_report_reward_account_detail_new_hi | AZ49: arrears_amount | BF49: 同本月账龄 | BO49: 直接对应 | BP49: Doris | BQ49: ods.odsfmfi_tk_hifi_baddebtverify ods.odsfmfi_tk_hifi_baddebtverifysub | BR49: fk_hifi_local_lossmoneys
B50: =IFERROR(VLOOKUP(C50,'字段信息'!A:C,3,),"") | C50: bcy_2_amt | D50: =IFERROR(VLOOKUP(C50,'字段信息'!A:C,2,),"") | F50: =B50 | G50: √ | M50: 同上
B51: =IFERROR(VLOOKUP(C51,'字段信息'!A:C,3,),"") | C51: bcy_3_amt | D51: =IFERROR(VLOOKUP(C51,'字段信息'!A:C,2,),"") | F51: =B51 | G51: √ | M51: 同上
B52: =IFERROR(VLOOKUP(C52,'字段信息'!A:C,3,),"") | C52: bcy_4_amt | D52: =IFERROR(VLOOKUP(C52,'字段信息'!A:C,2,),"") | F52: =B52 | G52: √ | M52: 同上
B53: =IFERROR(VLOOKUP(C53,'字段信息'!A:C,3,),"") | C53: bcy_5_amt | D53: =IFERROR(VLOOKUP(C53,'字段信息'!A:C,2,),"") | F53: =B53 | G53: √ | M53: 同上
B54: =IFERROR(VLOOKUP(C54,'字段信息'!A:C,3,),"") | C54: bcy_6_amt | D54: =IFERROR(VLOOKUP(C54,'字段信息'!A:C,2,),"") | F54: =B54 | G54: √ | M54: 同上
B55: =IFERROR(VLOOKUP(C55,'字段信息'!A:C,3,),"") | C55: bcy_7_amt | D55: =IFERROR(VLOOKUP(C55,'字段信息'!A:C,2,),"") | F55: =B55 | G55: √ | M55: 同上
B56: =IFERROR(VLOOKUP(C56,'字段信息'!A:C,3,),"") | C56: bcy_8_amt | D56: =IFERROR(VLOOKUP(C56,'字段信息'!A:C,2,),"") | F56: =B56 | G56: √ | M56: 同上
B57: =IFERROR(VLOOKUP(C57,'字段信息'!A:C,3,),"") | C57: bcy_9_amt | D57: =IFERROR(VLOOKUP(C57,'字段信息'!A:C,2,),"") | F57: =B57 | G57: √ | M57: 同上
B58: =IFERROR(VLOOKUP(C58,'字段信息'!A:C,3,),"") | C58: bcy_10_amt | D58: =IFERROR(VLOOKUP(C58,'字段信息'!A:C,2,),"") | F58: =B58 | G58: √ | M58: 同上
B59: =IFERROR(VLOOKUP(C59,'字段信息'!A:C,3,),"") | C59: bcy_11_amt | D59: =IFERROR(VLOOKUP(C59,'字段信息'!A:C,2,),"") | F59: =B59 | G59: √ | M59: 同上
B60: =IFERROR(VLOOKUP(C60,'字段信息'!A:C,3,),"") | C60: bcy_12_amt | D60: =IFERROR(VLOOKUP(C60,'字段信息'!A:C,2,),"") | F60: =B60 | G60: √ | M60: 同上
B61: =IFERROR(VLOOKUP(C61,'字段信息'!A:C,3,),"") | C61: bcy_13_amt | D61: =IFERROR(VLOOKUP(C61,'字段信息'!A:C,2,),"") | F61: =B61 | G61: √ | M61: 同上
... B63: =IFERROR(VLOOKUP(C63,'字段信息'!A:C,3,),"") | C63: bcy_15_amt | D63: =IFERROR(VLOOKUP(C63,'字段信息'!A:C,2,),"") | F63: =B63 | G63: √ | M63: 同上
B64: =IFERROR(VLOOKUP(C64,'字段信息'!A:C,3,),"") | C64: qcy_0_amt | D64: =IFERROR(VLOOKUP(C64,'字段信息'!A:C,2,),"") | F64: =B64 | G64: √ | L64: 普通级 | M64: 各个账龄段金额合计 | N64: Doris | O64: dwd_fi_mr_arap_detail_mi | P64: qcy_amt | V64: 公司放应收公司时：金额 公司放应付公司时：金额*-1 | W64: Doris | X64: ods.odsmt_fin_bill_view_data | Y64: BILL_AMOUNT | AE64: overdue_adj_after_amt inv_sample_amt 分两行数据展示 | AF64: Doris | AG64: dws.dws_fi_mr_ar_overdue_mi | AH64: overdue_adj_after_amt inv_sample_amt | AN64: 直接对应 | AO64: Doris | AP64: dwd_ltc_cem_reportpay_balance_summary_dd | AQ64: yue | AW64: 1、dim_rule_fi_mr_ar_cust_type规则库中，cust_type为结算类客户，筛选政策台账状态policystatename为【兑现过程中】、【确认完毕】的数据 2、电商类客户【待确认如何判断】，政策清单policy_list筛选【退差未冲红】的数据 | AX64: Doris | AY64: dwd_mrs_mc_report_reward_account_detail_new_hi | AZ64: arrears_amount | BF64: 1、应收合计数：ods_src为bsid和bsad%的，pay_reason_code=400，acct_map_code为1122%，判断净收付日期netcrp_dt<=当前年月最后一天，取大于0的数据 2、提前回款数：ods_src为bsid和bsad%的，pay_reason_code=400，acct_map_code为1122%，取小于0的数据 3、根据同一个科目+客商+利润中心计算1+2的数据，小于0时输出1+2的数据 | BI64: qcy_0_amt | BO64: 直接对应 | BP64: Doris | BQ64: ods.odsfmfi_tk_hifi_baddebtverify ods.odsfmfi_tk_hifi_baddebtverifysub | BR64: fk_hifi_lossmoneys
B65: =IFERROR(VLOOKUP(C65,'字段信息'!A:C,3,),"") | C65: qcy_1_amt | D65: =IFERROR(VLOOKUP(C65,'字段信息'!A:C,2,),"") | F65: =B65 | G65: √ | M65: 根据detail表中的账龄段编码将本位币账龄金额放入对应的账龄区间 | N65: Doris | O65: dwd_fi_mr_arap_detail_mi | P65: qcy_amt | V65: 公式:aging_days=月末最后一天-起算日期+1 起算日期为SIGN_DATE 根据计算的账龄天数匹配【账龄段配置表】 | AE65: overdue_adj_after_amt inv_sample_amt 分两行数据展示 | AF65: Doris | AG65: dws.dws_fi_mr_ar_overdue_mi | AH65: overdue_adj_after_amt inv_sample_amt | AN65: 直接对应 | AO65: Doris | AP65: dwd_ltc_cem_reportpay_balance_summary_dd | AQ65: yue | AW65: 同本月账龄逻辑 | AX65: Doris | AY65: dwd_mrs_mc_report_reward_account_detail_new_hi | AZ65: arrears_amount | BF65: 同本月账龄 | BO65: 直接对应 | BP65: Doris | BQ65: ods.odsfmfi_tk_hifi_baddebtverify ods.odsfmfi_tk_hifi_baddebtverifysub | BR65: fk_hifi_lossmoneys
B66: =IFERROR(VLOOKUP(C66,'字段信息'!A:C,3,),"") | C66: qcy_2_amt | D66: =IFERROR(VLOOKUP(C66,'字段信息'!A:C,2,),"") | F66: =B66 | G66: √ | M66: 同上
B67: =IFERROR(VLOOKUP(C67,'字段信息'!A:C,3,),"") | C67: qcy_3_amt | D67: =IFERROR(VLOOKUP(C67,'字段信息'!A:C,2,),"") | F67: =B67 | G67: √ | M67: 同上
B68: =IFERROR(VLOOKUP(C68,'字段信息'!A:C,3,),"") | C68: qcy_4_amt | D68: =IFERROR(VLOOKUP(C68,'字段信息'!A:C,2,),"") | F68: =B68 | G68: √ | M68: 同上
B69: =IFERROR(VLOOKUP(C69,'字段信息'!A:C,3,),"") | C69: qcy_5_amt | D69: =IFERROR(VLOOKUP(C69,'字段信息'!A:C,2,),"") | F69: =B69 | G69: √ | M69: 同上
B70: =IFERROR(VLOOKUP(C70,'字段信息'!A:C,3,),"") | C70: qcy_6_amt | D70: =IFERROR(VLOOKUP(C70,'字段信息'!A:C,2,),"") | F70: =B70 | G70: √ | M70: 同上
B71: =IFERROR(VLOOKUP(C71,'字段信息'!A:C,3,),"") | C71: qcy_7_amt | D71: =IFERROR(VLOOKUP(C71,'字段信息'!A:C,2,),"") | F71: =B71 | G71: √ | M71: 同上
B72: =IFERROR(VLOOKUP(C72,'字段信息'!A:C,3,),"") | C72: qcy_8_amt | D72: =IFERROR(VLOOKUP(C72,'字段信息'!A:C,2,),"") | F72: =B72 | G72: √ | M72: 同上
B73: =IFERROR(VLOOKUP(C73,'字段信息'!A:C,3,),"") | C73: qcy_9_amt | D73: =IFERROR(VLOOKUP(C73,'字段信息'!A:C,2,),"") | F73: =B73 | G73: √ | M73: 同上
B74: =IFERROR(VLOOKUP(C74,'字段信息'!A:C,3,),"") | C74: qcy_10_amt | D74: =IFERROR(VLOOKUP(C74,'字段信息'!A:C,2,),"") | F74: =B74 | G74: √ | M74: 同上
B75: =IFERROR(VLOOKUP(C75,'字段信息'!A:C,3,),"") | C75: qcy_11_amt | D75: =IFERROR(VLOOKUP(C75,'字段信息'!A:C,2,),"") | F75: =B75 | G75: √ | M75: 同上
B76: =IFERROR(VLOOKUP(C76,'字段信息'!A:C,3,),"") | C76: qcy_12_amt | D76: =IFERROR(VLOOKUP(C76,'字段信息'!A:C,2,),"") | F76: =B76 | G76: √ | M76: 同上
B77: =IFERROR(VLOOKUP(C77,'字段信息'!A:C,3,),"") | C77: qcy_13_amt | D77: =IFERROR(VLOOKUP(C77,'字段信息'!A:C,2,),"") | F77: =B77 | G77: √ | M77: 同上
... B79: =IFERROR(VLOOKUP(C79,'字段信息'!A:C,3,),"") | C79: qcy_15_amt | D79: =IFERROR(VLOOKUP(C79,'字段信息'!A:C,2,),"") | F79: =B79 | G79: √ | M79: 同上
B80: =IFERROR(VLOOKUP(C80,'字段信息'!A:C,3,),"") | C80: pays_tran | D80: =IFERROR(VLOOKUP(C80,'字段信息'!A:C,2,),"") | F80: =B80 | G80: √ | M80: 直接对应 | N80: Doris | O80: dwd_fi_mr_arap_detail_mi | P80: pays_tran
B81: =IFERROR(VLOOKUP(C81,'字段信息'!A:C,3,),"") | C81: system_src | D81: =IFERROR(VLOOKUP(C81,'字段信息'!A:C,2,),"") | F81: =B81 | G81: √ | L81: 普通级 | M81: 直接对应 | N81: Doris | O81: dwd_fi_mr_arap_detail_mi | P81: system_src | V81: XH | W81: Doris | AE81: FM_WTZJ | AN81: SMS | AW81: POLICY | BF81: 直接对应 | BG81: doris | BH81: dwd_fi_mr_arap_sum_mi | BI81: system_src
B82: =IFERROR(VLOOKUP(C82,'字段信息'!A:C,3,),"") | C82: ods_src | D82: =IFERROR(VLOOKUP(C82,'字段信息'!A:C,2,),"") | F82: =B82 | G82: √ | L82: 普通级 | M82: ORG_ZZT003 | V82: ORG_XH | W82: Doris | AE82: OVERDUE INV_SAMPLE | AH82: 取overdue_amt金额时，放overdue-超期款 取inv_sample_amt金额时，放inv_sample-开票样机额度 | AN82: UREB | AW82: UREB | BF82: EPAY | BO82: FM
B83: =IFERROR(VLOOKUP(C83,'字段信息'!A:C,3,),"") | C83: load_dt | D83: =IFERROR(VLOOKUP(C83,'字段信息'!A:C,2,),"") | F83: =B83 | G83: √ | L83: 普通级 | M83: NOW() | N83: Doris | V83: NOW() | W83: Doris | AE83: NOW() | AF83: Doris | AG83: dws.dws_fi_mr_ar_overdue_mi | AH83: load_dt | AN83: 数据更新时间 | AO83: Doris | AW83: 数据更新时间 | AX83: Doris | BO83: WRITEOFF
B84: =IFERROR(VLOOKUP(C84,'字段信息'!A:C,3,),"") | C84: reb_type | D84: =IFERROR(VLOOKUP(C84,'字段信息'!A:C,2,),"") | F84: =B84 | G84: √ | AN84: 直接对应 | AO84: Doris | AP84: dwd_ltc_cem_reportpay_balance_summary_dd | AQ84: leibie | AW84: 直接对应 | AX84: Doris
B85: =IFERROR(VLOOKUP(C85,'字段信息'!A:C,3,),"") | C85: ledger_status | D85: =IFERROR(VLOOKUP(C85,'字段信息'!A:C,2,),"") | F85: =B85 | G85: √ | AW85: 直接对应 | AX85: Doris | AY85: dwd_mrs_mc_report_reward_account_detail_new_hi | AZ85: policystatename | BB85: 已确认未兑现：兑现过程中、确认完成 已计提未兑现：待确认
B86: =IFERROR(VLOOKUP(C86,'字段信息'!A:C,3,),"") | C86: acct_cert_type | D86: =IFERROR(VLOOKUP(C86,'字段信息'!A:C,2,),"") | F86: =B86 | G86: √
B87: =IFERROR(VLOOKUP(C87,'字段信息'!A:C,3,),"") | C87: tax_rate | D87: =IFERROR(VLOOKUP(C86,'字段信息'!A:C,2,),"") | F87: =B87 | G87: √ | M87: 匹配《税率维护表》，按照顺序优先级处理 1、匹配规则batch_id为1，按照公司company_code+主户cust_code匹配对应税率 2、匹配规则batch_id为2，按照公司company_code+利润中心profitcenter_code匹配对应税率 3、匹配规则batch_id为3，按照公司company_code匹配税率 匹配不到的默认为0.13 | N87: Doris | O87: dim_rule_fi_mr_ar_tax_rate | P87: tax_rate
B88: =IFERROR(VLOOKUP(C88,'字段信息'!A:C,3,),"") | C88: nature_l1_name | D88: varchar(2000) | F88: =B88 | G88: √ | M88: 直接对应 | N88: Doris | O88: dwd_fi_mr_arap_detail_mi | P88: nature_l1_name | V88: 匹配《性质维护表》，按照顺序优先级处理 1、匹配规则batch_id为1，按照公司company_code+科目acct_src_code+主户cust_code匹配 2、匹配规则batch_id为2，按照公司company_code+主户cust_code匹配 3、匹配规则batch_id为3，按照公司company_code+科目acct_src_code+利润中心profitcenter_code匹配 4、匹配规则batch_id为4，按照公司company_code+科目acct_src_code匹配 5、匹配规则batch_id为5，按照科目company_code+主户cust_code匹配 6、以上未匹配到的，按照公司+客商性质+客商编码匹配sap主数据客户和供应商主数据取KVERM | W88: Doris | X88: dim_rule_fi_mr_ar_nature | Y88: nature_l1_name
B89: =IFERROR(VLOOKUP(C89,'字段信息'!A:C,3,),"") | C89: nature_l2_name | D89: varchar(2000) | F89: =B89 | G89: √ | M89: 直接对应 | N89: Doris | O89: dwd_fi_mr_arap_detail_mi | P89: nature_l2_name | V89: 同一级性质 | W89: Doris | X89: dim_rule_fi_mr_ar_nature | Y89: nature_l2_name
B90: =IFERROR(VLOOKUP(C90,'字段信息'!A:C,3,),"") | C90: nature_l3_name | D90: varchar(2000) | F90: =B90 | G90: √ | M90: 直接对应 | N90: Doris | O90: dwd_fi_mr_arap_detail_mi | P90: nature_l3_name | V90: 同一级性质 | W90: Doris | X90: dim_rule_fi_mr_ar_nature | Y90: nature_l3_name
B91: =IFERROR(VLOOKUP(C91,'字段信息'!A:C,3,),"") | C91: exchange_rate_eval_flag | D91: =IFERROR(VLOOKUP(C91,'字段信息'!A:C,2,),"") | F91: =B91 | G91: √ | M91: 匹配《不汇率评估范围维护表》 1、维护规则logic_name为'按照公司+客商维护'，根据公司company_code+主户cust_code匹配，匹配到输出为S 2、维护规则logic_name为'按照SAP系统+科目维护'，根据SAP系统号system_src+原始科目编码acct_src_code匹配，匹配到输出为M 3、如果两个都匹配到，输出SM 4、都没有匹配匹配到输出NULL | N91: Doris | O91: dim_rule_fi_mr_ar_ex_rate_eval_range
B92: =IFERROR(VLOOKUP(C92,'字段信息'!A:C,3,),"") | C92: is_apar_flag | D92: =IFERROR(VLOOKUP(C92,'字段信息'!A:C,2,),"") | F92: =B92 | G92: √ | M92: 匹配《账龄表进数范围维护》 1、取数类型为EX1，按照公司+主户匹配，匹配到的输出N 2、取数类型为EX2，按照公司+科目匹配，匹配到的输出N 3、取数类型为EX3，按照系统号+科目匹配，匹配到的输出N 4、取数类型为IN1，按照系统号+公司+科目匹配，匹配到的输出Y | N92: Doris | O92: dim_rule_fi_mr_ar_aging_range
B93: =IFERROR(VLOOKUP(C93,'字段信息'!A:C,3,),"") | C93: pay_term_code | D93: varchar(300) | F93: =B93 | G93: √ | M93: 直接对应 | N93: Doris | O93: dwd_fi_mr_ar_cterm_md | P93: pay_term_code
B94: =IFERROR(VLOOKUP(C94,'字段信息'!A:C,3,),"") | C94: pay_term_desc | D94: varchar(2000) | F94: =B94 | G94: √ | M94: 直接对应 | N94: Doris | O94: dwd_fi_mr_ar_cterm_md | P94: pay_term_desc
B95: 返利/费用标识 | C95: ufee_ureb_flag | D95: =IFERROR(VLOOKUP(C95,'字段信息'!A:C,2,),"") | F95: =B95 | G95: √ | M95: 满足以下条件，标识为UFEE： 1、acct_cert_type = zz 2、pay_reason_code = 800 3、acct_map_code为1122% 满足以下条件，标识为UREB： 1、acct_cert_type = zz 2、pay_reason_code = 600 3、acct_map_code为1122%
B96: 电商零售标识 | C96: ecls_flag | D96: =IFERROR(VLOOKUP(C96,'字段信息'!A:C,2,),"") | F96: =B96 | G96: √ | M96: 客户范围限制在《电商零售客户》 pay_reason_code=400，acct_map_code为1122%，判断同一个科目+客商+付款服务商编号的金额>0且最小的净收付日期大于本月的最后一天 满足以上条件打Y

Sheet 2. DWM逻辑处理--》》

Sheet 2. 0 DWM层目录
A1: DWM 数据集编码规则：
A2: AW+域编码+M+5位数据集编码
A4: 编码 | B4: 描述 | C4: 数据集域 | D4: 类型
A6: AW_MR9_ARPM01 | B6: 往来账龄计算底稿 | C6: MR9 | D6: 实体数据集
A9: 步骤ID | B9: 步骤 | C9: 源表 | D9: 处理类型 | E9: 处理内容 | F9: mrd需求
A10: 1 | B10: ARP001_STEP_1 | C10: dwd_fi_mr_arap_sum_mi AW_MR9_REVM01_000001 dwd_fi_mr_ar_overdue_mi dwd_fi_mr_ar_ureb_mi | D10: 数据聚合处理 | E10: 将往来账龄及周转影响因素需要的数据聚合到计算底稿中，包括SAP的账龄明细、信汇明细、出库未开、退货未办、超期款数据、提前回款、电商零售节奏、欠付费用、欠付返利，通过数据分类字段区分开 | F10: 应收指标构成+影响因素
A11: 2 | B11: ARP001_STEP_2 | C11: AW_MR9_REVM01_000001 | D11: 数据范围限制 | E11: 往来账龄需要对部分客商或科目等进行剔除，此步骤用于将步骤1取到的数据根据进数范围进行限制
A12: 3 | B12: ARP001_STEP_3 | C12: AW_MR9_REVM01_000001 | D12: 重分类处理 | E12: 此步骤将往来账龄的数据根据重分类的规则进行重分类的判断，法人口径、管理口径、管理分公司口径三个口径的重分类处理，以及集团归属范围的判断 | F12: 重分类处理
A14: 编码 | B14: 描述 | C14: 数据集域 | D14: 类型
A16: AW_MR9_ARPM02 | B16: 往来账龄结果表 | C16: MR9 | D16: 实体数据集
A19: 步骤ID | B19: 步骤 | C19: 源表 | D19: 处理类型 | E19: 处理内容 | F19: mrd需求
A20: 1 | B20: ARP002_STEP_1 | C20: AW_MR9_ARPM01_000001 | D20: 数据匹配到同一行 | E20: 此表将往来账龄计算底稿不同数据分类的数据平铺到列上展示，并且针对应收重分类到合同负债的数据，把对应的税额剔除
A22: 编码 | B22: 描述 | C22: 数据集域 | D22: 类型
A24: AW_MR9_ARPM03 | B24: 坏账计算表 | C24: MR9 | D24: 实体数据集
A27: 步骤ID | B27: 步骤 | C27: 源表 | D27: 处理类型 | E27: 处理内容 | F27: mrd需求
A28: 1 | B28: ARP003_STEP_1 | C28: AW_MR9_ARPM02_000001 | D28: 坏账计提基数计算 | E28: 将往来账龄表中涉及到需要计算坏账的数据取到坏账计算表中，根据管理分类和分公司分类不同生成两个口径的数据，并且匹配出坏账的调整项，如果有直销垫资的金额，用垫资的金额冲减坏账计提基数，优先从长账龄冲销，如果同一个客户存在负数的账龄金额，拆分到长账龄的区间中 | F28: 坏账计算规则
A29: 2 | B29: ARP003_STEP_2 | C29: AW_MR9_ARPM03_000001 | D29: 坏账计算 | E29: 根据不同的坏账计提规则计算坏账金额，如果有个别认定和煤改电，优先取对应的金额计提坏账，再按照优先级匹配坏账计提比例，根据坏账计提比例*坏账计提基数计算坏账金额，如果保障天数>0，需要再根据保障天数判断坏账计提区间，根据坏账计提比例*坏账计提基数*未覆盖比例计算坏账 | F29: 坏账计算规则
A30: 3 | B30: ARP003_STEP_3 | C30: AW_MR9_ARPM03_000001 | D30: 负坏账分摊 | E30: 针对坏账计算出来为负数的行项目，按照同一个公司+客户+科目计算正数行的比例，把负数的坏账金额分摊到正数行上 | F30: 坏账计算规则-分摊
A33: 编码 | B33: 描述 | C33: 数据集域 | D33: 类型
A35: AW_MR9_ARPM04 | B35: 周转计算-占用明细表 | C35: MR9 | D35: 实体数据集
A38: 步骤ID | B38: 步骤 | C38: 源表 | D38: 处理类型 | E38: 处理内容 | F38: mrd需求
A39: 1 | B39: ARP004_STEP_1 | C39: AW_MR9_ARPM02_000001 | D39: 周转占用取数 | E39: 把往来账龄结果表的数据筛选出需要计算周转的应收占用数据，根据取数配置表中的限制进行数据的取数及剔除，以及将手工调整的影响因素也匹配到同一行数据中 | F39: 应收周转占用取数
A42: 编码 | B42: 描述 | C42: 数据集域 | D42: 类型
A44: AW_MR9_ARPM05 | B44: 周转计算-收入明细表 | C44: MR9 | D44: 实体数据集
A47: 步骤ID | B47: 步骤 | C47: 源表 | D47: 处理类型 | E47: 处理内容 | F47: mrd需求
A48: 1 | B48: ARP005_STEP_1 | C48: AW_MR9_REVM01_000001 | D48: 周转收入取数 | E48: 把单体销售明细表的数据筛选出需要计算周转的收入数据，根据取数配置表中的限制进行数据的取数及剔除 | F48: 应收周转收入取数

Sheet ARPM01账龄计算底稿-STEP1数据聚合
A1: 返回 | B1: AW_MR9_ARPM01_000001逻辑处理
A2: 规则库 | B2: 表名称 | C2: AW_MR9_ARPM01_000001 | M2: 存储过程名称：CPM_SP_D2M_ARP_M
B3: 表描述 | C3: 往来账龄计算底稿 | D3: 表类型 | E3: 事实表 | F3: 数仓分层 | G3: DWM | M3: 参数：场景 P_SCENARIO
B4: L1数仓目录 | C4: 管理财经 | D4: L2数仓目录 | E4: 财报管理 | F4: L3数仓目录 | G4: 应收 | M4: 期间：P_PERIODO
B5: 更新方式 | C5: 增量更新 | D5: 设计人员 | F5: 时间 | M5: 公司：P_AZIENDA
B6: 使用场景 | C6: 将D层往来账龄汇总表的数据推到M层，并汇总取出库和退货的数据 | M6: 用户：SESSION_USER | V6: M01还有出库和退货的调整数，所以只能从M01取数
B7: 目标表 | M7: 往来账龄明细表【dwd_fi_mr_arap_sum_mi】 | V7: 单体销售明细表【AW_MR9_REVM01_000001】 | AE7: 超期款明细表【dwd_fi_mr_ar_overdue_mi】 | AN7: 提前回款【dwd_fi_mr_arap_sum_mi】 | AW7: 电商零售销售节奏【dwd_fi_mr_arap_sum_mi】 | BF7: 欠付费用【dwd_fi_mr_arap_sum_mi】 | BO7: 欠付返利【dwd_fi_mr_arap_sum_mi】
B8: 字段中文名称 | C8: *字段名称 | D8: *类型 | E8: 主键 | F8: *描述 | G8: 允许为空 | H8: 默认值 | I8: 聚合类型 | J8: 基础标准 | K8: 标准代码 | L8: *安全分级 | M8: 转换清洗规则 | N8: 源系统 | O8: 源头表 | P8: 源头字段 | Q8: 匹配字段 | R8: 匹配过滤 | S8: 数仓处理脚本 | T8: 备注 | V8: 转换清洗规则 | W8: 源系统 | X8: 源头表 | Y8: 源头字段 | Z8: 匹配字段 | AA8: 匹配过滤 | AB8: 数仓处理脚本 | AC8: 备注 | AE8: 转换清洗规则 | AF8: 源系统 | AG8: 源头表 | AH8: 源头字段 | AI8: 匹配字段 | AJ8: 匹配过滤 | AK8: 数仓处理脚本 | AL8: 备注 | AN8: 转换清洗规则 | AO8: 源系统 | AP8: 源头表 | AQ8: 源头字段 | AR8: 匹配字段 | AS8: 匹配过滤 | AT8: 数仓处理脚本 | AU8: 备注 | AW8: 转换清洗规则 | AX8: 源系统 | AY8: 源头表 | AZ8: 源头字段 | BA8: 匹配字段 | BB8: 匹配过滤 | BC8: 数仓处理脚本 | BD8: 备注 | BF8: 转换清洗规则 | BG8: 源系统 | BH8: 源头表 | BI8: 源头字段 | BJ8: 匹配字段 | BK8: 匹配过滤 | BL8: 数仓处理脚本 | BM8: 备注 | BO8: 转换清洗规则 | BP8: 源系统 | BQ8: 源头表 | BR8: 源头字段 | BS8: 匹配字段 | BT8: 匹配过滤 | BU8: 数仓处理脚本 | BV8: 备注
B9: =IFERROR(VLOOKUP(C9,'字段信息'!A:C,3,),"") | C9: COD_SCENARIO | D9: =IFERROR(VLOOKUP(C9,'字段信息'!A:C,2,),"") | F9: =B9 | M9: 限制条件： 1、取is_apar_flag为Y或为空的 2、限制公司在抽取范围内的AW_RUL_DWMCRS_000001中ARP_FLAG为Y的COD_AZIENDA范围 | N9: doris | O9: dwd_fi_mr_arap_sum_mi | P9: year+"ACT" | V9: 直接对应 | W9: TA | X9: AW_MR9_REVM01_000001 | Y9: COD_SCENARIO | AE9: 直接对应 | AG9: dwd_fi_mr_ar_overdue_mi | AH9: year+"ACT" | AN9: 直接对应 | AO9: doris | AP9: dwd_fi_mr_arap_sum_mi | AQ9: year+"ACT" | AW9: 直接对应 | AX9: doris | AY9: dwd_fi_mr_arap_sum_mi | AZ9: year+"ACT" | BF9: 直接对应 | BG9: doris | BH9: dwd_fi_mr_arap_sum_mi | BI9: year+"ACT" | BO9: 直接对应 | BP9: doris | BQ9: dwd_fi_mr_ar_ureb_mi | BR9: year+"ACT"
B10: =IFERROR(VLOOKUP(C10,'字段信息'!A:C,3,),"") | C10: COD_PERIODO | D10: =IFERROR(VLOOKUP(C10,'字段信息'!A:C,2,),"") | F10: =B10 | G10: √ | L10: 普通级 | M10: 直接对应 | N10: doris | O10: dwd_fi_mr_arap_sum_mi | P10: month | V10: 直接对应 | W10: TA | X10: AW_MR9_REVM01_000001 | Y10: COD_PERIODO | AE10: 直接对应 | AG10: dwd_fi_mr_ar_overdue_mi | AH10: month | AN10: 直接对应 | AO10: doris | AP10: dwd_fi_mr_arap_sum_mi | AQ10: month | AW10: 直接对应 | AX10: doris | AY10: dwd_fi_mr_arap_sum_mi | AZ10: month | BF10: 直接对应 | BG10: doris | BH10: dwd_fi_mr_arap_sum_mi | BI10: month | BO10: 直接对应 | BP10: doris | BQ10: dwd_fi_mr_ar_ureb_mi | BR10: month
B11: =IFERROR(VLOOKUP(C11,'字段信息'!A:C,3,),"") | C11: COD_AZIENDA | D11: =IFERROR(VLOOKUP(C11,'字段信息'!A:C,2,),"") | F11: =B11 | G11: √ | L11: 普通级 | M11: 直接对应 | N11: doris | O11: dwd_fi_mr_arap_sum_mi | P11: company_code | V11: 直接对应 | W11: TA | X11: AW_MR9_REVM01_000001 | Y11: COD_AZIENDA | AE11: 直接对应 | AG11: dwd_fi_mr_ar_overdue_mi | AH11: company_code | AN11: 直接对应 | AO11: doris | AP11: dwd_fi_mr_arap_sum_mi | AQ11: company_code | AW11: 直接对应 | AX11: doris | AY11: dwd_fi_mr_arap_sum_mi | AZ11: company_code | BF11: 直接对应 | BG11: doris | BH11: dwd_fi_mr_arap_sum_mi | BI11: company_code | BO11: 直接对应 | BP11: doris | BQ11: dwd_fi_mr_ar_ureb_mi | BR11: company_code
B12: =IFERROR(VLOOKUP(C12,'字段信息'!A:C,3,),"") | C12: COD_CATEGORIA | D12: =IFERROR(VLOOKUP(C12,'字段信息'!A:C,2,),"") | F12: =B12 | G12: √ | L12: 普通级 | M12: ZAMOUNT | V12: ZAMOUNT | W12: TA | AE12: ZAMOUNT | AN12: ZAMOUNT | AW12: ZAMOUNT | BF12: ZAMOUNT | BO12: ZAMOUNT
B13: =IFERROR(VLOOKUP(C13,'字段信息'!A:C,3,),"") | C13: SRC_DETAIL | D13: =IFERROR(VLOOKUP(C13,'字段信息'!A:C,2,),"") | F13: =B13 | G13: √ | L13: 普通级 | M13: 直接对应 | N13: doris | O13: dwd_fi_mr_arap_sum_mi | P13: ods_src | V13: 如果是S600101%则ZTSO04_CK-出库未开，如果是S600102%则ZTSO04_TH-退货未办 | W13: TA | X13: AW_MR9_REVM01_000001 | Y13: COD_CONTO | AA13: S600101%/S600102% | AE13: 取overdue_amt金额时，放overdue-超期款 取inv_sample_amt金额时，放inv_sample-开票样机额度 | AG13: dwd_fi_mr_ar_overdue_mi | AN13: epay-提前回款 | AW13: ECLS-电商零售销售节奏 | BF13: UFEE-欠付费用 | BO13: UREB-欠付返利
B14: =IFERROR(VLOOKUP(C14,'字段信息'!A:C,3,),"") | C14: CUST_CODE | D14: =IFERROR(VLOOKUP(C14,'字段信息'!A:C,2,),"") | F14: =B14 | G14: √ | L14: 普通级 | M14: 直接对应 | N14: doris | O14: dwd_fi_mr_arap_sum_mi | P14: cust_code | V14: 直接对应 | W14: TA | X14: AW_MR9_REVM01_000001 | Y14: cust_code | AE14: 直接对应 | AG14: dwd_fi_mr_ar_overdue_mi | AH14: cust_code | AN14: 直接对应 | AO14: doris | AP14: dwd_fi_mr_arap_sum_mi | AQ14: cust_code | AW14: 直接对应 | AX14: doris | AY14: dwd_fi_mr_arap_sum_mi | AZ14: cust_code | BF14: 直接对应 | BG14: doris | BH14: dwd_fi_mr_arap_sum_mi | BI14: cust_code | BO14: 匹配《欠付返利客户取值范围》 1、ods_src为SAP时，取客户类型为结算类客户的范围 2、ods_src为policy时，排除客户类型为结算类客户 2.1客户类型为电商零售类客户时，取ledger_status为 2.2客户类型不为电商零售类客户时，取ledger_status为兑现过程 中、确认完成 | BP14: doris | BQ14: dwd_fi_mr_ar_ureb_mi | BR14: cust_code
B15: =IFERROR(VLOOKUP(C15,'字段信息'!A:C,3,),"") | C15: CUST_NAME | D15: =IFERROR(VLOOKUP(C15,'字段信息'!A:C,2,),"") | F15: =B15 | G15: √ | L15: 普通级 | M15: 直接对应 | N15: doris | O15: dwd_fi_mr_arap_sum_mi | P15: cust_name | V15: 直接对应 | W15: TA | X15: AW_MR9_REVM01_000001 | Y15: cust_name | AE15: 直接对应 | AG15: dwd_fi_mr_ar_overdue_mi | AH15: cust_name | AN15: 直接对应 | AO15: doris | AP15: dwd_fi_mr_arap_sum_mi | AQ15: cust_name | AW15: 直接对应 | AX15: doris | AY15: dwd_fi_mr_arap_sum_mi | AZ15: cust_name | BF15: 直接对应 | BG15: doris | BH15: dwd_fi_mr_arap_sum_mi | BI15: cust_name | BO15: 直接对应 | BP15: doris | BQ15: dwd_fi_mr_ar_ureb_mi | BR15: cust_name
B16: =IFERROR(VLOOKUP(C16,'字段信息'!A:C,3,),"") | C16: CUST_HEAD_CODE | D16: =IFERROR(VLOOKUP(C16,'字段信息'!A:C,2,),"") | F16: =B16 | G16: √ | L16: 普通级 | M16: 直接对应 | N16: doris | O16: dwd_fi_mr_arap_sum_mi | P16: cust_head_code | AN16: 直接对应 | AO16: doris | AP16: dwd_fi_mr_arap_sum_mi | AQ16: cust_head_code | AW16: 直接对应 | AX16: doris | AY16: dwd_fi_mr_arap_sum_mi | AZ16: cust_head_code | BF16: 直接对应 | BG16: doris | BH16: dwd_fi_mr_arap_sum_mi | BI16: cust_head_code
B17: =IFERROR(VLOOKUP(C17,'字段信息'!A:C,3,),"") | C17: CUST_HEAD_NAME | D17: =IFERROR(VLOOKUP(C17,'字段信息'!A:C,2,),"") | F17: =B17 | G17: √ | M17: 直接对应 | N17: doris | O17: dwd_fi_mr_arap_sum_mi | P17: cust_head_name | AN17: 直接对应 | AO17: doris | AP17: dwd_fi_mr_arap_sum_mi | AQ17: cust_head_name | AW17: 直接对应 | AX17: doris | AY17: dwd_fi_mr_arap_sum_mi | AZ17: cust_head_name | BF17: 直接对应 | BG17: doris | BH17: dwd_fi_mr_arap_sum_mi | BI17: cust_head_name
B18: =IFERROR(VLOOKUP(C18,'字段信息'!A:C,3,),"") | C18: CUST_BRANCH_CODE | D18: =IFERROR(VLOOKUP(C18,'字段信息'!A:C,2,),"") | F18: =B18 | G18: √ | M18: 直接对应 | N18: doris | O18: dwd_fi_mr_arap_sum_mi | P18: cust_branch_code | AN18: 直接对应 | AO18: doris | AP18: dwd_fi_mr_arap_sum_mi | AQ18: cust_branch_code | AW18: 直接对应 | AX18: doris | AY18: dwd_fi_mr_arap_sum_mi | AZ18: cust_branch_code | BF18: 直接对应 | BG18: doris | BH18: dwd_fi_mr_arap_sum_mi | BI18: cust_branch_code
B19: =IFERROR(VLOOKUP(C19,'字段信息'!A:C,3,),"") | C19: CUST_BRANCH_NAME | D19: =IFERROR(VLOOKUP(C19,'字段信息'!A:C,2,),"") | F19: =B19 | G19: √ | L19: 普通级 | M19: 直接对应 | N19: doris | O19: dwd_fi_mr_arap_sum_mi | P19: cust_branch_name | AN19: 直接对应 | AO19: doris | AP19: dwd_fi_mr_arap_sum_mi | AQ19: cust_branch_name | AW19: 直接对应 | AX19: doris | AY19: dwd_fi_mr_arap_sum_mi | AZ19: cust_branch_name | BF19: 直接对应 | BG19: doris | BH19: dwd_fi_mr_arap_sum_mi | BI19: cust_branch_name
B20: =IFERROR(VLOOKUP(C20,'字段信息'!A:C,3,),"") | C20: COD_AZI_CTP | D20: =IFERROR(VLOOKUP(C20,'字段信息'!A:C,2,),"") | F20: =B20 | G20: √ | M20: 直接对应 | N20: doris | O20: dwd_fi_mr_arap_sum_mi | P20: cp_company_code | V20: 直接对应 | W20: TA | X20: AW_MR9_REVM01_000001 | Y20: COD_AZI_CTP | AE20: 直接对应 | AG20: dwd_fi_mr_ar_overdue_mi | AH20: cp_company_code | AN20: 直接对应 | AO20: doris | AP20: dwd_fi_mr_arap_sum_mi | AQ20: cp_company_code | AW20: 直接对应 | AX20: doris | AY20: dwd_fi_mr_arap_sum_mi | AZ20: cp_company_code | BF20: 直接对应 | BG20: doris | BH20: dwd_fi_mr_arap_sum_mi | BI20: cp_company_code | BO20: 直接对应 | BP20: doris | BQ20: dwd_fi_mr_ar_ureb_mi | BR20: cp_company_code
B21: =IFERROR(VLOOKUP(C21,'字段信息'!A:C,3,),"") | C21: COUNTRY_CODE | D21: =IFERROR(VLOOKUP(C21,'字段信息'!A:C,2,),"") | F21: =B21 | G21: √ | M21: 直接对应 | N21: doris | O21: dwd_fi_mr_arap_sum_mi | P21: country_code
B22: =IFERROR(VLOOKUP(C22,'字段信息'!A:C,3,),"") | C22: COUNTRY_NAME | D22: =IFERROR(VLOOKUP(C22,'字段信息'!A:C,2,),"") | F22: =B22 | G22: √ | M22: 直接对应 | N22: doris | O22: dwd_fi_mr_arap_sum_mi | P22: country_name
B23: =IFERROR(VLOOKUP(C23,'字段信息'!A:C,3,),"") | C23: ACCT_SRC_CODE | D23: =IFERROR(VLOOKUP(C23,'字段信息'!A:C,2,),"") | F23: =B23 | G23: √ | M23: 直接对应 | N23: doris | O23: dwd_fi_mr_arap_sum_mi | P23: acct_src_code | AE23: 直接对应 | AG23: dwd_fi_mr_ar_overdue_mi | AH23: acct_src_code | AN23: 直接对应 | AO23: doris | AP23: dwd_fi_mr_arap_sum_mi | AQ23: acct_src_code | AW23: 直接对应 | AX23: doris | AY23: dwd_fi_mr_arap_sum_mi | AZ23: acct_src_code | BF23: 直接对应 | BG23: doris | BH23: dwd_fi_mr_arap_sum_mi | BI23: acct_src_code | BO23: 直接对应 | BP23: doris | BQ23: dwd_fi_mr_ar_ureb_mi | BR23: acct_src_code
B24: =IFERROR(VLOOKUP(C24,'字段信息'!A:C,3,),"") | C24: ACCT_REC_CODE | D24: =IFERROR(VLOOKUP(C24,'字段信息'!A:C,2,),"") | F24: =B24 | G24: √ | M24: 根据原始科目判断合并 | S24: CASE WHEN ACCT_SRC_CODE LIKE '1466%' THEN '1466000000' WHEN COMPANY_CODE IN ('6500', '6510') AND ACCT_SRC_CODE IN ('2241010100', '2241010200', '2241020000', '2241040000') THEN '2241010100' WHEN COMPANY_CODE IN ('6500', '6510') AND ACCT_SRC_CODE IN ('1221010000', '1221020000', '1221040000') THEN '1221010000' WHEN COMPANY_CODE IN ('1007', '1008', '1041') AND ACCT_SRC_CODE LIKE '2202%' THEN '2202000000' WHEN COMPANY_CODE LIKE '66%' AND COMPANY_CODE <> '6600' AND ACCT_SRC_CODE LIKE '1131%' AND ACCT_SRC_CODE <> '1131999001' THEN '1131002000' WHEN COMPANY_CODE LIKE '66%' AND COMPANY_CODE <> '6600' AND ACCT_SRC_CODE LIKE '1133%' AND ACCT_SRC_CODE <> '1133999001' THEN '1133001003' WHEN COMPANY_CODE LIKE '66%' AND COMPANY_CODE <> '6600' AND ACCT_SRC_CODE LIKE '2181%' AND ACCT_SRC_CODE <> '2181999001' THEN '2181001005' WHEN COMPANY_CODE LIKE '66%' AND COMPANY_CODE <> '6600' AND ACCT_SRC_CODE LIKE '2121%' AND ACCT_SRC_CODE <> '2121999001' THEN '2121001000' WHEN COMPANY_CODE IN ('6000', '6600') AND ACCT_SRC_CODE LIKE '1131%' THEN '1131002000' WHEN COMPANY_CODE IN ('6000', '6600') AND ACCT_SRC_CODE LIKE '1133%' THEN '1133001003' WHEN COMPANY_CODE IN ('6000', '6600') AND ACCT_SRC_CODE LIKE '2181%' THEN '2181001005' WHEN COMPANY_CODE IN ('6000', '6600') AND ACCT_SRC_CODE LIKE '2121%' THEN '2121001000' WHEN COMPANY_CODE LIKE '16%' AND COMPANY_CODE NOT LIKE '163%' AND COMPANY_CODE NOT LIKE '162%' AND ACCT_SRC_CODE IN ('2202000000', '2202000089') THEN '2202000000' ELSE ACCT_SRC_CODE END
B25: =IFERROR(VLOOKUP(C25,'字段信息'!A:C,3,),"") | C25: ACCT_MAP_CODE | D25: =IFERROR(VLOOKUP(C25,'字段信息'!A:C,2,),"") | F25: =B25 | G25: √ | M25: 直接对应 | N25: doris | O25: dwd_fi_mr_arap_sum_mi | P25: acct_map_code
B26: =IFERROR(VLOOKUP(C26,'字段信息'!A:C,3,),"") | C26: LE_AGE_FLAG | D26: =IFERROR(VLOOKUP(C26,'字段信息'!A:C,2,),"") | F26: =B26 | G26: √ | L26: 普通级
B27: =IFERROR(VLOOKUP(C27,'字段信息'!A:C,3,),"") | C27: ME_AGE_FLAG | D27: =IFERROR(VLOOKUP(C27,'字段信息'!A:C,2,),"") | F27: =B27 | G27: √ | L27: 普通级
B28: =IFERROR(VLOOKUP(C28,'字段信息'!A:C,3,),"") | C28: MB_AGE_FLAG | D28: =IFERROR(VLOOKUP(C28,'字段信息'!A:C,2,),"") | F28: =B28 | G28: √ | L28: 普通级
B29: =IFERROR(VLOOKUP(C29,'字段信息'!A:C,3,),"") | C29: GRP_SCOPE | D29: =IFERROR(VLOOKUP(C29,'字段信息'!A:C,2,),"") | F29: =B29 | G29: √ | L29: 普通级
B30: =IFERROR(VLOOKUP(C30,'字段信息'!A:C,3,),"") | C30: D_CHANNEL | D30: =IFERROR(VLOOKUP(C30,'字段信息'!A:C,2,),"") | F30: =B30 | G30: √ | L30: 普通级 | M30: 直接对应 | N30: doris | O30: dwd_fi_mr_arap_sum_mi | P30: channel_l3_code | V30: 直接对应 | W30: TA | X30: AW_MR9_REVM01_000001 | Y30: D_CHANNEL | AE30: 直接对应 | AG30: dwd_fi_mr_ar_overdue_mi | AH30: channel_l3_code | AN30: 直接对应 | AO30: doris | AP30: dwd_fi_mr_arap_sum_mi | AQ30: channel_l3_code | AW30: 直接对应 | AX30: doris | AY30: dwd_fi_mr_arap_sum_mi | AZ30: channel_l3_code | BF30: 直接对应 | BG30: doris | BH30: dwd_fi_mr_arap_sum_mi | BI30: channel_l3_code
B31: =IFERROR(VLOOKUP(C31,'字段信息'!A:C,3,),"") | C31: D_ONOFFLINE | D31: =IFERROR(VLOOKUP(C31,'字段信息'!A:C,2,),"") | F31: =B31 | G31: √ | M31: 直接对应 | N31: doris | O31: dwd_fi_mr_arap_sum_mi | P31: onoffline_code | V31: 直接对应 | W31: TA | X31: AW_MR9_REVM01_000001 | Y31: D_ONOFFLINE | AE31: 直接对应 | AG31: dwd_fi_mr_ar_overdue_mi | AH31: onoffline_code | AN31: 直接对应 | AO31: doris | AP31: dwd_fi_mr_arap_sum_mi | AQ31: onoffline_code | AW31: 直接对应 | AX31: doris | AY31: dwd_fi_mr_arap_sum_mi | AZ31: onoffline_code | BF31: 直接对应 | BG31: doris | BH31: dwd_fi_mr_arap_sum_mi | BI31: onoffline_code
B32: =IFERROR(VLOOKUP(C32,'字段信息'!A:C,3,),"") | C32: COD_DEST2 | D32: =IFERROR(VLOOKUP(C32,'字段信息'!A:C,2,),"") | F32: =B32 | G32: √ | L32: 普通级 | M32: 直接对应 | N32: doris | O32: dwd_fi_mr_arap_sum_mi | P32: profitcenter_code | V32: 直接对应 | W32: TA | X32: AW_MR9_REVM01_000001 | Y32: COD_DEST2 | AE32: 直接对应 | AG32: dwd_fi_mr_ar_overdue_mi | AH32: profitcenter_code | AN32: 直接对应 | AO32: doris | AP32: dwd_fi_mr_arap_sum_mi | AQ32: profitcenter_code | AW32: 直接对应 | AX32: doris | AY32: dwd_fi_mr_arap_sum_mi | AZ32: profitcenter_code | BF32: 直接对应 | BG32: doris | BH32: dwd_fi_mr_arap_sum_mi | BI32: profitcenter_code | BO32: 直接对应 | BP32: doris | BQ32: dwd_fi_mr_ar_ureb_mi | BR32: profitcenter_code
B33: =IFERROR(VLOOKUP(C33,'字段信息'!A:C,3,),"") | C33: COD_DEST3 | D33: =IFERROR(VLOOKUP(C33,'字段信息'!A:C,2,),"") | F33: =B33 | G33: √ | L33: 普通级 | M33: 直接对应 | N33: doris | O33: dwd_fi_mr_arap_sum_mi | P33: bus_range_code | V33: 直接对应 | W33: TA | X33: AW_MR9_REVM01_000001 | Y33: COD_DEST3 | AE33: 直接对应 | AG33: dwd_fi_mr_ar_overdue_mi | AH33: bus_range_code | AN33: 直接对应 | AO33: doris | AP33: dwd_fi_mr_arap_sum_mi | AQ33: bus_range_code | AW33: 直接对应 | AX33: doris | AY33: dwd_fi_mr_arap_sum_mi | AZ33: bus_range_code | BF33: 直接对应 | BG33: doris | BH33: dwd_fi_mr_arap_sum_mi | BI33: bus_range_code
B34: =IFERROR(VLOOKUP(C34,'字段信息'!A:C,3,),"") | C34: D_SALE_DEPT | D34: =IFERROR(VLOOKUP(C33,'字段信息'!A:C,2,),"") | F34: =B34 | G34: √ | L34: 普通级 | M34: 直接对应 | N34: doris | O34: dwd_fi_mr_arap_sum_mi | P34: marketing_dept_code | V34: 直接对应 | W34: TA | X34: AW_MR9_REVM01_000001 | Y34: D_SALE_DEPT | AE34: 直接对应 | AG34: dwd_fi_mr_ar_overdue_mi | AH34: marketing_dept_code | AN34: 直接对应 | AO34: doris | AP34: dwd_fi_mr_arap_sum_mi | AQ34: marketing_dept_code | AW34: 直接对应 | AX34: doris | AY34: dwd_fi_mr_arap_sum_mi | AZ34: marketing_dept_code | BF34: 直接对应 | BG34: doris | BH34: dwd_fi_mr_arap_sum_mi | BI34: marketing_dept_code
B35: =IFERROR(VLOOKUP(C35,'字段信息'!A:C,3,),"") | C35: D_TOV_CHAN | D35: =IFERROR(VLOOKUP(C34,'字段信息'!A:C,2,),"") | F35: =B35 | G35: √ | M35: 直接对应 | N35: doris | O35: dwd_fi_mr_arap_sum_mi | P35: tov_channel_code
B36: =IFERROR(VLOOKUP(C36,'字段信息'!A:C,3,),"") | C36: D_CC_CUSTGRP | D36: =IFERROR(VLOOKUP(C34,'字段信息'!A:C,2,),"") | F36: =B36 | G36: √ | M36: 直接对应 | N36: doris | O36: dwd_fi_mr_arap_sum_mi | P36: cc_cust_group_code
B37: =IFERROR(VLOOKUP(C37,'字段信息'!A:C,3,),"") | C37: COD_VALUTA | D37: =IFERROR(VLOOKUP(C34,'字段信息'!A:C,2,),"") | F37: =B37 | G37: √ | L37: 普通级 | M37: 直接对应 | N37: doris | O37: dwd_fi_mr_arap_sum_mi | P37: bcy_code | V37: 直接对应 | W37: TA | X37: AW_MR9_REVM01_000001 | Y37: COD_VALUTA | AE37: 直接对应 | AN37: 直接对应 | AO37: doris | AP37: dwd_fi_mr_arap_sum_mi | AQ37: bcy_code | AW37: 直接对应 | AX37: doris | AY37: dwd_fi_mr_arap_sum_mi | AZ37: bcy_code | BF37: 直接对应 | BG37: doris | BH37: dwd_fi_mr_arap_sum_mi | BI37: bcy_code | BO37: 直接对应 | BP37: doris | BQ37: dwd_fi_mr_ar_ureb_mi | BR37: bcy_code
B38: =IFERROR(VLOOKUP(C38,'字段信息'!A:C,3,),"") | C38: COD_VALUTA_ORIGINARIA | D38: =IFERROR(VLOOKUP(C38,'字段信息'!A:C,2,),"") | F38: =B38 | G38: √ | L38: 普通级 | M38: 直接对应 | N38: doris | O38: dwd_fi_mr_arap_sum_mi | P38: qcy_code | V38: CNY | W38: TA | AE38: CNY | AN38: 同本位币币种 | AO38: doris | AP38: dwd_fi_mr_arap_sum_mi | AQ38: bcy_code | AW38: 同本位币币种 | AX38: doris | AY38: dwd_fi_mr_arap_sum_mi | AZ38: bcy_code | BF38: 直接对应 | BG38: doris | BH38: dwd_fi_mr_arap_sum_mi | BI38: qcy_code | BO38: 直接对应 | BP38: doris | BQ38: dwd_fi_mr_ar_ureb_mi | BR38: qcy_code
B39: =IFERROR(VLOOKUP(C39,'字段信息'!A:C,3,),"") | C39: BCY_0_AMT | D39: =IFERROR(VLOOKUP(C39,'字段信息'!A:C,2,),"") | F39: =B39 | G39: √ | L39: 普通级 | M39: 直接对应 | N39: doris | O39: dwd_fi_mr_arap_sum_mi | P39: BCY_0_AMT | V39: 汇总同一维度的BCY_REV金额数 | W39: TA | X39: AW_MR9_REVM01_000001 | Y39: BCY_REV | AE39: overdue_amt inv_sample_amt 分两行数据展示 | AG39: dwd_fi_mr_ar_overdue_mi | AH39: overdue_amt inv_sample_amt | AN39: 1、ods_src为bsid和bsad的，pay_reason_code=400，acct_map_code为1122%，判断baseline_dt<=当前年月最后一天，取大于0的数据 2、ods_src为bsid和bsad的，pay_reason_code=400，acct_map_code为1122%，取小于0的数据 3、计算1+2的数据，小于0时输出1+2的数据 | AO39: doris | AP39: dwd_fi_mr_arap_sum_mi | AQ39: bcy_amt | AW39: 客户范围限制在《电商零售客户》 ods_src为bsid和bsad的，pay_reason_code=400，acct_map_code为1122%，判断同一个科目+客商+付款服务商编号的金额>0且最小的基准日期大于本月的最后一天 | AX39: doris | AY39: dwd_fi_mr_arap_sum_mi | AZ39: bcy_amt | BF39: 合计所有的金额 | BG39: doris | BH39: dwd_fi_mr_arap_sum_mi | BI39: bcy_amt | BK39: 筛选条件： 1、acct_cert_type = zz 2、pay_reason_code = 800 3、acct_map_code为1122% | BO39: 合计所有的金额 | BP39: doris | BR39: bcy_amt
B40: =IFERROR(VLOOKUP(C40,'字段信息'!A:C,3,),"") | C40: BCY_1_AMT | D40: =IFERROR(VLOOKUP(C40,'字段信息'!A:C,2,),"") | F40: =B40 | G40: √ | L40: 普通级 | M40: 直接对应 | N40: doris | O40: dwd_fi_mr_arap_sum_mi | P40: BCY_1_AMT | V40: 汇总同一维度的BCY_REV金额数 | W40: TA | X40: AW_MR9_REVM01_000001 | Y40: BCY_REV | AE40: overdue_amt inv_sample_amt 分两行数据展示 | AG40: dwd_fi_mr_ar_overdue_mi | AH40: overdue_amt inv_sample_amt | AN40: 同BCY_AMT0 | AO40: doris | AP40: dwd_fi_mr_arap_sum_mi | AQ40: bcy_amt | AW40: 同BCY_AMT0 | AX40: doris | AY40: dwd_fi_mr_arap_sum_mi | AZ40: bcy_amt | BF40: 合计所有的金额，不区分账龄区间 | BG40: doris | BH40: dwd_fi_mr_arap_sum_mi | BI40: bcy_amt | BO40: 合计所有的金额，不区分账龄区间 | BP40: doris | BQ40: dwd_fi_mr_arap_sum_mi | BR40: bcy_amt
B41: =IFERROR(VLOOKUP(C41,'字段信息'!A:C,3,),"") | C41: BCY_2_AMT | D41: =IFERROR(VLOOKUP(C41,'字段信息'!A:C,2,),"") | F41: =B41 | G41: √ | L41: 普通级 | M41: 直接对应 | N41: doris | O41: dwd_fi_mr_arap_sum_mi | P41: BCY_2_AMT
B42: =IFERROR(VLOOKUP(C42,'字段信息'!A:C,3,),"") | C42: BCY_3_AMT | D42: =IFERROR(VLOOKUP(C42,'字段信息'!A:C,2,),"") | F42: =B42 | G42: √ | L42: 普通级 | M42: 直接对应 | N42: doris | O42: dwd_fi_mr_arap_sum_mi | P42: BCY_3_AMT
B43: =IFERROR(VLOOKUP(C43,'字段信息'!A:C,3,),"") | C43: BCY_4_AMT | D43: =IFERROR(VLOOKUP(C43,'字段信息'!A:C,2,),"") | F43: =B43 | G43: √ | L43: 普通级 | M43: 直接对应 | N43: doris | O43: dwd_fi_mr_arap_sum_mi | P43: BCY_4_AMT
B44: =IFERROR(VLOOKUP(C44,'字段信息'!A:C,3,),"") | C44: BCY_5_AMT | D44: =IFERROR(VLOOKUP(C44,'字段信息'!A:C,2,),"") | F44: =B44 | G44: √ | L44: 普通级 | M44: 直接对应 | N44: doris | O44: dwd_fi_mr_arap_sum_mi | P44: BCY_5_AMT
B45: =IFERROR(VLOOKUP(C45,'字段信息'!A:C,3,),"") | C45: BCY_6_AMT | D45: =IFERROR(VLOOKUP(C45,'字段信息'!A:C,2,),"") | F45: =B45 | G45: √ | L45: 普通级 | M45: 直接对应 | N45: doris | O45: dwd_fi_mr_arap_sum_mi | P45: BCY_6_AMT
B46: =IFERROR(VLOOKUP(C46,'字段信息'!A:C,3,),"") | C46: BCY_7_AMT | D46: =IFERROR(VLOOKUP(C46,'字段信息'!A:C,2,),"") | F46: =B46 | G46: √ | L46: 普通级 | M46: 直接对应 | N46: doris | O46: dwd_fi_mr_arap_sum_mi | P46: BCY_7_AMT
B47: =IFERROR(VLOOKUP(C47,'字段信息'!A:C,3,),"") | C47: BCY_8_AMT | D47: =IFERROR(VLOOKUP(C47,'字段信息'!A:C,2,),"") | F47: =B47 | G47: √ | L47: 普通级 | M47: 直接对应 | N47: doris | O47: dwd_fi_mr_arap_sum_mi | P47: BCY_8_AMT
B48: =IFERROR(VLOOKUP(C48,'字段信息'!A:C,3,),"") | C48: BCY_9_AMT | D48: =IFERROR(VLOOKUP(C48,'字段信息'!A:C,2,),"") | F48: =B48 | G48: √ | L48: 普通级 | M48: 直接对应 | N48: doris | O48: dwd_fi_mr_arap_sum_mi | P48: BCY_9_AMT
B49: =IFERROR(VLOOKUP(C49,'字段信息'!A:C,3,),"") | C49: BCY_10_AMT | D49: =IFERROR(VLOOKUP(C49,'字段信息'!A:C,2,),"") | F49: =B49 | G49: √ | L49: 普通级 | M49: 直接对应 | N49: doris | O49: dwd_fi_mr_arap_sum_mi | P49: BCY_10_AMT
B50: =IFERROR(VLOOKUP(C50,'字段信息'!A:C,3,),"") | C50: BCY_11_AMT | D50: =IFERROR(VLOOKUP(C50,'字段信息'!A:C,2,),"") | F50: =B50 | G50: √ | L50: 普通级 | M50: 直接对应 | N50: doris | O50: dwd_fi_mr_arap_sum_mi | P50: BCY_11_AMT
B51: =IFERROR(VLOOKUP(C51,'字段信息'!A:C,3,),"") | C51: BCY_12_AMT | D51: =IFERROR(VLOOKUP(C51,'字段信息'!A:C,2,),"") | F51: =B51 | G51: √ | L51: 普通级 | M51: 直接对应 | N51: doris | O51: dwd_fi_mr_arap_sum_mi | P51: BCY_12_AMT
B52: =IFERROR(VLOOKUP(C52,'字段信息'!A:C,3,),"") | C52: BCY_13_AMT | D52: =IFERROR(VLOOKUP(C52,'字段信息'!A:C,2,),"") | F52: =B52 | G52: √ | L52: 普通级 | M52: 直接对应 | N52: doris | O52: dwd_fi_mr_arap_sum_mi | P52: BCY_13_AMT
... B54: =IFERROR(VLOOKUP(C54,'字段信息'!A:C,3,),"") | C54: BCY_15_AMT | D54: =IFERROR(VLOOKUP(C54,'字段信息'!A:C,2,),"") | F54: =B54 | G54: √ | L54: 普通级 | M54: 直接对应 | N54: doris | O54: dwd_fi_mr_arap_sum_mi | P54: BCY_15_AMT
B55: =IFERROR(VLOOKUP(C55,'字段信息'!A:C,3,),"") | C55: QCY_0_AMT | D55: =IFERROR(VLOOKUP(C55,'字段信息'!A:C,2,),"") | F55: =B55 | G55: √ | L55: 普通级 | M55: 直接对应 | N55: doris | O55: dwd_fi_mr_arap_sum_mi | P55: QCY_0_AMT | V55: 汇总同一维度的ORG_REV金额数 | W55: TA | X55: AW_MR9_REVM01_000001 | Y55: ORG_REV | AE55: overdue_amt inv_sample_amt 分两行数据展示 | AG55: dwd_fi_mr_ar_overdue_mi | AH55: overdue_amt inv_sample_amt | AN55: 限制客户范围不在《电商零售客户》 1、应收账款金额：ods_src为bsid和bsad的，pay_reason_code=400，acct_map_code为1122%，判断baseline_dt<=当前年月最后一天，取大于0的数据 2、本账期回款金额：ods_src为bsid和bsad的，pay_reason_code=400，acct_map_code为1122%，取小于0的数据 3、计算1+2的数据，小于0时输出1+2的数据 | AO55: doris | AP55: dwd_fi_mr_arap_sum_mi | AQ55: bcy_amt | AW55: 限制客户范围在《电商零售客户》 ods_src为bsid和bsad的，pay_reason_code=400，acct_map_code为1122%，判断同一个科目+客商+付款服务商编号的金额>0且最小的基准日期大于本月的最后一天 | AX55: doris | AY55: dwd_fi_mr_arap_sum_mi | AZ55: bcy_amt | BF55: 合计所有的金额 | BG55: doris | BH55: dwd_fi_mr_arap_sum_mi | BI55: qcy_amt | BO55: 合计所有的金额 | BP55: doris | BQ55: dwd_fi_mr_arap_sum_mi | BR55: qcy_amt
B56: =IFERROR(VLOOKUP(C56,'字段信息'!A:C,3,),"") | C56: QCY_1_AMT | D56: =IFERROR(VLOOKUP(C56,'字段信息'!A:C,2,),"") | F56: =B56 | G56: √ | L56: 普通级 | M56: 直接对应 | N56: doris | O56: dwd_fi_mr_arap_sum_mi | P56: QCY_1_AMT | V56: 汇总同一维度的ORG_REV金额数 | W56: TA | X56: AW_MR9_REVM01_000001 | Y56: ORG_REV | AE56: overdue_amt inv_sample_amt 分两行数据展示 | AG56: dwd_fi_mr_ar_overdue_mi | AH56: overdue_amt inv_sample_amt | AN56: 同BCY_AMT0 | AO56: doris | AP56: dwd_fi_mr_arap_sum_mi | AQ56: bcy_amt | AW56: 同BCY_AMT0 | AX56: doris | AY56: dwd_fi_mr_arap_sum_mi | AZ56: bcy_amt | BF56: 合计所有的金额，不区分账龄区间 | BG56: doris | BH56: dwd_fi_mr_arap_sum_mi | BI56: qcy_amt | BO56: 合计所有的金额，不区分账龄区间 | BP56: doris | BQ56: dwd_fi_mr_arap_sum_mi | BR56: qcy_amt
B57: =IFERROR(VLOOKUP(C57,'字段信息'!A:C,3,),"") | C57: QCY_2_AMT | D57: =IFERROR(VLOOKUP(C57,'字段信息'!A:C,2,),"") | F57: =B57 | G57: √ | L57: 普通级 | M57: 直接对应 | N57: doris | O57: dwd_fi_mr_arap_sum_mi | P57: QCY_2_AMT
B58: =IFERROR(VLOOKUP(C58,'字段信息'!A:C,3,),"") | C58: QCY_3_AMT | D58: =IFERROR(VLOOKUP(C58,'字段信息'!A:C,2,),"") | F58: =B58 | G58: √ | L58: 普通级 | M58: 直接对应 | N58: doris | O58: dwd_fi_mr_arap_sum_mi | P58: QCY_3_AMT
B59: =IFERROR(VLOOKUP(C59,'字段信息'!A:C,3,),"") | C59: QCY_4_AMT | D59: =IFERROR(VLOOKUP(C59,'字段信息'!A:C,2,),"") | F59: =B59 | G59: √ | L59: 普通级 | M59: 直接对应 | N59: doris | O59: dwd_fi_mr_arap_sum_mi | P59: QCY_4_AMT
B60: =IFERROR(VLOOKUP(C60,'字段信息'!A:C,3,),"") | C60: QCY_5_AMT | D60: =IFERROR(VLOOKUP(C60,'字段信息'!A:C,2,),"") | F60: =B60 | G60: √ | L60: 普通级 | M60: 直接对应 | N60: doris | O60: dwd_fi_mr_arap_sum_mi | P60: QCY_5_AMT
B61: =IFERROR(VLOOKUP(C61,'字段信息'!A:C,3,),"") | C61: QCY_6_AMT | D61: =IFERROR(VLOOKUP(C61,'字段信息'!A:C,2,),"") | F61: =B61 | G61: √ | L61: 普通级 | M61: 直接对应 | N61: doris | O61: dwd_fi_mr_arap_sum_mi | P61: QCY_6_AMT
B62: =IFERROR(VLOOKUP(C62,'字段信息'!A:C,3,),"") | C62: QCY_7_AMT | D62: =IFERROR(VLOOKUP(C62,'字段信息'!A:C,2,),"") | F62: =B62 | G62: √ | L62: 普通级 | M62: 直接对应 | N62: doris | O62: dwd_fi_mr_arap_sum_mi | P62: QCY_7_AMT
B63: =IFERROR(VLOOKUP(C63,'字段信息'!A:C,3,),"") | C63: QCY_8_AMT | D63: =IFERROR(VLOOKUP(C63,'字段信息'!A:C,2,),"") | F63: =B63 | G63: √ | L63: 普通级 | M63: 直接对应 | N63: doris | O63: dwd_fi_mr_arap_sum_mi | P63: QCY_8_AMT
B64: =IFERROR(VLOOKUP(C64,'字段信息'!A:C,3,),"") | C64: QCY_9_AMT | D64: =IFERROR(VLOOKUP(C64,'字段信息'!A:C,2,),"") | F64: =B64 | G64: √ | L64: 普通级 | M64: 直接对应 | N64: doris | O64: dwd_fi_mr_arap_sum_mi | P64: QCY_9_AMT
B65: =IFERROR(VLOOKUP(C65,'字段信息'!A:C,3,),"") | C65: QCY_10_AMT | D65: =IFERROR(VLOOKUP(C65,'字段信息'!A:C,2,),"") | F65: =B65 | G65: √ | L65: 普通级 | M65: 直接对应 | N65: doris | O65: dwd_fi_mr_arap_sum_mi | P65: QCY_10_AMT
B66: =IFERROR(VLOOKUP(C66,'字段信息'!A:C,3,),"") | C66: QCY_11_AMT | D66: =IFERROR(VLOOKUP(C66,'字段信息'!A:C,2,),"") | F66: =B66 | G66: √ | M66: 直接对应 | N66: doris | O66: dwd_fi_mr_arap_sum_mi | P66: QCY_11_AMT
B67: =IFERROR(VLOOKUP(C67,'字段信息'!A:C,3,),"") | C67: QCY_12_AMT | D67: =IFERROR(VLOOKUP(C67,'字段信息'!A:C,2,),"") | F67: =B67 | G67: √ | M67: 直接对应 | N67: doris | O67: dwd_fi_mr_arap_sum_mi | P67: QCY_12_AMT
B68: =IFERROR(VLOOKUP(C68,'字段信息'!A:C,3,),"") | C68: QCY_13_AMT | D68: =IFERROR(VLOOKUP(C68,'字段信息'!A:C,2,),"") | F68: =B68 | G68: √ | M68: 直接对应 | N68: doris | O68: dwd_fi_mr_arap_sum_mi | P68: QCY_13_AMT
B69: =IFERROR(VLOOKUP(C69,'字段信息'!A:C,3,),"") | C69: QCY_14_AMT | D69: =IFERROR(VLOOKUP(C69,'字段信息'!A:C,2,),"") | F69: =B69 | G69: √ | M69: 直接对应 | N69: doris | O69: dwd_fi_mr_arap_sum_mi | P69: QCY_14_AMT
B70: =IFERROR(VLOOKUP(C70,'字段信息'!A:C,3,),"") | C70: QCY_15_AMT | D70: =IFERROR(VLOOKUP(C70,'字段信息'!A:C,2,),"") | F70: =B70 | G70: √ | M70: 直接对应 | N70: doris | O70: dwd_fi_mr_arap_sum_mi | P70: QCY_15_AMT
B71: =IFERROR(VLOOKUP(C71,'字段信息'!A:C,3,),"") | C71: SYSTEM_SRC | D71: =IFERROR(VLOOKUP(C71,'字段信息'!A:C,2,),"") | F71: =B71 | G71: √ | M71: 直接对应 | N71: doris | O71: dwd_fi_mr_arap_sum_mi | P71: system_src
B72: =IFERROR(VLOOKUP(C72,'字段信息'!A:C,3,),"") | C72: D_ADJ_TYPE | D72: =IFERROR(VLOOKUP(C72,'字段信息'!A:C,2,),"") | F72: =B72 | G72: √ | M72: 直接对应 | P72: ZZZZ
B73: =IFERROR(VLOOKUP(C73,'字段信息'!A:C,3,),"") | C73: TAX_RATE | D73: =IFERROR(VLOOKUP(C73,'字段信息'!A:C,2,),"") | F73: =B73 | G73: √ | M73: 直接对应 | N73: doris | O73: dwd_fi_mr_arap_sum_mi | P73: TAX_RATE
B74: =IFERROR(VLOOKUP(C74,'字段信息'!A:C,3,),"") | C74: NATURE_L1_NAME | D74: =IFERROR(VLOOKUP(C74,'字段信息'!A:C,2,),"") | F74: =B74 | G74: √ | M74: 直接对应 | N74: doris | O74: dwd_fi_mr_arap_sum_mi | P74: NATURE_L1_NAME
B75: =IFERROR(VLOOKUP(C75,'字段信息'!A:C,3,),"") | C75: NATURE_L2_NAME | D75: =IFERROR(VLOOKUP(C75,'字段信息'!A:C,2,),"") | F75: =B75 | G75: √ | M75: 直接对应 | N75: doris | O75: dwd_fi_mr_arap_sum_mi | P75: NATURE_L2_NAME
B76: =IFERROR(VLOOKUP(C76,'字段信息'!A:C,3,),"") | C76: NATURE_L3_NAME | D76: =IFERROR(VLOOKUP(C76,'字段信息'!A:C,2,),"") | F76: =B76 | G76: √ | M76: 直接对应 | N76: doris | O76: dwd_fi_mr_arap_sum_mi | P76: NATURE_L3_NAME
B77: =IFERROR(VLOOKUP(C77,'字段信息'!A:C,3,),"") | C77: UFEE_UREB_FLAG | D77: =IFERROR(VLOOKUP(C77,'字段信息'!A:C,2,),"") | F77: =B77 | G77: √ | M77: 直接对应 | N77: doris | O77: dwd_fi_mr_arap_sum_mi | P77: UFEE_UREB_FLAG
B78: =IFERROR(VLOOKUP(C78,'字段信息'!A:C,3,),"") | C78: ECLS_FLAG | D78: =IFERROR(VLOOKUP(C78,'字段信息'!A:C,2,),"") | F78: =B78 | G78: √ | M78: 直接对应 | N78: doris | O78: dwd_fi_mr_arap_sum_mi | P78: ECLS_FLAG
B79: =IFERROR(VLOOKUP(C79,'字段信息'!A:C,3,),"") | C79: PAY_TERM_CODE | D79: =IFERROR(VLOOKUP(C79,'字段信息'!A:C,2,),"") | F79: =B79 | G79: √ | M79: 直接对应 | N79: doris | O79: dwd_fi_mr_arap_sum_mi | P79: PAY_TERM_CODE
B80: =IFERROR(VLOOKUP(C80,'字段信息'!A:C,3,),"") | C80: PAY_TERM_DESC | D80: =IFERROR(VLOOKUP(C80,'字段信息'!A:C,2,),"") | F80: =B80 | G80: √ | M80: 直接对应 | N80: doris | O80: dwd_fi_mr_arap_sum_mi | P80: PAY_TERM_DESC
B81: =IFERROR(VLOOKUP(C81,'字段信息'!A:C,3,),"") | C81: EXCHANGE_RATE_EVAL_FLAG | D81: =IFERROR(VLOOKUP(C81,'字段信息'!A:C,2,),"") | F81: =B81 | G81: √ | M81: 直接对应 | N81: doris | O81: dwd_fi_mr_arap_sum_mi | P81: EXCHANGE_RATE_EVAL_FLAG

Sheet ARPM01账龄计算底稿-STEP2数据范围限制
A1: 返回 | B1: AW_MR9_ARPM01_000001逻辑处理
A2: 规则库 | B2: 表名称 | C2: AW_MR9_ARPM01_000001
B3: 表描述 | C3: 往来账龄计算底稿 | D3: 表类型 | E3: 事实表 | F3: 数仓分层 | G3: DWM
B4: L1数仓目录 | C4: 管理财经 | D4: L2数仓目录 | E4: 财报管理 | F4: L3数仓目录 | G4: 应收
B5: 更新方式 | C5: 增量更新 | D5: 设计人员 | F5: 时间
B6: 使用场景 | C6: 往来账龄需要对部分客商或科目等进行剔除，此步骤用于将步骤1取到的数据根据进数范围进行限制
B7: 目标表 | M7: 往来账龄计算底稿【AW_MR9_ARPM01_000001】
B8: 字段中文名称 | C8: *字段名称 | D8: *类型 | E8: 主键 | F8: *描述 | G8: 允许为空 | H8: 默认值 | I8: 聚合类型 | J8: 基础标准 | K8: 标准代码 | L8: *安全分级 | M8: 转换清洗规则 | N8: 源系统 | O8: 源头表 | P8: 源头字段 | Q8: 匹配字段 | R8: 匹配过滤 | S8: 数仓处理脚本 | T8: 备注
B9: =IFERROR(VLOOKUP(C9,'字段信息'!A:C,3,),"") | C9: COD_SCENARIO | D9: =IFERROR(VLOOKUP(C9,'字段信息'!A:C,2,),"") | F9: =B9 | M9: 直接对应 | N9: doris | O9: dwd_fi_mr_arap_sum_mi | P9: year+"ACT"
B10: =IFERROR(VLOOKUP(C10,'字段信息'!A:C,3,),"") | C10: COD_PERIODO | D10: =IFERROR(VLOOKUP(C10,'字段信息'!A:C,2,),"") | F10: =B10 | G10: √ | L10: 普通级 | M10: 直接对应 | N10: doris | O10: dwd_fi_mr_arap_sum_mi | P10: month
B11: =IFERROR(VLOOKUP(C11,'字段信息'!A:C,3,),"") | C11: COD_AZIENDA | D11: =IFERROR(VLOOKUP(C11,'字段信息'!A:C,2,),"") | F11: =B11 | G11: √ | L11: 普通级 | M11: 根据《账龄表进数范围维护》表按取数类型进行数据的剔除和取数 1、取数类型为EX1-按公司+客商剔除：根据公司和客商匹配，排除对应的公司+客商数据 2、取数类型为EX2-按公司+科目剔除：根据公司和科目匹配，排除对应的公司+科目数据 3、取数类型为EX3-按系统号+科目剔除：根据系统号和科目匹配，排除对应的系统号+科目数据 4、取数类型为IN1-按系统号+公司+科目剔除：根据系统号和公司和科目匹配，取对应的数据 | N11: doris | O11: dwd_fi_mr_arap_sum_mi | P11: company_code | R11: 按照1.0的配置表过滤数据 1、排除: 国际营销客户(ZS_APAR01_IPT04/XT02) 2、排除: 暂估科目(ZS_APAR01_IPT06/XT02/XT03) | S11: 1、CVCODE NOT IN (select TESTO_11 from tgk_gb_hisense.form_dati where cod_prospetto = 'ZS_APAR01_IPT04' and COD_AZIENDA =V_ENTITY AND COD_CATEGORIA='XT02' AND LTRIM(TRIM(TESTO_11),'0') IS NOT NULL AND V_YEARMONTH BETWEEN NVL(TRIM(TESTO_13),'0') AND NVL(TRIM(TESTO_13),'999999') 2、(ZS.MANDT||ZS.HKONT NOT IN (select TRIM(TESTO_1)||TRIM(TESTO_3) from tgk_gb_hisense.form_dati FD where cod_prospetto = 'ZS_APAR01_IPT06' AND COD_CATEGORIA='XT02' AND TRIM(TESTO_3) IS NOT NULL AND V_YEARMONTH BETWEEN NVL(TRIM(TESTO_13),'0') AND NVL(TRIM(TESTO_13),'999999') ) OR ZS.MANDT||ZS.BUKRS||ZS.HKONT IN (select TRIM(TESTO_1)||TRIM(TESTO_12)||TRIM(TESTO_3) from tgk_gb_hisense.form_dati FD where cod_prospetto = 'ZS_APAR01_IPT06' AND COD_CATEGORIA='XT03' AND TRIM(TESTO_13)='A' AND TRIM(TESTO_3) IS NOT NULL) ) AND ZS.MANDT||ZS.BUKRS||ZS.HKONT NOT IN (select TRIM(TESTO_1)||TRIM(TESTO_12)||TRIM(TESTO_3) from tgk_gb_hisense.form_dati FD where cod_prospetto = 'ZS_APAR01_IPT06' AND COD_CATEGORIA='XT03' AND TRIM(TESTO_13)='B' AND TRIM(TESTO_3) IS NOT NULL)
B12: =IFERROR(VLOOKUP(C12,'字段信息'!A:C,3,),"") | C12: COD_CONTO | D12: =IFERROR(VLOOKUP(C12,'字段信息'!A:C,2,),"") | F12: =B12 | G12: √ | L12: 普通级 | N12: doris | O12: dwd_fi_mr_arap_sum_mi | P12: acct_map_code
B13: =IFERROR(VLOOKUP(C13,'字段信息'!A:C,3,),"") | C13: ACCT_SRC_CODE | D13: =IFERROR(VLOOKUP(C13,'字段信息'!A:C,2,),"") | F13: =B13 | G13: √ | N13: doris | O13: dwd_fi_mr_arap_sum_mi | P13: acct_src_code
B14: =IFERROR(VLOOKUP(C14,'字段信息'!A:C,3,),"") | C14: CUST_CODE | D14: =IFERROR(VLOOKUP(C14,'字段信息'!A:C,2,),"") | F14: =B14 | G14: √ | L14: 普通级 | N14: doris | O14: dwd_fi_mr_arap_sum_mi | P14: cust_code
B15: =IFERROR(VLOOKUP(C15,'字段信息'!A:C,3,),"") | C15: CUST_NAME | D15: =IFERROR(VLOOKUP(C15,'字段信息'!A:C,2,),"") | F15: =B15 | G15: √ | L15: 普通级 | M15: 直接对应 | N15: doris | O15: dwd_fi_mr_arap_sum_mi | P15: cust_name
B16: =IFERROR(VLOOKUP(C16,'字段信息'!A:C,3,),"") | C16: SYSTEM_SRC | D16: =IFERROR(VLOOKUP(C16,'字段信息'!A:C,2,),"") | F16: =B16 | G16: √ | M16: 直接对应 | N16: doris | O16: dwd_fi_mr_arap_sum_mi | P16: system_src

Sheet ARPM01账龄计算底稿-STEP3重分类处理
A1: 返回 | B1: AW_MR9_ARPM01_000001逻辑处理
A2: 规则库 | B2: 表名称 | C2: AW_MR9_ARPM01_000001 | M2: 存储过程名称：CPM_SP_D2M_ARP_M
B3: 表描述 | C3: 往来账龄计算底稿 | D3: 表类型 | E3: 事实表 | F3: 数仓分层 | G3: DWM | M3: 参数：场景 P_SCENARIO
B4: L1数仓目录 | C4: 管理财经 | D4: L2数仓目录 | E4: 财报管理 | F4: L3数仓目录 | G4: 应收 | M4: 期间：P_PERIODO
B5: 更新方式 | C5: 增量更新 | D5: 设计人员 | F5: 时间 | M5: 公司：P_AZIENDA
B6: 使用场景 | C6: 此步骤将往来账龄的数据根据重分类的规则进行重分类的判断，法人口径、管理口径、管理分公司口径三个口径的重分类处理，以及集团归属范围的判断 | M6: 用户：SESSION_USER
B7: 目标表 | M7: 往来账龄计算底稿【AW_MR9_ARPM01_000001】
B8: 字段中文名称 | C8: *字段名称 | D8: *类型 | E8: 主键 | F8: *描述 | G8: 允许为空 | H8: 默认值 | I8: 聚合类型 | J8: 基础标准 | K8: 标准代码 | L8: *安全分级 | M8: 转换清洗规则 | N8: 源系统 | O8: 源头表 | P8: 源头字段 | Q8: 匹配字段 | R8: 匹配过滤 | S8: 数仓处理脚本 | T8: 备注
B9: =IFERROR(VLOOKUP(C9,'字段信息'!A:C,3,),"") | C9: COD_CONTO | D9: =IFERROR(VLOOKUP(C9,'字段信息'!A:C,2,),"") | F9: =B9 | G9: √ | M9: 根据LE_AGE_FLG对应 AR 1122000000 OR 122101F AS 1123000000 CA 1460000000 RF 1124001000 AP 2202000000 OP 224199F AC 2203000000 CL 2204000000 A9 1910000A70 A10 1531000000
B10: =IFERROR(VLOOKUP(C10,'字段信息'!A:C,3,),"") | C10: LE_AGE_FLAG | D10: =IFERROR(VLOOKUP(C10,'字段信息'!A:C,2,),"") | F10: =B10 | G10: √ | L10: 普通级 | M10: 使用重分类函数F_APAR_REC，根据系统号+公司+科目范围+主户匹配，判断同一账套+主户编码下数据分类为BS%和总账标识（FAGLFLEXT/GLFUNCT）的bcy_amt金额汇总是否符合金额条件，输出【重分类标识】 | N10: TA | O10: AW_MR9_ARPM01_000001
B11: =IFERROR(VLOOKUP(C11,'字段信息'!A:C,3,),"") | C11: IS_REC_LG | D11: =IFERROR(VLOOKUP(C11,'字段信息'!A:C,2,),"") | F11: =B11 | G11: √ | M11: 使用重分类函数F_APAR_REC，根据系统号+公司+科目范围+主户匹配，判断同一账套+主户编码下数据分类为BS%和总账标识（FAGLFLEXT/GLFUNCT）的bcy_amt金额汇总是否符合金额条件，输出【是否重分类】 | N11: TA | O11: AW_MR9_ARPM01_000001
B12: =IFERROR(VLOOKUP(C12,'字段信息'!A:C,3,),"") | C12: ME_AGE_FLAG | D12: =IFERROR(VLOOKUP(C12,'字段信息'!A:C,2,),"") | F12: =B12 | G12: √ | L12: 普通级 | M12: 使用重分类函数F_APAR_REC，根据系统号+公司+科目范围+主户匹配，判断同一账套+主户编码下数据分类为BS%和总账标识（FAGLFLEXT/GLFUNCT）和ZTSO04%的bcy_amt金额汇总是否符合金额条件，输出【重分类标识】 | N12: TA | O12: AW_MR9_ARPM01_000001
B13: =IFERROR(VLOOKUP(C13,'字段信息'!A:C,3,),"") | C13: IS_REC_ME | D13: =IFERROR(VLOOKUP(C13,'字段信息'!A:C,2,),"") | F13: =B13 | G13: √ | M13: 使用重分类函数F_APAR_REC，根据系统号+公司+科目范围+主户匹配，判断同一账套+主户编码下数据分类为BS%和总账标识（FAGLFLEXT/GLFUNCT）和ZTSO04%的bcy_amt金额汇总是否符合金额条件，输出【是否重分类】 | N13: TA | O13: AW_MR9_ARPM01_000001
B14: =IFERROR(VLOOKUP(C14,'字段信息'!A:C,3,),"") | C14: MB_AGE_FLAG | D14: =IFERROR(VLOOKUP(C14,'字段信息'!A:C,2,),"") | F14: =B14 | G14: √ | L14: 普通级 | M14: 使用重分类函数F_APAR_REC，根据系统号+公司+科目范围+主户匹配，判断同一账套+主户编码+利润中心下数据分类为BS%和总账标识（FAGLFLEXT/GLFUNCT）和ZTSO04%的bcy_amt金额汇总是否符合金额条件，输出【重分类标识】 | N14: TA | O14: AW_MR9_ARPM01_000001
B15: =IFERROR(VLOOKUP(C15,'字段信息'!A:C,3,),"") | C15: IS_REC_MB | D15: =IFERROR(VLOOKUP(C15,'字段信息'!A:C,2,),"") | F15: =B15 | G15: √ | M15: 使用重分类函数F_APAR_REC，根据系统号+公司+科目范围+主户匹配，判断同一账套+主户编码+利润中心下数据分类为BS%和总账标识（FAGLFLEXT/GLFUNCT）和ZTSO04%的bcy_amt金额汇总是否符合金额条件，输出【是否重分类】 | N15: TA | O15: AW_MR9_ARPM01_000001
B16: =IFERROR(VLOOKUP(C16,'字段信息'!A:C,3,),"") | C16: GRP_SCOPE | D16: =IFERROR(VLOOKUP(C16,'字段信息'!A:C,2,),"") | F16: =B16 | G16: √ | L16: 普通级 | M16: 按照场景期间公司，取1.0视图V_APAR_ELEM_NODE_TAB，获取两个字段node（如果是日立公司则取nodes），hq 在使用对方公司匹配这个视图V_APAR_ELEM_NODE_TAB，如果两个字段都相等，那么放SUB-子公司，如果只有HQ相等，放GIN-集团内，其他放GEX-集团外 | N16: TA | O16: AW_MR9_ARPM01_000001

Sheet ARPM02-账龄结果表
A1: 返回 | B1: AW_MR9_ARPM02_000001逻辑处理
A2: 规则库 | B2: 表名称 | C2: AW_MR9_ARPM02_000001 | M2: 存储过程名称：CPM_SP_M2M_ARP_AG_M
B3: 表描述 | C3: 往来账龄结果表 | D3: 表类型 | E3: 事实表 | F3: 数仓分层 | G3: DWM | M3: 参数：场景 P_SCENARIO
B4: L1数仓目录 | C4: 管理财经 | D4: L2数仓目录 | E4: 财报管理 | F4: L3数仓目录 | G4: 应收 | M4: 期间：P_PERIODO
B5: 更新方式 | C5: 增量更新 | D5: 设计人员 | F5: 时间 | M5: 公司：P_AZIENDA
B6: 使用场景 | C6: 此表将往来账龄计算底稿不同数据分类的数据平铺到列上展示，并且针对应收重分类到合同负债的数据，把对应的税额剔除 | M6: 用户：SESSION_USER | O6: 0908：年初、期初等需要放出来，有可能会有修改
B7: 目标表 | M7: 往来账龄计算底稿【AW_MR9_ARPM01_000001】
B8: 字段中文名称 | C8: *字段名称 | D8: *类型 | E8: 主键 | F8: *描述 | G8: 允许为空 | H8: 默认值 | I8: 聚合类型 | J8: 基础标准 | K8: 标准代码 | L8: *安全分级 | M8: 转换清洗规则 | N8: 源系统 | O8: 源头表 | P8: 源头字段 | Q8: 匹配字段 | R8: 匹配过滤 | S8: 数仓处理脚本 | T8: 备注
B9: =IFERROR(VLOOKUP(C9,'字段信息'!A:C,3,),"") | C9: COD_SCENARIO | D9: =IFERROR(VLOOKUP(C9,'字段信息'!A:C,2,),"") | F9: =B9 | M9: 直接对应 | N9: TA | O9: AW_MR9_ARPM01_000001 | P9: COD_SCENARIO
B10: =IFERROR(VLOOKUP(C10,'字段信息'!A:C,3,),"") | C10: COD_PERIODO | D10: =IFERROR(VLOOKUP(C10,'字段信息'!A:C,2,),"") | F10: =B10 | G10: √ | L10: 普通级 | M10: 直接对应 | N10: TA | O10: AW_MR9_ARPM01_000001 | P10: COD_PERIODO
B11: =IFERROR(VLOOKUP(C11,'字段信息'!A:C,3,),"") | C11: COD_AZIENDA | D11: =IFERROR(VLOOKUP(C11,'字段信息'!A:C,2,),"") | F11: =B11 | G11: √ | L11: 普通级 | M11: 直接对应 | N11: TA | O11: AW_MR9_ARPM01_000001 | P11: COD_AZIENDA
B12: =IFERROR(VLOOKUP(C12,'字段信息'!A:C,3,),"") | C12: COD_CONTO | D12: =IFERROR(VLOOKUP(C12,'字段信息'!A:C,2,),"") | F12: =B12 | G12: √ | L12: 普通级 | M12: 直接对应 | N12: TA | O12: AW_MR9_ARPM01_000001 | P12: COD_CONTO
B13: =IFERROR(VLOOKUP(C13,'字段信息'!A:C,3,),"") | C13: COD_CATEGORIA | D13: =IFERROR(VLOOKUP(C13,'字段信息'!A:C,2,),"") | F13: =B13 | G13: √ | L13: 普通级 | M13: ZAMOUNT
B14: =IFERROR(VLOOKUP(C14,'字段信息'!A:C,3,),"") | C14: CUST_CODE | D14: =IFERROR(VLOOKUP(C14,'字段信息'!A:C,2,),"") | F14: =B14 | G14: √ | L14: 普通级 | M14: 直接对应 | N14: TA | O14: AW_MR9_ARPM01_000001 | P14: CUST_CODE
B15: =IFERROR(VLOOKUP(C15,'字段信息'!A:C,3,),"") | C15: CUST_NAME | D15: =IFERROR(VLOOKUP(C15,'字段信息'!A:C,2,),"") | F15: =B15 | G15: √ | L15: 普通级 | M15: 直接对应 | N15: TA | O15: AW_MR9_ARPM01_000001 | P15: CUST_NAME
B16: =IFERROR(VLOOKUP(C16,'字段信息'!A:C,3,),"") | C16: CUST_HEAD_CODE | D16: =IFERROR(VLOOKUP(C16,'字段信息'!A:C,2,),"") | F16: =B16 | G16: √ | L16: 普通级 | M16: 直接对应 | N16: TA | O16: AW_MR9_ARPM01_000001 | P16: CUST_HEAD_CODE
B17: =IFERROR(VLOOKUP(C17,'字段信息'!A:C,3,),"") | C17: CUST_HEAD_NAME | D17: =IFERROR(VLOOKUP(C17,'字段信息'!A:C,2,),"") | F17: =B17 | G17: √ | M17: 直接对应 | N17: TA | O17: AW_MR9_ARPM01_000001 | P17: CUST_HEAD_NAME
B18: =IFERROR(VLOOKUP(C18,'字段信息'!A:C,3,),"") | C18: CUST_BRANCH_CODE | D18: =IFERROR(VLOOKUP(C18,'字段信息'!A:C,2,),"") | F18: =B18 | G18: √ | M18: 直接对应 | N18: TA | O18: AW_MR9_ARPM01_000001 | P18: CUST_BRANCH_CODE
B19: =IFERROR(VLOOKUP(C19,'字段信息'!A:C,3,),"") | C19: CUST_BRANCH_NAME | D19: =IFERROR(VLOOKUP(C19,'字段信息'!A:C,2,),"") | F19: =B19 | G19: √ | L19: 普通级 | M19: 直接对应 | N19: TA | O19: AW_MR9_ARPM01_000001 | P19: CUST_BRANCH_NAME
B20: =IFERROR(VLOOKUP(C20,'字段信息'!A:C,3,),"") | C20: COD_AZI_CTP | D20: =IFERROR(VLOOKUP(C20,'字段信息'!A:C,2,),"") | F20: =B20 | G20: √ | M20: 直接对应 | N20: TA | O20: AW_MR9_ARPM01_000001 | P20: COD_AZI_CTP
B21: =IFERROR(VLOOKUP(C21,'字段信息'!A:C,3,),"") | C21: COUNTRY_CODE | D21: =IFERROR(VLOOKUP(C21,'字段信息'!A:C,2,),"") | F21: =B21 | G21: √ | M21: 直接对应 | N21: TA | O21: AW_MR9_ARPM01_000001 | P21: COUNTRY_CODE
B22: =IFERROR(VLOOKUP(C22,'字段信息'!A:C,3,),"") | C22: COUNTRY_NAME | D22: =IFERROR(VLOOKUP(C22,'字段信息'!A:C,2,),"") | F22: =B22 | G22: √ | M22: 直接对应 | N22: TA | O22: AW_MR9_ARPM01_000001 | P22: COUNTRY_NAME
B23: =IFERROR(VLOOKUP(C23,'字段信息'!A:C,3,),"") | C23: ACCT_SRC_CODE | D23: =IFERROR(VLOOKUP(C23,'字段信息'!A:C,2,),"") | F23: =B23 | G23: √ | M23: 直接对应 | N23: TA | O23: AW_MR9_ARPM01_000001 | P23: ACCT_SRC_CODE
B24: =IFERROR(VLOOKUP(C24,'字段信息'!A:C,3,),"") | C24: LE_AGE_FLAG | D24: =IFERROR(VLOOKUP(C24,'字段信息'!A:C,2,),"") | F24: =B24 | G24: √ | L24: 普通级 | M24: 直接对应 | N24: TA | O24: AW_MR9_ARPM01_000001 | P24: LE_AGE_FLG
B25: =IFERROR(VLOOKUP(C25,'字段信息'!A:C,3,),"") | C25: IS_REC_LG | D25: =IFERROR(VLOOKUP(C25,'字段信息'!A:C,2,),"") | F25: =B25 | G25: √ | M25: 直接对应 | N25: TA | O25: AW_MR9_ARPM01_000001 | P25: IS_REC_LG
B26: =IFERROR(VLOOKUP(C26,'字段信息'!A:C,3,),"") | C26: ME_AGE_FLAG | D26: =IFERROR(VLOOKUP(C26,'字段信息'!A:C,2,),"") | F26: =B26 | G26: √ | L26: 普通级 | M26: 直接对应 | N26: TA | O26: AW_MR9_ARPM01_000001 | P26: ME_AGE_FLG
B27: =IFERROR(VLOOKUP(C27,'字段信息'!A:C,3,),"") | C27: IS_REC_ME | D27: =IFERROR(VLOOKUP(C27,'字段信息'!A:C,2,),"") | F27: =B27 | G27: √ | M27: 直接对应 | N27: TA | O27: AW_MR9_ARPM01_000001 | P27: IS_REC_ME
B28: =IFERROR(VLOOKUP(C28,'字段信息'!A:C,3,),"") | C28: MB_AGE_FLAG | D28: =IFERROR(VLOOKUP(C28,'字段信息'!A:C,2,),"") | F28: =B28 | G28: √ | L28: 普通级 | M28: 直接对应 | N28: TA | O28: AW_MR9_ARPM01_000001 | P28: MB_AGE_FLG
B29: =IFERROR(VLOOKUP(C29,'字段信息'!A:C,3,),"") | C29: IS_REC_MB | D29: =IFERROR(VLOOKUP(C29,'字段信息'!A:C,2,),"") | F29: =B29 | G29: √ | M29: 直接对应 | N29: TA | O29: AW_MR9_ARPM01_000001 | P29: IS_REC_MB
B30: =IFERROR(VLOOKUP(C30,'字段信息'!A:C,3,),"") | C30: GRP_SCOPE | D30: =IFERROR(VLOOKUP(C30,'字段信息'!A:C,2,),"") | F30: =B30 | G30: √ | L30: 普通级 | M30: 直接对应 | N30: TA | O30: AW_MR9_ARPM01_000001 | P30: GRP_SCOPE
B31: =IFERROR(VLOOKUP(C31,'字段信息'!A:C,3,),"") | C31: NATURE_L1_NAME | D31: varchar(2000) | F31: =B31 | G31: √ | M31: 直接对应 | N31: TA | O31: AW_MR9_ARPM01_000001 | P31: NATURE_L1_NAME
B32: =IFERROR(VLOOKUP(C32,'字段信息'!A:C,3,),"") | C32: NATURE_L2_NAME | D32: varchar(2000) | F32: =B32 | G32: √ | M32: 直接对应 | N32: TA | O32: AW_MR9_ARPM01_000001 | P32: NATURE_L2_NAME
B33: =IFERROR(VLOOKUP(C33,'字段信息'!A:C,3,),"") | C33: NATURE_L3_NAME | D33: varchar(2000) | F33: =B33 | G33: √ | M33: 直接对应 | N33: TA | O33: AW_MR9_ARPM01_000001 | P33: NATURE_L3_NAME
B34: =IFERROR(VLOOKUP(C34,'字段信息'!A:C,3,),"") | C34: D_CHANNEL | D34: =IFERROR(VLOOKUP(C34,'字段信息'!A:C,2,),"") | F34: =B34 | G34: √ | L34: 普通级 | M34: 直接对应 | N34: TA | O34: AW_MR9_ARPM01_000001 | P34: D_CHANNEL
B35: =IFERROR(VLOOKUP(C35,'字段信息'!A:C,3,),"") | C35: D_ONOFFLINE | D35: =IFERROR(VLOOKUP(C35,'字段信息'!A:C,2,),"") | F35: =B35 | G35: √ | M35: 直接对应 | N35: TA | O35: AW_MR9_ARPM01_000001 | P35: D_ONOFFLINE
B36: =IFERROR(VLOOKUP(C36,'字段信息'!A:C,3,),"") | C36: COD_DEST2 | D36: =IFERROR(VLOOKUP(C36,'字段信息'!A:C,2,),"") | F36: =B36 | G36: √ | L36: 普通级 | M36: 直接对应 | N36: TA | O36: AW_MR9_ARPM01_000001 | P36: COD_DEST2
B37: =IFERROR(VLOOKUP(C37,'字段信息'!A:C,3,),"") | C37: COD_DEST3 | D37: =IFERROR(VLOOKUP(C37,'字段信息'!A:C,2,),"") | F37: =B37 | G37: √ | L37: 普通级 | M37: 直接对应 | N37: TA | O37: AW_MR9_ARPM01_000001 | P37: COD_DEST3
B38: =IFERROR(VLOOKUP(C38,'字段信息'!A:C,3,),"") | C38: D_SALE_DEPT | D38: =IFERROR(VLOOKUP(C37,'字段信息'!A:C,2,),"") | F38: =B38 | G38: √ | L38: 普通级 | M38: 直接对应 | N38: TA | O38: AW_MR9_ARPM01_000001 | P38: D_SALE_DEPT
B39: =IFERROR(VLOOKUP(C39,'字段信息'!A:C,3,),"") | C39: TAX_RATE | D39: =IFERROR(VLOOKUP(C38,'字段信息'!A:C,2,),"") | F39: =B39 | G39: √ | M39: 直接对应 | N39: TA | O39: AW_MR9_ARPM01_000001 | P39: TAX_RATE
B40: =IFERROR(VLOOKUP(C40,'字段信息'!A:C,3,),"") | C40: COD_VALUTA | D40: =IFERROR(VLOOKUP(C38,'字段信息'!A:C,2,),"") | F40: =B40 | G40: √ | L40: 普通级 | M40: 直接对应 | N40: TA | O40: AW_MR9_ARPM01_000001 | P40: COD_VALUTA
B41: =IFERROR(VLOOKUP(C41,'字段信息'!A:C,3,),"") | C41: COD_VALUTA_ORIGINARIA | D41: =IFERROR(VLOOKUP(C41,'字段信息'!A:C,2,),"") | F41: =B41 | G41: √ | L41: 普通级 | M41: 直接对应 | N41: TA | O41: AW_MR9_ARPM01_000001 | P41: COD_VALUTA_ORIGINARIA
B42: =IFERROR(VLOOKUP(C42,'字段信息'!A:C,3,),"") | C42: BY_BCY_0_AMT | D42: =IFERROR(VLOOKUP(C42,'字段信息'!A:C,2,),"") | F42: =B42 | G42: √ | M42: AW_MR9_ARPM02_000001年初的场景期间，根据公司+科目+客商+利润中心匹配取BCY_0_AMT，全量匹配，如果本月没有，年初有，则其他字段取年初的信息
B43: =IFERROR(VLOOKUP(C43,'字段信息'!A:C,3,),"") | C43: LM_BCY_0_AMT | D43: =IFERROR(VLOOKUP(C43,'字段信息'!A:C,2,),"") | F43: =B43 | G43: √ | M43: AW_MR9_ARPM02_000001上月的场景期间，根据公司+科目+客商+利润中心匹配取BCY_0_AMT，全量匹配，如果本月没有，上月有，则其他字段取上月的信息
B44: =IFERROR(VLOOKUP(C44,'字段信息'!A:C,3,),"") | C44: BCY_0_AMT | D44: =IFERROR(VLOOKUP(C44,'字段信息'!A:C,2,),"") | F44: =B44 | G44: √ | L44: 普通级 | M44: 判断le_age_flg为CL且IS_REC_LG为Y的，取SRC_DETAIL为ORG%的数据/（1+tax_rate） | N44: TA | O44: AW_MR9_ARPM01_000001 | P44: BCY_AMT0
B45: =IFERROR(VLOOKUP(C45,'字段信息'!A:C,3,),"") | C45: BCY_1_AMT | D45: =IFERROR(VLOOKUP(C45,'字段信息'!A:C,2,),"") | F45: =B45 | G45: √ | L45: 普通级 | M45: 同本月账龄处理逻辑 | N45: TA | O45: AW_MR9_ARPM01_000001 | P45: BCY_AMT1
B46: =IFERROR(VLOOKUP(C46,'字段信息'!A:C,3,),"") | C46: BCY_2_AMT | D46: =IFERROR(VLOOKUP(C46,'字段信息'!A:C,2,),"") | F46: =B46 | G46: √ | L46: 普通级 | M46: 同本月账龄处理逻辑 | N46: TA | O46: AW_MR9_ARPM01_000001 | P46: BCY_AMT2
B47: =IFERROR(VLOOKUP(C47,'字段信息'!A:C,3,),"") | C47: BCY_3_AMT | D47: =IFERROR(VLOOKUP(C47,'字段信息'!A:C,2,),"") | F47: =B47 | G47: √ | L47: 普通级 | M47: 同本月账龄处理逻辑 | N47: TA | O47: AW_MR9_ARPM01_000001 | P47: BCY_AMT3
B48: =IFERROR(VLOOKUP(C48,'字段信息'!A:C,3,),"") | C48: BCY_4_AMT | D48: =IFERROR(VLOOKUP(C48,'字段信息'!A:C,2,),"") | F48: =B48 | G48: √ | L48: 普通级 | M48: 同本月账龄处理逻辑 | N48: TA | O48: AW_MR9_ARPM01_000001 | P48: BCY_AMT4
B49: =IFERROR(VLOOKUP(C49,'字段信息'!A:C,3,),"") | C49: BCY_5_AMT | D49: =IFERROR(VLOOKUP(C49,'字段信息'!A:C,2,),"") | F49: =B49 | G49: √ | L49: 普通级 | M49: 同本月账龄处理逻辑 | N49: TA | O49: AW_MR9_ARPM01_000001 | P49: BCY_AMT5
B50: =IFERROR(VLOOKUP(C50,'字段信息'!A:C,3,),"") | C50: BCY_6_AMT | D50: =IFERROR(VLOOKUP(C50,'字段信息'!A:C,2,),"") | F50: =B50 | G50: √ | L50: 普通级 | M50: 同本月账龄处理逻辑 | N50: TA | O50: AW_MR9_ARPM01_000001 | P50: BCY_AMT6
B51: =IFERROR(VLOOKUP(C51,'字段信息'!A:C,3,),"") | C51: BCY_7_AMT | D51: =IFERROR(VLOOKUP(C51,'字段信息'!A:C,2,),"") | F51: =B51 | G51: √ | L51: 普通级 | M51: 同本月账龄处理逻辑 | N51: TA | O51: AW_MR9_ARPM01_000001 | P51: BCY_AMT7
B52: =IFERROR(VLOOKUP(C52,'字段信息'!A:C,3,),"") | C52: BCY_8_AMT | D52: =IFERROR(VLOOKUP(C52,'字段信息'!A:C,2,),"") | F52: =B52 | G52: √ | L52: 普通级 | M52: 同本月账龄处理逻辑 | N52: TA | O52: AW_MR9_ARPM01_000001 | P52: BCY_AMT8
B53: =IFERROR(VLOOKUP(C53,'字段信息'!A:C,3,),"") | C53: BCY_9_AMT | D53: =IFERROR(VLOOKUP(C53,'字段信息'!A:C,2,),"") | F53: =B53 | G53: √ | L53: 普通级 | M53: 同本月账龄处理逻辑 | N53: TA | O53: AW_MR9_ARPM01_000001 | P53: BCY_AMT9
B54: =IFERROR(VLOOKUP(C54,'字段信息'!A:C,3,),"") | C54: BCY_10_AMT | D54: =IFERROR(VLOOKUP(C54,'字段信息'!A:C,2,),"") | F54: =B54 | G54: √ | L54: 普通级 | M54: 同本月账龄处理逻辑 | N54: TA | O54: AW_MR9_ARPM01_000001 | P54: BCY_AMT10
B55: =IFERROR(VLOOKUP(C55,'字段信息'!A:C,3,),"") | C55: BCY_11_AMT | D55: =IFERROR(VLOOKUP(C55,'字段信息'!A:C,2,),"") | F55: =B55 | G55: √ | L55: 普通级 | M55: 同本月账龄处理逻辑 | N55: TA | O55: AW_MR9_ARPM01_000001 | P55: BCY_AMT11
... B70: =IFERROR(VLOOKUP(C70,'字段信息'!A:C,3,),"") | C70: QCY_10_AMT | D70: =IFERROR(VLOOKUP(C70,'字段信息'!A:C,2,),"") | F70: =B70 | G70: √ | L70: 普通级 | M70: 同本月账龄处理逻辑 | N70: TA | O70: AW_MR9_ARPM01_000001 | P70: QCY_AMT10
B71: =IFERROR(VLOOKUP(C71,'字段信息'!A:C,3,),"") | C71: QCY_11_AMT | D71: =IFERROR(VLOOKUP(C71,'字段信息'!A:C,2,),"") | F71: =B71 | G71: √ | M71: 同本月账龄处理逻辑 | N71: TA | O71: AW_MR9_ARPM01_000001 | P71: QCY_AMT11
B72: =IFERROR(VLOOKUP(C72,'字段信息'!A:C,3,),"") | C72: QCY_12_AMT | D72: =IFERROR(VLOOKUP(C72,'字段信息'!A:C,2,),"") | F72: =B72 | G72: √ | M72: 同本月账龄处理逻辑 | N72: TA | O72: AW_MR9_ARPM01_000001 | P72: QCY_AMT12
B73: =IFERROR(VLOOKUP(C73,'字段信息'!A:C,3,),"") | C73: QCY_13_AMT | D73: =IFERROR(VLOOKUP(C73,'字段信息'!A:C,2,),"") | F73: =B73 | G73: √ | M73: 同本月账龄处理逻辑 | N73: TA | O73: AW_MR9_ARPM01_000001 | P73: QCY_AMT13
B74: =IFERROR(VLOOKUP(C74,'字段信息'!A:C,3,),"") | C74: QCY_14_AMT | D74: =IFERROR(VLOOKUP(C74,'字段信息'!A:C,2,),"") | F74: =B74 | G74: √ | M74: 同本月账龄处理逻辑 | N74: TA | O74: AW_MR9_ARPM01_000001 | P74: QCY_AMT14
B75: =IFERROR(VLOOKUP(C75,'字段信息'!A:C,3,),"") | C75: QCY_15_AMT | D75: =IFERROR(VLOOKUP(C75,'字段信息'!A:C,2,),"") | F75: =B75 | G75: √ | M75: 同本月账龄处理逻辑 | N75: TA | O75: AW_MR9_ARPM01_000001 | P75: QCY_AMT15
B76: =IFERROR(VLOOKUP(C76,'字段信息'!A:C,3,),"") | C76: SHP_NINV_AMT | D76: =IFERROR(VLOOKUP(C76,'字段信息'!A:C,2,),"") | F76: =B76 | G76: √ | M76: 取SRC_DETAIL为ZSTO04_CK%的数据，根据科目+客户+利润中心匹配到同一行 | N76: TA | O76: AW_MR9_ARPM01_000001 | P76: BCY_AMT0
B77: =IFERROR(VLOOKUP(C77,'字段信息'!A:C,3,),"") | C77: RET_NTRF_AMT | D77: =IFERROR(VLOOKUP(C77,'字段信息'!A:C,2,),"") | F77: =B77 | G77: √ | M77: 取SRC_DETAIL为ZTSO04_TH%的数据，根据科目+客户+利润中心匹配到同一行 | N77: TA | O77: AW_MR9_ARPM01_000001 | P77: BCY_AMT0
B78: =IFERROR(VLOOKUP(C78,'字段信息'!A:C,3,),"") | C78: BCY_ADJ_INCL_0_AMT | D78: =IFERROR(VLOOKUP(C78,'字段信息'!A:C,2,),"") | F78: =B78 | G78: √ | M78: 判断le_age_flg为CL且IS_REC_LG为N的，取SRC_DETAIL为ORG%的数据*（1+tax_rate）+shp_ninv_amt-ret_ntrf_amt 其余取SRC_DETAIL为ORG%的数据+shp_ninv_amt-ret_ntrf_amt | N78: TA | O78: AW_MR9_ARPM01_000001 | P78: BCY_AMT0
B79: =IFERROR(VLOOKUP(C79,'字段信息'!A:C,3,),"") | C79: BCY_ADJ_INCL_1_AMT | D79: =IFERROR(VLOOKUP(C79,'字段信息'!A:C,2,),"") | F79: =B79 | G79: √ | M79: 同本月账龄处理逻辑 | N79: TA | O79: AW_MR9_ARPM01_000001 | P79: BCY_AMT1
B80: =IFERROR(VLOOKUP(C80,'字段信息'!A:C,3,),"") | C80: BCY_ADJ_INCL_2_AMT | D80: =IFERROR(VLOOKUP(C80,'字段信息'!A:C,2,),"") | F80: =B80 | G80: √ | M80: 同本月账龄处理逻辑 | N80: TA | O80: AW_MR9_ARPM01_000001 | P80: BCY_AMT2
B81: =IFERROR(VLOOKUP(C81,'字段信息'!A:C,3,),"") | C81: BCY_ADJ_INCL_3_AMT | D81: =IFERROR(VLOOKUP(C81,'字段信息'!A:C,2,),"") | F81: =B81 | G81: √ | M81: 同本月账龄处理逻辑 | N81: TA | O81: AW_MR9_ARPM01_000001 | P81: BCY_AMT3
B82: =IFERROR(VLOOKUP(C82,'字段信息'!A:C,3,),"") | C82: BCY_ADJ_INCL_4_AMT | D82: =IFERROR(VLOOKUP(C82,'字段信息'!A:C,2,),"") | F82: =B82 | G82: √ | M82: 同本月账龄处理逻辑 | N82: TA | O82: AW_MR9_ARPM01_000001 | P82: BCY_AMT4
... B94: =IFERROR(VLOOKUP(C94,'字段信息'!A:C,3,),"") | C94: BCY_ADJ_EXCL_0_AMT | D94: =IFERROR(VLOOKUP(C94,'字段信息'!A:C,2,),"") | F94: =B94 | G94: √ | M94: 判断me_age_flg为CL且IS_REC_ME为N的，取SRC_DETAIL为ORG%的数据+shp_ninv_amt-ret_ntrf_amt me_age_flg为CL且IS_REC_ME为Y的，SRC_DETAIL为ORG%的数据/（1+tax_rate）+shp_ninv_amt-ret_ntrf_amt | N94: TA | O94: AW_MR9_ARPM01_000001 | P94: BCY_AMT0
B95: =IFERROR(VLOOKUP(C95,'字段信息'!A:C,3,),"") | C95: overdue_0_amt | D95: number(27,9) | F95: =B95 | G95: √ | M95: 取SRC_DETAIL为overdue%的数据，根据科目+客户+利润中心匹配到同一行
B96: =IFERROR(VLOOKUP(C96,'字段信息'!A:C,3,),"") | C96: overdue_1_amt | D96: number(27,9) | F96: =B96 | G96: √ | M96: 取SRC_DETAIL为overdue%的数据，根据科目+客户+利润中心匹配到同一行 | N96: TA | O96: AW_MR9_ARPM01_000001 | P96: BCY_AMT0
B97: =IFERROR(VLOOKUP(C97,'字段信息'!A:C,3,),"") | C97: overdue_2_amt | D97: number(27,9) | F97: =B97 | G97: √ | M97: 置空 | N97: TA | O97: AW_MR9_ARPM01_000001 | P97: BCY_AMT0
B98: =IFERROR(VLOOKUP(C98,'字段信息'!A:C,3,),"") | C98: overdue_3_amt | D98: number(27,9) | F98: =B98 | G98: √ | M98: 置空
B99: =IFERROR(VLOOKUP(C99,'字段信息'!A:C,3,),"") | C99: overdue_4_amt | D99: number(27,9) | F99: =B99 | G99: √ | M99: 置空
B100: =IFERROR(VLOOKUP(C100,'字段信息'!A:C,3,),"") | C100: overdue_5_amt | D100: number(27,9) | F100: =B100 | G100: √ | M100: 置空
B101: =IFERROR(VLOOKUP(C101,'字段信息'!A:C,3,),"") | C101: overdue_6_amt | D101: number(27,9) | F101: =B101 | G101: √ | M101: 置空
B102: =IFERROR(VLOOKUP(C102,'字段信息'!A:C,3,),"") | C102: overdue_7_amt | D102: number(27,9) | F102: =B102 | G102: √ | M102: 置空
B103: =IFERROR(VLOOKUP(C103,'字段信息'!A:C,3,),"") | C103: overdue_8_amt | D103: number(27,9) | F103: =B103 | G103: √ | M103: 置空
B104: =IFERROR(VLOOKUP(C104,'字段信息'!A:C,3,),"") | C104: overdue_9_amt | D104: number(27,9) | F104: =B104 | G104: √ | M104: 置空
B105: =IFERROR(VLOOKUP(C105,'字段信息'!A:C,3,),"") | C105: INV_SAMPLE_AMT | D105: number(27,9) | F105: =B105 | G105: √ | M105: 取SRC_DETAIL为inv_sample%的数据，根据科目+客户+利润中心匹配到同一行 | N105: TA | O105: AW_MR9_ARPM01_000001 | P105: BCY_AMT0
B106: =IFERROR(VLOOKUP(C106,'字段信息'!A:C,3,),"") | C106: EPAY_AMT | D106: number(27,9) | F106: =B106 | G106: √ | M106: 取SRC_DETAIL为epay%的数据，根据科目+客户+利润中心匹配到同一行 | N106: TA | O106: AW_MR9_ARPM01_000001 | P106: BCY_AMT0
B107: =IFERROR(VLOOKUP(C107,'字段信息'!A:C,3,),"") | C107: ECLS_AMT | D107: number(27,9) | F107: =B107 | G107: √ | M107: 取SRC_DETAIL为ECLS%的数据，根据科目+客户+利润中心匹配到同一行 | N107: TA | O107: AW_MR9_ARPM01_000001 | P107: BCY_AMT0
B108: =IFERROR(VLOOKUP(C108,'字段信息'!A:C,3,),"") | C108: UREB_AMT | D108: number(27,9) | F108: =B108 | G108: √ | M108: 取SRC_DETAIL为ufee%的数据，根据科目+客户+利润中心匹配到同一行 | N108: TA | O108: AW_MR9_ARPM01_000001 | P108: BCY_AMT0
B109: =IFERROR(VLOOKUP(C109,'字段信息'!A:C,3,),"") | C109: UFEE_AMT | D109: number(27,9) | F109: =B109 | G109: √ | M109: 取SRC_DETAIL为ureb%的数据，根据科目+客户+利润中心匹配到同一行 | N109: TA | O109: AW_MR9_ARPM01_000001 | P109: BCY_AMT0
B110: =IFERROR(VLOOKUP(C110,'字段信息'!A:C,3,),"") | C110: PAY_TERM_CODE | D110: varchar(300) | F110: =B110 | G110: √ | M110: 直接对应 | N110: TA | O110: AW_MR9_ARPM01_000001 | P110: PAY_TERM_CODE
B111: =IFERROR(VLOOKUP(C111,'字段信息'!A:C,3,),"") | C111: PAY_TERM_DESC | D111: varchar(2000) | F111: =B111 | G111: √ | M111: 直接对应 | N111: TA | O111: AW_MR9_ARPM01_000001 | P111: PAY_TERM_DESC
B112: =IFERROR(VLOOKUP(C112,'字段信息'!A:C,3,),"") | C112: CLOSING_RATE_BCY_AMT | D112: number(27,9) | F112: =B112 | G112: √ | M112: 1、非2023公司： 交易币且本位币<>CNY， 根据交易币计算折算成本位币的汇率，汇率取系统的汇率表中的最终汇率；保留5位小数，用汇率*交易币金额 2、2023公司： 根据交易币计算折算成本位币的汇率，汇率取SAP-TCURR的汇率，用汇率*交易币金额 3、其他：根据交易币计算折算成本位币的汇率，汇率取系统的汇率表中的最终汇率；用汇率*交易币金额 | N112: Doris | O112: DATI_CAMBIO ODS.ODSS600_TCURR@FMSLK | P112: CAMBIO_FINALE UKURS*(CASE WHEN TCURR='VND' AND FCURR IN ('USD') THEN 1000 WHEN TCURR='VND' THEN 100 ELSE 1 END)
B113: =IFERROR(VLOOKUP(C113,'字段信息'!A:C,3,),"") | C113: POSTING_RATE_BCY_AMT | D113: number(27,9) | F113: =B113 | G113: √ | M113: 直接对应 | N113: TA | O113: AW_MR9_ARPM01_000001 | P113: BCY_0_AMT
B114: =IFERROR(VLOOKUP(C114,'字段信息'!A:C,3,),"") | C114: EXCHANGE_RATE_EVAL_FLAG | D114: =IFERROR(VLOOKUP(C114,'字段信息'!A:C,2,),"") | F114: =B114 | G114: √ | M114: 直接对应 | N114: TA | O114: AW_MR9_ARPM01_000001 | P114: EXCHANGE_RATE_EVAL_FLAG
B115: =IFERROR(VLOOKUP(C115,'字段信息'!A:C,3,),"") | C115: TH_FX_EVAL_AMT | D115: =IFERROR(VLOOKUP(C115,'字段信息'!A:C,2,),"") | F115: =B115 | G115: √ | M115: BCY_AMT0 - posting_rate_bcy_amt
B116: =IFERROR(VLOOKUP(C116,'字段信息'!A:C,3,),"") | C116: CURRENCY_ACCT_DETAIL | D116: =IFERROR(VLOOKUP(C116,'字段信息'!A:C,2,),"") | F116: =B116 | G116: √ | M116: 格式为：【法人分类标识:本币余额\原币:原币余额;】 | N116: TA | O116: AW_MR9_ARPM01_000001 | P116: LISTAGG(LE_AGE_FLG || ':' || BCY_0_AMT|| '\' || COD_VALUTA_ORIGINARIA || ':' || QCY_0_AMT, ';') WITHIN GROUP (ORDER BY LE_AGE_FLG, BCY_0_AMT)
B117: =IFERROR(VLOOKUP(C117,'字段信息'!A:C,3,),"") | C117: ADJ_REB_AMT | D117: =IFERROR(VLOOKUP(C117,'字段信息'!A:C,2,),"") | F117: =B117 | G117: √ | M117: UREB_AMT - MIN(BCY_AMT0/UREB_AMT)
B118: =IFERROR(VLOOKUP(C118,'字段信息'!A:C,3,),"") | C118: ADJ_RET_AMT | D118: =IFERROR(VLOOKUP(C118,'字段信息'!A:C,2,),"") | F118: =B118 | G118: √ | M118: MIN(BCY_AMT0/ret_ntrf_amt)

Sheet ARPM02-坏账计算表-STEP1坏账计提基数
A1: 返回 | B1: AW_MR9_ARPM03_000001逻辑处理
A2: 规则库 | B2: 表名称 | C2: AW_MR9_ARPM03_000001 | M2: 存储过程名称：CPM_SP_M2M_ARP_BD_M
B3: 表描述 | C3: 坏账计算表 | D3: 表类型 | E3: 事实表 | F3: 数仓分层 | G3: DWM | M3: 参数：场景 P_SCENARIO
B4: L1数仓目录 | C4: 管理财经 | D4: L2数仓目录 | E4: 财报管理 | F4: L3数仓目录 | G4: 应收 | M4: 期间：P_PERIODO
B5: 更新方式 | C5: 增量更新 | D5: 设计人员 | F5: 时间 | M5: 公司：P_AZIENDA
B6: 使用场景 | C6: 将往来账龄表中涉及到需要计算坏账的数据取到坏账计算表中，根据管理分类和分公司分类不同生成两个口径的数据，并且匹配出坏账的调整项，如果有直销垫资的金额，用垫资的金额冲减坏账计提基数，优先从长账龄冲销，如果同一个客户存在负数的账龄金额，拆分到长账龄的区间中 | M6: 用户：SESSION_USER
B7: 目标表 | M7: 往来账龄结果【AW_MR9_ARPM02_000001】
B8: 字段中文名称 | C8: *字段名称 | D8: *类型 | E8: 主键 | F8: *描述 | G8: 允许为空 | H8: 默认值 | I8: 聚合类型 | J8: 基础标准 | K8: 标准代码 | L8: *安全分级 | M8: 转换清洗规则 | N8: 源系统 | O8: 源头表 | P8: 源头字段 | Q8: 匹配字段 | R8: 匹配过滤 | S8: 数仓处理脚本 | T8: 备注
B9: =IFERROR(VLOOKUP(C9,'字段信息'!A:C,3,),"") | C9: COD_SCENARIO | D9: =IFERROR(VLOOKUP(C9,'字段信息'!A:C,2,),"") | F9: =B9 | M9: 直接对应 | N9: TA | O9: AW_MR9_ARPM02_000001 | P9: COD_SCENARIO
B10: =IFERROR(VLOOKUP(C10,'字段信息'!A:C,3,),"") | C10: COD_PERIODO | D10: =IFERROR(VLOOKUP(C10,'字段信息'!A:C,2,),"") | F10: =B10 | G10: √ | L10: 普通级 | M10: 直接对应 | N10: TA | O10: AW_MR9_ARPM02_000001 | P10: COD_PERIODO
B11: =IFERROR(VLOOKUP(C11,'字段信息'!A:C,3,),"") | C11: COD_AZIENDA | D11: =IFERROR(VLOOKUP(C11,'字段信息'!A:C,2,),"") | F11: =B11 | G11: √ | L11: 普通级 | M11: 直接对应 | N11: TA | O11: AW_MR9_ARPM02_000001 | P11: COD_AZIENDA
B12: =IFERROR(VLOOKUP(C12,'字段信息'!A:C,3,),"") | C12: COD_CONTO | D12: =IFERROR(VLOOKUP(C12,'字段信息'!A:C,2,),"") | F12: =B12 | G12: √ | L12: 普通级 | M12: 直接对应 | N12: TA | O12: AW_MR9_ARPM02_000001 | P12: COD_CONTO
B13: =IFERROR(VLOOKUP(C13,'字段信息'!A:C,3,),"") | C13: COD_CATEGORIA | D13: =IFERROR(VLOOKUP(C13,'字段信息'!A:C,2,),"") | F13: =B13 | G13: √ | L13: 普通级 | M13: 根据me_age_flg取AR/OR/CA/A10的数据，类别放ZAMOUNT 根据mb_age_flg取AR/OR/CA/A10的数据，类别放ZAMOUNT_L2 | N13: TA | O13: AW_MR9_ARPM02_000001
B14: =IFERROR(VLOOKUP(C14,'字段信息'!A:C,3,),"") | C14: CUST_CODE | D14: =IFERROR(VLOOKUP(C14,'字段信息'!A:C,2,),"") | F14: =B14 | G14: √ | L14: 普通级 | M14: 直接对应 | N14: TA | O14: AW_MR9_ARPM02_000001 | P14: CUST_CODE
B15: =IFERROR(VLOOKUP(C15,'字段信息'!A:C,3,),"") | C15: CUST_NAME | D15: =IFERROR(VLOOKUP(C15,'字段信息'!A:C,2,),"") | F15: =B15 | G15: √ | L15: 普通级 | M15: 直接对应 | N15: TA | O15: AW_MR9_ARPM02_000001 | P15: CUST_NAME
B16: =IFERROR(VLOOKUP(C16,'字段信息'!A:C,3,),"") | C16: CUST_HEAD_CODE | D16: =IFERROR(VLOOKUP(C16,'字段信息'!A:C,2,),"") | F16: =B16 | G16: √ | L16: 普通级 | M16: 直接对应 | N16: TA | O16: AW_MR9_ARPM02_000001 | P16: CUST_HEAD_CODE
B17: =IFERROR(VLOOKUP(C17,'字段信息'!A:C,3,),"") | C17: CUST_HEAD_NAME | D17: =IFERROR(VLOOKUP(C17,'字段信息'!A:C,2,),"") | F17: =B17 | G17: √ | M17: 直接对应 | N17: TA | O17: AW_MR9_ARPM02_000001 | P17: CUST_HEAD_NAME
B18: =IFERROR(VLOOKUP(C18,'字段信息'!A:C,3,),"") | C18: CUST_BRANCH_CODE | D18: =IFERROR(VLOOKUP(C18,'字段信息'!A:C,2,),"") | F18: =B18 | G18: √ | M18: 直接对应 | N18: TA | O18: AW_MR9_ARPM02_000001 | P18: CUST_BRANCH_CODE
B19: =IFERROR(VLOOKUP(C19,'字段信息'!A:C,3,),"") | C19: CUST_BRANCH_NAME | D19: =IFERROR(VLOOKUP(C19,'字段信息'!A:C,2,),"") | F19: =B19 | G19: √ | L19: 普通级 | M19: 直接对应 | N19: TA | O19: AW_MR9_ARPM02_000001 | P19: CUST_BRANCH_NAME
B20: =IFERROR(VLOOKUP(C20,'字段信息'!A:C,3,),"") | C20: COD_AZI_CTP | D20: =IFERROR(VLOOKUP(C20,'字段信息'!A:C,2,),"") | F20: =B20 | G20: √ | M20: 直接对应 | N20: TA | O20: AW_MR9_ARPM02_000001 | P20: COD_AZI_CTP
B21: =IFERROR(VLOOKUP(C21,'字段信息'!A:C,3,),"") | C21: COUNTRY_CODE | D21: =IFERROR(VLOOKUP(C21,'字段信息'!A:C,2,),"") | F21: =B21 | G21: √ | M21: 直接对应 | N21: TA | O21: AW_MR9_ARPM02_000001 | P21: COUNTRY_CODE
B22: =IFERROR(VLOOKUP(C22,'字段信息'!A:C,3,),"") | C22: COUNTRY_NAME | D22: =IFERROR(VLOOKUP(C22,'字段信息'!A:C,2,),"") | F22: =B22 | G22: √ | M22: 直接对应 | N22: TA | O22: AW_MR9_ARPM02_000001 | P22: COUNTRY_NAME
B23: =IFERROR(VLOOKUP(C23,'字段信息'!A:C,3,),"") | C23: GRP_SCOPE | D23: =IFERROR(VLOOKUP(C23,'字段信息'!A:C,2,),"") | F23: =B23 | G23: √ | L23: 普通级 | M23: 直接对应 | N23: TA | O23: AW_MR9_ARPM02_000001 | P23: GRP_SCOPE
B24: =IFERROR(VLOOKUP(C24,'字段信息'!A:C,3,),"") | C24: NATURE_L1_NAME | D24: varchar(2000) | F24: =B24 | G24: √ | M24: 直接对应 | N24: TA | O24: AW_MR9_ARPM02_000001 | P24: NATURE_L1_NAME
B25: =IFERROR(VLOOKUP(C25,'字段信息'!A:C,3,),"") | C25: NATURE_L2_NAME | D25: varchar(2000) | F25: =B25 | G25: √ | M25: 直接对应 | N25: TA | O25: AW_MR9_ARPM02_000001 | P25: NATURE_L2_NAME
B26: =IFERROR(VLOOKUP(C26,'字段信息'!A:C,3,),"") | C26: NATURE_L3_NAME | D26: varchar(2000) | F26: =B26 | G26: √ | M26: 直接对应 | N26: TA | O26: AW_MR9_ARPM02_000001 | P26: NATURE_L3_NAME
B27: =IFERROR(VLOOKUP(C27,'字段信息'!A:C,3,),"") | C27: D_CHANNEL | D27: =IFERROR(VLOOKUP(C27,'字段信息'!A:C,2,),"") | F27: =B27 | G27: √ | L27: 普通级 | M27: 直接对应 | N27: TA | O27: AW_MR9_ARPM02_000001 | P27: D_CHANNEL
B28: =IFERROR(VLOOKUP(C28,'字段信息'!A:C,3,),"") | C28: D_ONOFFLINE | D28: =IFERROR(VLOOKUP(C28,'字段信息'!A:C,2,),"") | F28: =B28 | G28: √ | M28: 直接对应 | N28: TA | O28: AW_MR9_ARPM02_000001 | P28: D_ONOFFLINE
B29: =IFERROR(VLOOKUP(C29,'字段信息'!A:C,3,),"") | C29: COD_DEST2 | D29: =IFERROR(VLOOKUP(C29,'字段信息'!A:C,2,),"") | F29: =B29 | G29: √ | L29: 普通级 | M29: 直接对应 | N29: TA | O29: AW_MR9_ARPM02_000001 | P29: COD_DEST2
B30: =IFERROR(VLOOKUP(C30,'字段信息'!A:C,3,),"") | C30: COD_DEST3 | D30: =IFERROR(VLOOKUP(C30,'字段信息'!A:C,2,),"") | F30: =B30 | G30: √ | L30: 普通级 | M30: 直接对应 | N30: TA | O30: AW_MR9_ARPM02_000001 | P30: COD_DEST3
B31: =IFERROR(VLOOKUP(C31,'字段信息'!A:C,3,),"") | C31: D_SALE_DEPT | D31: =IFERROR(VLOOKUP(C30,'字段信息'!A:C,2,),"") | F31: =B31 | G31: √ | L31: 普通级 | M31: 直接对应 | N31: TA | O31: AW_MR9_ARPM02_000001 | P31: D_SALE_DEPT
B32: =IFERROR(VLOOKUP(C32,'字段信息'!A:C,3,),"") | C32: COD_VALUTA | D32: =IFERROR(VLOOKUP(C31,'字段信息'!A:C,2,),"") | F32: =B32 | G32: √ | L32: 普通级 | M32: 直接对应 | N32: TA | O32: AW_MR9_ARPM02_000001 | P32: COD_VALUTA
B33: =IFERROR(VLOOKUP(C33,'字段信息'!A:C,3,),"") | C33: COD_VALUTA_ORIGINARIA | D33: =IFERROR(VLOOKUP(C33,'字段信息'!A:C,2,),"") | F33: =B33 | G33: √ | L33: 普通级 | M33: 直接对应 | N33: TA | O33: AW_MR9_ARPM02_000001 | P33: COD_VALUTA_ORIGINARIA
B34: =IFERROR(VLOOKUP(C34,'字段信息'!A:C,3,),"") | C34: BCY_ADJ_INCL_0_AMT | D34: =IFERROR(VLOOKUP(C34,'字段信息'!A:C,2,),"") | F34: =B34 | G34: √ | M34: 直接对应 | N34: TA | O34: AW_MR9_ARPM02_000001 | P34: BCY_ADJ_INCL_0_AMT
B35: =IFERROR(VLOOKUP(C35,'字段信息'!A:C,3,),"") | C35: BCY_ADJ_INCL_1_AMT | D35: =IFERROR(VLOOKUP(C35,'字段信息'!A:C,2,),"") | F35: =B35 | G35: √ | M35: 直接对应 | N35: TA | O35: AW_MR9_ARPM02_000001 | P35: BCY_ADJ_INCL_1_AMT
B36: =IFERROR(VLOOKUP(C36,'字段信息'!A:C,3,),"") | C36: BCY_ADJ_INCL_2_AMT | D36: =IFERROR(VLOOKUP(C36,'字段信息'!A:C,2,),"") | F36: =B36 | G36: √ | M36: 直接对应 | N36: TA | O36: AW_MR9_ARPM02_000001 | P36: BCY_ADJ_INCL_2_AMT
B37: =IFERROR(VLOOKUP(C37,'字段信息'!A:C,3,),"") | C37: BCY_ADJ_INCL_3_AMT | D37: =IFERROR(VLOOKUP(C37,'字段信息'!A:C,2,),"") | F37: =B37 | G37: √ | M37: 直接对应 | N37: TA | O37: AW_MR9_ARPM02_000001 | P37: BCY_ADJ_INCL_3_AMT
B38: =IFERROR(VLOOKUP(C38,'字段信息'!A:C,3,),"") | C38: BCY_ADJ_INCL_4_AMT | D38: =IFERROR(VLOOKUP(C38,'字段信息'!A:C,2,),"") | F38: =B38 | G38: √ | M38: 直接对应 | N38: TA | O38: AW_MR9_ARPM02_000001 | P38: BCY_ADJ_INCL_4_AMT
B39: =IFERROR(VLOOKUP(C39,'字段信息'!A:C,3,),"") | C39: BCY_ADJ_INCL_5_AMT | D39: =IFERROR(VLOOKUP(C39,'字段信息'!A:C,2,),"") | F39: =B39 | G39: √ | M39: 直接对应 | N39: TA | O39: AW_MR9_ARPM02_000001 | P39: BCY_ADJ_INCL_5_AMT
B40: =IFERROR(VLOOKUP(C40,'字段信息'!A:C,3,),"") | C40: BCY_ADJ_INCL_6_AMT | D40: =IFERROR(VLOOKUP(C40,'字段信息'!A:C,2,),"") | F40: =B40 | G40: √ | M40: 直接对应 | N40: TA | O40: AW_MR9_ARPM02_000001 | P40: BCY_ADJ_INCL_6_AMT
B41: =IFERROR(VLOOKUP(C41,'字段信息'!A:C,3,),"") | C41: BCY_ADJ_INCL_7_AMT | D41: =IFERROR(VLOOKUP(C41,'字段信息'!A:C,2,),"") | F41: =B41 | G41: √ | M41: 直接对应 | N41: TA | O41: AW_MR9_ARPM02_000001 | P41: BCY_ADJ_INCL_7_AMT
B42: =IFERROR(VLOOKUP(C42,'字段信息'!A:C,3,),"") | C42: BCY_ADJ_INCL_8_AMT | D42: =IFERROR(VLOOKUP(C42,'字段信息'!A:C,2,),"") | F42: =B42 | G42: √ | M42: 直接对应 | N42: TA | O42: AW_MR9_ARPM02_000001 | P42: BCY_ADJ_INCL_8_AMT
B43: =IFERROR(VLOOKUP(C43,'字段信息'!A:C,3,),"") | C43: BCY_ADJ_INCL_9_AMT | D43: =IFERROR(VLOOKUP(C43,'字段信息'!A:C,2,),"") | F43: =B43 | G43: √ | M43: 直接对应 | N43: TA | O43: AW_MR9_ARPM02_000001 | P43: BCY_ADJ_INCL_9_AMT
B44: =IFERROR(VLOOKUP(C44,'字段信息'!A:C,3,),"") | C44: BCY_ADJ_INCL_10_AMT | D44: =IFERROR(VLOOKUP(C44,'字段信息'!A:C,2,),"") | F44: =B44 | G44: √ | M44: 直接对应 | N44: TA | O44: AW_MR9_ARPM02_000001 | P44: BCY_ADJ_INCL_10_AMT
B45: =IFERROR(VLOOKUP(C45,'字段信息'!A:C,3,),"") | C45: BCY_ADJ_INCL_11_AMT | D45: =IFERROR(VLOOKUP(C45,'字段信息'!A:C,2,),"") | F45: =B45 | G45: √ | M45: 直接对应 | N45: TA | O45: AW_MR9_ARPM02_000001 | P45: BCY_ADJ_INCL_11_AMT
... B54: =IFERROR(VLOOKUP(C54,'字段信息'!A:C,3,),"") | C54: INS_UNCOV_RATE | D54: =IFERROR(VLOOKUP(C54,'字段信息'!A:C,2,),"") | F54: =B54 | G54: √ | M54: 根据公司+科目+客商编码匹配《投保信息表》，取未覆盖比例WFUGBL | N54: TA | O54: ZTAB_AG_TF_INSURE | P54: WFUGBL
B55: =IFERROR(VLOOKUP(C55,'字段信息'!A:C,3,),"") | C55: BD_BASE_0_AMT | D55: =IFERROR(VLOOKUP(C55,'字段信息'!A:C,2,),"") | F55: =B55 | G55: √ | M55: 合计各账龄段数据之和
B56: =IFERROR(VLOOKUP(C56,'字段信息'!A:C,3,),"") | C56: BD_BASE_1_AMT | D56: =IFERROR(VLOOKUP(C56,'字段信息'!A:C,2,),"") | F56: =B56 | G56: √ | M56: 1、垫资金额spc_dsv_ded_amt如果有值，先从长账龄段冲减BCY_ADJ_INCL_1_AMT原始账龄段的数据 2、如果存在负数的账龄段，根据同一个公司+客户下长账龄的数据开始拆分（先进先出的原理） | N56: TA | O56: AW_MR9_ARPM02_000001 | P56: BCY_ADJ_INCL_1_AMT
B57: =IFERROR(VLOOKUP(C57,'字段信息'!A:C,3,),"") | C57: BD_BASE_2_AMT | D57: =IFERROR(VLOOKUP(C57,'字段信息'!A:C,2,),"") | F57: =B57 | G57: √ | M57: 1、垫资金额spc_dsv_ded_amt如果有值，先从长账龄段冲减BCY_ADJ_INCL_2_AMT原始账龄段的数据 2、如果存在负数的账龄段，根据同一个公司+客户下长账龄的数据开始拆分（先进先出的原理） | N57: TA | O57: AW_MR9_ARPM02_000001 | P57: BCY_ADJ_INCL_2_AMT
B58: =IFERROR(VLOOKUP(C58,'字段信息'!A:C,3,),"") | C58: BD_BASE_3_AMT | D58: =IFERROR(VLOOKUP(C58,'字段信息'!A:C,2,),"") | F58: =B58 | G58: √ | M58: 1、垫资金额spc_dsv_ded_amt如果有值，先从长账龄段冲减BCY_ADJ_INCL_3_AMT原始账龄段的数据 2、如果存在负数的账龄段，根据同一个公司+客户下长账龄的数据开始拆分（先进先出的原理） | N58: TA | O58: AW_MR9_ARPM02_000001 | P58: BCY_ADJ_INCL_3_AMT
B59: =IFERROR(VLOOKUP(C59,'字段信息'!A:C,3,),"") | C59: BD_BASE_4_AMT | D59: =IFERROR(VLOOKUP(C59,'字段信息'!A:C,2,),"") | F59: =B59 | G59: √ | M59: 1、垫资金额spc_dsv_ded_amt如果有值，先从长账龄段冲减BCY_ADJ_INCL_4_AMT原始账龄段的数据 2、如果存在负数的账龄段，根据同一个公司+客户下长账龄的数据开始拆分（先进先出的原理） | N59: TA | O59: AW_MR9_ARPM02_000001 | P59: BCY_ADJ_INCL_4_AMT
B60: =IFERROR(VLOOKUP(C60,'字段信息'!A:C,3,),"") | C60: BD_BASE_5_AMT | D60: =IFERROR(VLOOKUP(C60,'字段信息'!A:C,2,),"") | F60: =B60 | G60: √ | M60: 1、垫资金额spc_dsv_ded_amt如果有值，先从长账龄段冲减BCY_ADJ_INCL_5_AMT原始账龄段的数据 2、如果存在负数的账龄段，根据同一个公司+客户下长账龄的数据开始拆分（先进先出的原理） | N60: TA | O60: AW_MR9_ARPM02_000001 | P60: BCY_ADJ_INCL_5_AMT
B61: =IFERROR(VLOOKUP(C61,'字段信息'!A:C,3,),"") | C61: BD_BASE_6_AMT | D61: =IFERROR(VLOOKUP(C61,'字段信息'!A:C,2,),"") | F61: =B61 | G61: √ | M61: 1、垫资金额spc_dsv_ded_amt如果有值，先从长账龄段冲减BCY_ADJ_INCL_6_AMT原始账龄段的数据 2、如果存在负数的账龄段，根据同一个公司+客户下长账龄的数据开始拆分（先进先出的原理） | N61: TA | O61: AW_MR9_ARPM02_000001 | P61: BCY_ADJ_INCL_6_AMT
B62: =IFERROR(VLOOKUP(C62,'字段信息'!A:C,3,),"") | C62: BD_BASE_7_AMT | D62: =IFERROR(VLOOKUP(C62,'字段信息'!A:C,2,),"") | F62: =B62 | G62: √ | M62: 1、垫资金额spc_dsv_ded_amt如果有值，先从长账龄段冲减BCY_ADJ_INCL_7_AMT原始账龄段的数据 2、如果存在负数的账龄段，根据同一个公司+客户下长账龄的数据开始拆分（先进先出的原理） | N62: TA | O62: AW_MR9_ARPM02_000001 | P62: BCY_ADJ_INCL_7_AMT
B63: =IFERROR(VLOOKUP(C63,'字段信息'!A:C,3,),"") | C63: BD_BASE_8_AMT | D63: =IFERROR(VLOOKUP(C63,'字段信息'!A:C,2,),"") | F63: =B63 | G63: √ | M63: 1、垫资金额spc_dsv_ded_amt如果有值，先从长账龄段冲减BCY_ADJ_INCL_8_AMT原始账龄段的数据 2、如果存在负数的账龄段，根据同一个公司+客户下长账龄的数据开始拆分（先进先出的原理） | N63: TA | O63: AW_MR9_ARPM02_000001 | P63: BCY_ADJ_INCL_8_AMT
B64: =IFERROR(VLOOKUP(C64,'字段信息'!A:C,3,),"") | C64: BD_BASE_9_AMT | D64: =IFERROR(VLOOKUP(C64,'字段信息'!A:C,2,),"") | F64: =B64 | G64: √ | M64: 1、垫资金额spc_dsv_ded_amt如果有值，先从长账龄段冲减BCY_ADJ_INCL_9_AMT原始账龄段的数据 2、如果存在负数的账龄段，根据同一个公司+客户下长账龄的数据开始拆分（先进先出的原理） | N64: TA | O64: AW_MR9_ARPM02_000001 | P64: BCY_ADJ_INCL_9_AMT
B65: =IFERROR(VLOOKUP(C65,'字段信息'!A:C,3,),"") | C65: BD_BASE_10_AMT | D65: =IFERROR(VLOOKUP(C65,'字段信息'!A:C,2,),"") | F65: =B65 | G65: √ | M65: 1、垫资金额spc_dsv_ded_amt如果有值，先从长账龄段冲减BCY_ADJ_INCL_10_AMT原始账龄段的数据 2、如果存在负数的账龄段，根据同一个公司+客户下长账龄的数据开始拆分（先进先出的原理） | N65: TA | O65: AW_MR9_ARPM02_000001 | P65: BCY_ADJ_INCL_10_AMT
B66: =IFERROR(VLOOKUP(C66,'字段信息'!A:C,3,),"") | C66: BD_BASE_11_AMT | D66: =IFERROR(VLOOKUP(C66,'字段信息'!A:C,2,),"") | F66: =B66 | G66: √ | M66: 1、垫资金额spc_dsv_ded_amt如果有值，先从长账龄段冲减BCY_ADJ_INCL_11_AMT原始账龄段的数据 2、如果存在负数的账龄段，根据同一个公司+客户下长账龄的数据开始拆分（先进先出的原理） | N66: TA | O66: AW_MR9_ARPM02_000001 | P66: BCY_ADJ_INCL_11_AMT
B67: =IFERROR(VLOOKUP(C67,'字段信息'!A:C,3,),"") | C67: BD_BASE_12_AMT | D67: =IFERROR(VLOOKUP(C67,'字段信息'!A:C,2,),"") | F67: =B67 | G67: √ | M67: 1、垫资金额spc_dsv_ded_amt如果有值，先从长账龄段冲减BCY_ADJ_INCL_12_AMT原始账龄段的数据 2、如果存在负数的账龄段，根据同一个公司+客户下长账龄的数据开始拆分（先进先出的原理） | N67: TA | O67: AW_MR9_ARPM02_000001 | P67: BCY_ADJ_INCL_12_AMT
... B70: =IFERROR(VLOOKUP(C70,'字段信息'!A:C,3,),"") | C70: BD_BASE_15_AMT | D70: =IFERROR(VLOOKUP(C70,'字段信息'!A:C,2,),"") | F70: =B70 | G70: √ | M70: 1、垫资金额spc_dsv_ded_amt如果有值，先从长账龄段冲减BCY_ADJ_INCL_15_AMT原始账龄段的数据 2、如果存在负数的账龄段，根据同一个公司+客户下长账龄的数据开始拆分（先进先出的原理） | N70: TA | O70: AW_MR9_ARPM02_000001 | P70: BCY_ADJ_INCL_15_AMT
B73: =IFERROR(VLOOKUP(C73,'字段信息'!A:C,3,),"") | C73: BD_0_AMT | D73: =IFERROR(VLOOKUP(C73,'字段信息'!A:C,2,),"") | F73: =B73 | G73: √
B74: =IFERROR(VLOOKUP(C74,'字段信息'!A:C,3,),"") | C74: BD_1_AMT | D74: =IFERROR(VLOOKUP(C74,'字段信息'!A:C,2,),"") | F74: =B74 | G74: √
B75: =IFERROR(VLOOKUP(C75,'字段信息'!A:C,3,),"") | C75: BD_2_AMT | D75: =IFERROR(VLOOKUP(C75,'字段信息'!A:C,2,),"") | F75: =B75 | G75: √
B76: =IFERROR(VLOOKUP(C76,'字段信息'!A:C,3,),"") | C76: BD_3_AMT | D76: =IFERROR(VLOOKUP(C76,'字段信息'!A:C,2,),"") | F76: =B76 | G76: √
B77: =IFERROR(VLOOKUP(C77,'字段信息'!A:C,3,),"") | C77: BD_4_AMT | D77: =IFERROR(VLOOKUP(C77,'字段信息'!A:C,2,),"") | F77: =B77 | G77: √
B78: =IFERROR(VLOOKUP(C78,'字段信息'!A:C,3,),"") | C78: BD_5_AMT | D78: =IFERROR(VLOOKUP(C78,'字段信息'!A:C,2,),"") | F78: =B78 | G78: √
B79: =IFERROR(VLOOKUP(C79,'字段信息'!A:C,3,),"") | C79: BD_6_AMT | D79: =IFERROR(VLOOKUP(C79,'字段信息'!A:C,2,),"") | F79: =B79 | G79: √
B80: =IFERROR(VLOOKUP(C80,'字段信息'!A:C,3,),"") | C80: BD_7_AMT | D80: =IFERROR(VLOOKUP(C80,'字段信息'!A:C,2,),"") | F80: =B80 | G80: √
B81: =IFERROR(VLOOKUP(C81,'字段信息'!A:C,3,),"") | C81: BD_8_AMT | D81: =IFERROR(VLOOKUP(C81,'字段信息'!A:C,2,),"") | F81: =B81 | G81: √
B82: =IFERROR(VLOOKUP(C82,'字段信息'!A:C,3,),"") | C82: BD_9_AMT | D82: =IFERROR(VLOOKUP(C82,'字段信息'!A:C,2,),"") | F82: =B82 | G82: √
B83: =IFERROR(VLOOKUP(C83,'字段信息'!A:C,3,),"") | C83: BD_10_AMT | D83: =IFERROR(VLOOKUP(C83,'字段信息'!A:C,2,),"") | F83: =B83 | G83: √
B84: =IFERROR(VLOOKUP(C84,'字段信息'!A:C,3,),"") | C84: BD_11_AMT | D84: =IFERROR(VLOOKUP(C84,'字段信息'!A:C,2,),"") | F84: =B84 | G84: √
... B121: =IFERROR(VLOOKUP(C121,'字段信息'!A:C,3,),"") | C121: BD_AFAL_15_AMT | D121: =IFERROR(VLOOKUP(C121,'字段信息'!A:C,2,),"") | F121: =B121 | G121: √

Sheet ARPM02-坏账计算表-STEP2坏账计算
A1: 返回 | B1: AW_MR9_ARPM03_000001逻辑处理
A2: 规则库 | B2: 表名称 | C2: AW_MR9_ARPM03_000001 | M2: 存储过程名称：CPM_SP_M2M_ARP_BD_M
B3: 表描述 | C3: 坏账计算表 | D3: 表类型 | E3: 事实表 | F3: 数仓分层 | G3: DWM | M3: 参数：场景 P_SCENARIO
B4: L1数仓目录 | C4: 管理财经 | D4: L2数仓目录 | E4: 财报管理 | F4: L3数仓目录 | G4: 应收 | M4: 期间：P_PERIODO
B5: 更新方式 | C5: 增量更新 | D5: 设计人员 | F5: 时间 | M5: 公司：P_AZIENDA
B6: 使用场景 | C6: 根据不同的坏账计提规则计算坏账金额，如果有个别认定和煤改电，优先取对应的金额计提坏账，再按照优先级匹配坏账计提比例，根据坏账计提比例*坏账计提基数计算坏账金额，如果保障天数>0，需要再根据保障天数判断坏账计提区间，根据坏账计提比例*坏账计提基数*未覆盖比例计算坏账 | M6: 用户：SESSION_USER
B7: 目标表 | M7: 坏账计提基数【AW_MR9_ARPM03_000001】
B8: 字段中文名称 | C8: *字段名称 | D8: *类型 | E8: 主键 | F8: *描述 | G8: 允许为空 | H8: 默认值 | I8: 聚合类型 | J8: 基础标准 | K8: 标准代码 | L8: *安全分级 | M8: 转换清洗规则 | N8: 源系统 | O8: 源头表 | P8: 源头字段 | Q8: 匹配字段 | R8: 匹配过滤 | S8: 数仓处理脚本 | T8: 备注
B9: =IFERROR(VLOOKUP(C9,'字段信息'!A:C,3,),"") | C9: SPID_0_AMT | D9: =IFERROR(VLOOKUP(C9,'字段信息'!A:C,2,),"") | F9: =B9 | G9: √ | M9: 根据公司+客户+利润中心+三级性质匹配AW_MR9_ARPM03_000001，限制类别为ZFAMOUNT，取spid_0_amt
B10: =IFERROR(VLOOKUP(C10,'字段信息'!A:C,3,),"") | C10: SPID_1_AMT | D10: =IFERROR(VLOOKUP(C10,'字段信息'!A:C,2,),"") | F10: =B10 | G10: √ | M10: 根据公司+客户+利润中心+三级性质匹配AW_MR9_ARPM03_000001，限制类别为ZFAMOUNT，取spid_1_amt
B11: =IFERROR(VLOOKUP(C11,'字段信息'!A:C,3,),"") | C11: SPID_2_AMT | D11: =IFERROR(VLOOKUP(C11,'字段信息'!A:C,2,),"") | F11: =B11 | G11: √ | M11: 根据公司+客户+利润中心+三级性质匹配AW_MR9_ARPM03_000001，限制类别为ZFAMOUNT，取spid_2_amt
B12: =IFERROR(VLOOKUP(C12,'字段信息'!A:C,3,),"") | C12: SPID_3_AMT | D12: =IFERROR(VLOOKUP(C12,'字段信息'!A:C,2,),"") | F12: =B12 | G12: √ | M12: 根据公司+客户+利润中心+三级性质匹配AW_MR9_ARPM03_000001，限制类别为ZFAMOUNT，取spid_3_amt
B13: =IFERROR(VLOOKUP(C13,'字段信息'!A:C,3,),"") | C13: SPID_4_AMT | D13: =IFERROR(VLOOKUP(C13,'字段信息'!A:C,2,),"") | F13: =B13 | G13: √ | M13: 根据公司+客户+利润中心+三级性质匹配AW_MR9_ARPM03_000001，限制类别为ZFAMOUNT，取spid_4_amt
B14: =IFERROR(VLOOKUP(C14,'字段信息'!A:C,3,),"") | C14: SPID_5_AMT | D14: =IFERROR(VLOOKUP(C14,'字段信息'!A:C,2,),"") | F14: =B14 | G14: √ | M14: 根据公司+客户+利润中心+三级性质匹配AW_MR9_ARPM03_000001，限制类别为ZFAMOUNT，取spid_5_amt
B15: =IFERROR(VLOOKUP(C15,'字段信息'!A:C,3,),"") | C15: SPID_6_AMT | D15: =IFERROR(VLOOKUP(C15,'字段信息'!A:C,2,),"") | F15: =B15 | G15: √ | M15: 根据公司+客户+利润中心+三级性质匹配AW_MR9_ARPM03_000001，限制类别为ZFAMOUNT，取spid_6_amt
B16: =IFERROR(VLOOKUP(C16,'字段信息'!A:C,3,),"") | C16: SPID_7_AMT | D16: =IFERROR(VLOOKUP(C16,'字段信息'!A:C,2,),"") | F16: =B16 | G16: √ | M16: 根据公司+客户+利润中心+三级性质匹配AW_MR9_ARPM03_000001，限制类别为ZFAMOUNT，取spid_7_amt
B17: =IFERROR(VLOOKUP(C17,'字段信息'!A:C,3,),"") | C17: SPID_8_AMT | D17: =IFERROR(VLOOKUP(C17,'字段信息'!A:C,2,),"") | F17: =B17 | G17: √ | M17: 根据公司+客户+利润中心+三级性质匹配AW_MR9_ARPM03_000001，限制类别为ZFAMOUNT，取spid_8_amt
B18: =IFERROR(VLOOKUP(C18,'字段信息'!A:C,3,),"") | C18: SPID_9_AMT | D18: =IFERROR(VLOOKUP(C18,'字段信息'!A:C,2,),"") | F18: =B18 | G18: √ | M18: 根据公司+客户+利润中心+三级性质匹配AW_MR9_ARPM03_000001，限制类别为ZFAMOUNT，取spid_9_amt
B19: =IFERROR(VLOOKUP(C19,'字段信息'!A:C,3,),"") | C19: SPID_10_AMT | D19: =IFERROR(VLOOKUP(C19,'字段信息'!A:C,2,),"") | F19: =B19 | G19: √ | M19: 根据公司+客户+利润中心+三级性质匹配AW_MR9_ARPM03_000001，限制类别为ZFAMOUNT，取spid_10_amt
B20: =IFERROR(VLOOKUP(C20,'字段信息'!A:C,3,),"") | C20: SPID_11_AMT | D20: =IFERROR(VLOOKUP(C20,'字段信息'!A:C,2,),"") | F20: =B20 | G20: √ | M20: 根据公司+客户+利润中心+三级性质匹配AW_MR9_ARPM03_000001，限制类别为ZFAMOUNT，取spid_11_amt
... B24: =IFERROR(VLOOKUP(C24,'字段信息'!A:C,3,),"") | C24: SPID_15_AMT | D24: =IFERROR(VLOOKUP(C24,'字段信息'!A:C,2,),"") | F24: =B24 | G24: √ | M24: 根据公司+客户+利润中心+三级性质匹配AW_MR9_ARPM03_000001，限制类别为ZFAMOUNT，取spid_15_amt
B25: =IFERROR(VLOOKUP(C25,'字段信息'!A:C,3,),"") | C25: BD_0_AMT | D25: =IFERROR(VLOOKUP(C25,'字段信息'!A:C,2,),"") | F25: =B25 | G25: √ | M25: 合计各账龄段数据之和 | N25: TA
B26: =IFERROR(VLOOKUP(C26,'字段信息'!A:C,3,),"") | C26: BD_1_AMT | D26: =IFERROR(VLOOKUP(C26,'字段信息'!A:C,2,),"") | F26: =B26 | G26: √ | M26: 如果个别认定金额有值，则直接取个别认定金额SPID_1_AMT 如果煤改电金额有值，则直接取煤改电金额spc_c2e_ded_amt 按照优先级匹配坏账计提比例（组织架构01层级下，节点2000排除2910，用2000维护的比例；组织架构10层级下，节点04020，排除6600，用6800的比例；组织架构10层级下，节点03020，排除6000A，用6700的比例） 1、特殊客户级：根据公司+客户+科目匹配1.0form_dati表单，ZS_AR0001_IPT01，COD_CONTO IN ('1122000000','122101F','1460000000','1531000000')，COD_CATEGORIA IN ('$AMOUNT','1ADJ','1REC')，TESTO_14客户不为空 grp_scope为SUB匹配$AMOUNT，GIN匹配1ADJ，GEX匹配1REC 2、特殊性质级：根据公司+科目+三级性质匹配1.0form_dati表单，ZS_AR0001_IPT01，COD_CONTO IN ('1122000000','122101F','1460000000','1531000000')，COD_CATEGORIA IN ('$AMOUNT','1ADJ','1REC')，TESTO_14客户为空，TESTO_2三级性质不为空 grp_scope为SUB匹配$AMOUNT，GIN匹配1ADJ，GEX匹配1REC，nature_l3_name和TESTO_2匹配 3、通用级：根据公司+科目匹配1.0form_dati表单，ZS_AR0001_IPT01，COD_CONTO IN ('1122000000','122101F','1460000000','1531000000')，COD_CATEGORIA IN ('$AMOUNT','1ADJ','1REC')，TESTO_14客户为空，TESTO_2三级性质为空 grp_scope为SUB匹配$AMOUNT，GIN匹配1ADJ，GEX匹配1REC 根据bd_base_1_amt*IMPORTO_06 根据保障天数计算比例 保障天数>0且<=30，bd_base_1_amt*IMPORTO_06 * ins_uncov_rate | N26: TA
B27: =IFERROR(VLOOKUP(C27,'字段信息'!A:C,3,),"") | C27: BD_2_AMT | D27: =IFERROR(VLOOKUP(C27,'字段信息'!A:C,2,),"") | F27: =B27 | G27: √ | M27: 按照优先级匹配坏账计提比例 1、特殊客户级：根据公司+客户+科目匹配1.0form_dati表单，ZS_AR0001_IPT01，COD_CONTO IN ('1122000000','122101F','1460000000','1531000000')，COD_CATEGORIA IN ('$AMOUNT','1ADJ','1REC')，TESTO_14客户不为空 grp_scope为SUB匹配$AMOUNT，GIN匹配1ADJ，GEX匹配1REC 2、特殊性质级：根据公司+科目+三级性质匹配1.0form_dati表单，ZS_AR0001_IPT01，COD_CONTO IN ('1122000000','122101F','1460000000','1531000000')，COD_CATEGORIA IN ('$AMOUNT','1ADJ','1REC')，TESTO_14客户为空，TESTO_2三级性质不为空 grp_scope为SUB匹配$AMOUNT，GIN匹配1ADJ，GEX匹配1REC，nature_l3_name和TESTO_2匹配 3、通用级：根据公司+科目匹配1.0form_dati表单，ZS_AR0001_IPT01，COD_CONTO IN ('1122000000','122101F','1460000000','1531000000')，COD_CATEGORIA IN ('$AMOUNT','1ADJ','1REC')，TESTO_14客户为空，TESTO_2三级性质为空 grp_scope为SUB匹配$AMOUNT，GIN匹配1ADJ，GEX匹配1REC 根据bd_base_2_amt*IMPORTO_07 根据保障天数计算比例 保障天数>30且<=90，bd_base_2_amt*IMPORTO_07 * ins_uncov_rate | N27: TA
B28: =IFERROR(VLOOKUP(C28,'字段信息'!A:C,3,),"") | C28: BD_3_AMT | D28: =IFERROR(VLOOKUP(C28,'字段信息'!A:C,2,),"") | F28: =B28 | G28: √ | M28: 按照优先级匹配坏账计提比例 1、特殊客户级：根据公司+客户+科目匹配1.0form_dati表单，ZS_AR0001_IPT01，COD_CONTO IN ('1122000000','122101F','1460000000','1531000000')，COD_CATEGORIA IN ('$AMOUNT','1ADJ','1REC')，TESTO_14客户不为空 grp_scope为SUB匹配$AMOUNT，GIN匹配1ADJ，GEX匹配1REC 2、特殊性质级：根据公司+科目+三级性质匹配1.0form_dati表单，ZS_AR0001_IPT01，COD_CONTO IN ('1122000000','122101F','1460000000','1531000000')，COD_CATEGORIA IN ('$AMOUNT','1ADJ','1REC')，TESTO_14客户为空，TESTO_2三级性质不为空 grp_scope为SUB匹配$AMOUNT，GIN匹配1ADJ，GEX匹配1REC，nature_l3_name和TESTO_2匹配 3、通用级：根据公司+科目匹配1.0form_dati表单，ZS_AR0001_IPT01，COD_CONTO IN ('1122000000','122101F','1460000000','1531000000')，COD_CATEGORIA IN ('$AMOUNT','1ADJ','1REC')，TESTO_14客户为空，TESTO_2三级性质为空 grp_scope为SUB匹配$AMOUNT，GIN匹配1ADJ，GEX匹配1REC 根据bd_base_3_amt*IMPORTO_08 根据保障天数计算比例 保障天数>90且<=180，bd_base_3_amt*IMPORTO_08* ins_uncov_rate | N28: TA
B29: =IFERROR(VLOOKUP(C29,'字段信息'!A:C,3,),"") | C29: BD_4_AMT | D29: =IFERROR(VLOOKUP(C29,'字段信息'!A:C,2,),"") | F29: =B29 | G29: √ | M29: 按照优先级匹配坏账计提比例 1、特殊客户级：根据公司+客户+科目匹配1.0form_dati表单，ZS_AR0001_IPT01，COD_CONTO IN ('1122000000','122101F','1460000000','1531000000')，COD_CATEGORIA IN ('$AMOUNT','1ADJ','1REC')，TESTO_14客户不为空 grp_scope为SUB匹配$AMOUNT，GIN匹配1ADJ，GEX匹配1REC 2、特殊性质级：根据公司+科目+三级性质匹配1.0form_dati表单，ZS_AR0001_IPT01，COD_CONTO IN ('1122000000','122101F','1460000000','1531000000')，COD_CATEGORIA IN ('$AMOUNT','1ADJ','1REC')，TESTO_14客户为空，TESTO_2三级性质不为空 grp_scope为SUB匹配$AMOUNT，GIN匹配1ADJ，GEX匹配1REC，nature_l3_name和TESTO_2匹配 3、通用级：根据公司+科目匹配1.0form_dati表单，ZS_AR0001_IPT01，COD_CONTO IN ('1122000000','122101F','1460000000','1531000000')，COD_CATEGORIA IN ('$AMOUNT','1ADJ','1REC')，TESTO_14客户为空，TESTO_2三级性质为空 grp_scope为SUB匹配$AMOUNT，GIN匹配1ADJ，GEX匹配1REC 根据bd_base_4_amt*IMPORTO_09 根据保障天数计算比例 保障天数>180，bd_base_4_amt*IMPORTO_09* ins_uncov_rate | N29: TA
